Workbook

Sheet Risk_Inputs
A1: Date | B1: Intercept | C1: IV | D1: RV10 | E1: RV20 | F1: VRP10 | G1: VRP20 | H1: SPREAD20 | I1: RV_TREND | J1: IV_Ratio | K1: Str_Ratio | L1: Norm_OG | M1: Adj_IV_Chg | N1: Fixed_IDV | O1: u_range_bps | P1: str_range_pct | Q1: str_chg_abs | R1: spread_pct | S1: CW Stage=09:17 | T1: CW Stage=09:18 | U1: CW Stage=09:19 | V1: CW Stage=09:20+ | W1: CW DTE=2.0 | X1: CW DTE=3.0 | Y1: CW DTE=4.0 | Z1: CW DTE=5.0 | AA1: CW Weekday=1 | AB1: CW Weekday=2 | AC1: CW Weekday=3 | AD1: CW Weekday=4 | AE1: CW Weekday=5 | AF1: CW Weekday=6 | AG1: CW Event | AH1: NW | AI1: Prev_flat_DD | AJ1: Prev_flat_loss_streak
A2: 2021-01-01 | B2: 1 | C2: 0.18718514 | D2: 0.94760849 | E2: 0.039149468 | F2: -1.0050402 | G2: -0.092877302 | H2: 0.14982471 | I2: -1.0717408 | J2: 1.6719678 | K2: -0.25362685 | L2: 0.42048401 | M2: -0.77790542 | N2: -0.5932807 | O2: -0.58013725 | P2: -0.64546399 | Q2: -0.43823592 | R2: 0.43592499 | S2: 1 | T2: 0 | U2: 0 | V2: 0 | W2: 0 | X2: 0 | Y2: 0 | Z2: 1 | AA2: 0 | AB2: 0 | AC2: 0 | AD2: 1 | AE2: 0 | AF2: 0 | AG2: 0 | AH2: 0 | AI2: 0 | AJ2: 0
A3: 2021-01-04 | B3: 1 | C3: 0.4213145 | D3: 0.94521197 | E3: 0.037238942 | F3: -0.8698864 | G3: 0.13092832 | H3: 0.39282174 | I3: -1.4325015 | J3: 3 | K3: -0.73713791 | L3: 1.0636738 | M3: -1.4118135 | N3: -1.0186274 | O3: 2.1394967 | P3: -0.26214813 | Q3: 0.011743564 | R3: 0.53527339 | S3: 0 | T3: 0 | U3: 0 | V3: 1 | W3: 0 | X3: 0 | Y3: 1 | Z3: 0 | AA3: 0 | AB3: 0 | AC3: 0 | AD3: 0 | AE3: 0 | AF3: 0 | AG3: 0 | AH3: 0 | AI3: 0 | AJ3: 0
A4: 2021-01-05 | B4: 1 | C4: -0.017580683 | D4: 0.97100109 | E4: 0.027836102 | F4: -1.1354633 | G4: -0.27336135 | H4: -0.04850793 | I4: -1.684403 | J4: -0.56133784 | K4: -0.90046638 | L4: -0.60832159 | M4: -1.005994 | N4: 0.2841252 | O4: -0.43226081 | P4: -0.24811971 | Q4: 0.048974769 | R4: 0.97268922 | S4: 1 | T4: 0 | U4: 0 | V4: 0 | W4: 0 | X4: 1 | Y4: 0 | Z4: 0 | AA4: 1 | AB4: 0 | AC4: 0 | AD4: 0 | AE4: 0 | AF4: 0 | AG4: 0 | AH4: 0 | AI4: 0 | AJ4: 0
A5: 2021-01-06 | B5: 1 | C5: 0.039521971 | D5: -1.1307143 | E5: 0.019571149 | F5: 2.7347344 | G5: -0.20936183 | H5: 0.019279901 | I5: -1.6720652 | J5: 0.52653827 | K5: -0.24048233 | L5: 0.30957935 | M5: 1.161994 | N5: -0.25998975 | O5: -0.36223045 | P5: -0.61115944 | Q5: -0.33020527 | R5: 0.44812766 | S5: 1 | T5: 0 | U5: 0 | V5: 0 | W5: 1 | X5: 0 | Y5: 0 | Z5: 0 | AA5: 0 | AB5: 1 | AC5: 0 | AD5: 0 | AE5: 0 | AF5: 0 | AG5: 0 | AH5: 0 | AI5: 0.14245693 | AJ5: 0.33333333
A6: 2021-01-07 | B6: 1 | C6: -0.66124481 | D6: -1.0464756 | E6: 0.036949141 | F6: 1.1588054 | G6: -0.89280935 | H6: -0.72076962 | I6: -1.4375015 | J6: -1.6152319 | K6: 3 | L6: 0.98253858 | M6: 1.2872282 | N6: 0.30035824 | O6: -0.66219979 | P6: -0.40051294 | Q6: -0.47320354 | R6: 0.39961899 | S6: 0 | T6: 1 | U6: 0 | V6: 0 | W6: 0 | X6: 0 | Y6: 0 | Z6: 0 | AA6: 0 | AB6: 0 | AC6: 1 | AD6: 0 | AE6: 0 | AF6: 0 | AG6: 0 | AH6: 0 | AI6: 0.74654689 | AJ6: 0.66666667
A7: 2021-01-11 | B7: 1 | C7: 0.15232608 | D7: -1.0379561 | E7: 0.042482068 | F7: 2.4350316 | G7: -0.12985861 | H7: 0.11031448 | I7: -0.90054156 | J7: 0.71727518 | K7: -0.19795133 | L7: 1.0745783 | M7: -0.84480991 | N7: -0.24868827 | O7: -0.28004971 | P7: -0.39417293 | Q7: -0.17310025 | R7: -0.0010337041 | S7: 0 | T7: 0 | U7: 1 | V7: 0 | W7: 0 | X7: 0 | Y7: 1 | Z7: 0 | AA7: 0 | AB7: 0 | AC7: 0 | AD7: 0 | AE7: 0 | AF7: 0 | AG7: 0 | AH7: 0 | AI7: 0.20748762 | AJ7: 0
A8: 2021-01-12 | B8: 1 | C8: 0.29834864 | D8: -1.0647775 | E8: 0.05943708 | F8: 2.8107897 | G8: -0.013258176 | H8: 0.24203782 | I8: -0.84636081 | J8: 0.24550697 | K8: -0.35500301 | L8: -0.089688685 | M8: 0.29647818 | N8: 0.11295913 | O8: -0.63507095 | P8: -0.59405986 | Q8: -0.3432021 | R8: 0.42416802 | S8: 1 | T8: 0 | U8: 0 | V8: 0 | W8: 0 | X8: 1 | Y8: 0 | Z8: 0 | AA8: 1 | AB8: 0 | AC8: 0 | AD8: 0 | AE8: 0 | AF8: 0 | AG8: 0 | AH8: 0 | AI8: 0.71311177 | AJ8: 0.33333333
A9: 2021-01-13 | B9: 1 | C9: -0.10015267 | D9: -1.0311521 | E9: 0.072387111 | F9: 1.9983806 | G9: -0.40122041 | H9: -0.18215454 | I9: -0.81908595 | J9: 0.97149195 | K9: 0.60590011 | L9: 0.5400705 | M9: -0.086137758 | N9: -0.5645133 | O9: -0.80595558 | P9: -0.42347662 | Q9: -0.55533119 | R9: 0.49836622 | S9: 1 | T9: 0 | U9: 0 | V9: 0 | W9: 1 | X9: 0 | Y9: 0 | Z9: 0 | AA9: 0 | AB9: 1 | AC9: 0 | AD9: 0 | AE9: 0 | AF9: 0 | AG9: 0 | AH9: 0 | AI9: 0.46717269 | AJ9: 0
A10: 2021-01-14 | B10: 1 | C10: -0.50074395 | D10: -0.99968788 | E10: 0.074897006 | F10: 1.2389421 | G10: -0.77747164 | H10: -0.59708884 | I10: -1.0300787 | J10: -1.0018753 | K10: 0.54277591 | L10: -0.17494 | M10: -1.4548652 | N10: 0.040218691 | O10: -0.61020694 | P10: -0.31813007 | Q10: -0.26178147 | R10: 1.6619456 | S10: 1 | T10: 0 | U10: 0 | V10: 0 | W10: 0 | X10: 0 | Y10: 0 | Z10: 0 | AA10: 0 | AB10: 0 | AC10: 1 | AD10: 0 | AE10: 0 | AF10: 0 | AG10: 0 | AH10: 0 | AI10: 0.18321027 | AJ10: 0
A11: 2021-01-15 | B11: 1 | C11: 0.18964253 | D11: -1.0585658 | E11: 0.063015129 | F11: 2.5993652 | G11: -0.11952356 | H11: 0.12627385 | I11: -1.1342126 | J11: 1.2807866 | K11: -0.42911214 | L11: -0.26668138 | M11: -0.5199406 | N11: -0.45047108 | O11: 0.096250757 | P11: -0.58678842 | Q11: -0.50915038 | R11: 0.63409106 | S11: 1 | T11: 0 | U11: 0 | V11: 0 | W11: 0 | X11: 0 | Y11: 0 | Z11: 1 | AA11: 0 | AB11: 0 | AC11: 0 | AD11: 1 | AE11: 0 | AF11: 0 | AG11: 0 | AH11: 0 | AI11: 0 | AJ11: 0
A12: 2021-01-18 | B12: 1 | C12: 1.2503377 | D12: -0.49719404 | E12: 0.22307041 | F12: 1.8393936 | G12: 0.63542223 | H12: 1.0427828 | I12: -0.32497338 | J12: 0.11801854 | K12: -0.37828597 | L12: -0.25608891 | M12: 1.7678678 | N12: 1.0787221 | O12: -0.71998534 | P12: -0.69446716 | Q12: -0.5809523 | R12: -0.091305086 | S12: 0 | T12: 1 | U12: 0 | V12: 0 | W12: 0 | X12: 0 | Y12: 1 | Z12: 0 | AA12: 0 | AB12: 0 | AC12: 0 | AD12: 0 | AE12: 0 | AF12: 0 | AG12: 0 | AH12: 0 | AI12: 0.60178525 | AJ12: 0.33333333
A13: 2021-01-19 | B13: 1 | C13: 0.6793239 | D13: -0.23961241 | E13: 0.34732154 | F13: 0.65946653 | G13: -0.014239261 | H13: 0.31945707 | I13: -0.33196196 | J13: -0.68033172 | K13: 0.4101082 | L13: 1.0504165 | M13: -0.30550835 | N13: 1.1253664 | O13: -0.26075248 | P13: 0.017957625 | Q13: -0.17448046 | R13: 2.4712854 | S13: 0 | T13: 0 | U13: 0 | V13: 0 | W13: 0 | X13: 1 | Y13: 0 | Z13: 0 | AA13: 1 | AB13: 0 | AC13: 0 | AD13: 0 | AE13: 0 | AF13: 0 | AG13: 0 | AH13: 0 | AI13: 0.44873718 | AJ13: 0
... A800: 2026-10-13 | B800: 1 | C800: -0.28020812 | D800: 0.29353485 | E800: -0.20312557 | F800: -0.82475473 | G800: -0.25301037 | H800: -0.066355124 | I800: 1.5123442 | J800: -0.6943052 | K800: -0.056649271 | L800: 0.14234687 | M800: 0.62552895 | N800: 0.08727395 | O800: -0.31918533 | P800: -0.33517661 | Q800: -0.30094485 | R800: -0.24881362 | S800: 1 | T800: 0 | U800: 0 | V800: 0 | W800: 0 | X800: 0 | Y800: 0 | Z800: 0 | AA800: 1 | AB800: 0 | AC800: 0 | AD800: 0 | AE800: 0 | AF800: 0 | AG800: 0 | AH800: 0 | AI800: 0.95973597 | AJ800: 0

Sheet Risk_Coefs
A1: Model | B1: Intercept | C1: IV | D1: RV10 | E1: RV20 | F1: VRP10 | G1: VRP20 | H1: SPREAD20 | I1: RV_TREND | J1: IV_Ratio | K1: Str_Ratio | L1: Norm_OG | M1: Adj_IV_Chg | N1: Fixed_IDV | O1: u_range_bps | P1: str_range_pct | Q1: str_chg_abs | R1: spread_pct | S1: CW Stage=09:17 | T1: CW Stage=09:18 | U1: CW Stage=09:19 | V1: CW Stage=09:20+ | W1: CW DTE=2.0 | X1: CW DTE=3.0 | Y1: CW DTE=4.0 | Z1: CW DTE=5.0 | AA1: CW Weekday=1 | AB1: CW Weekday=2 | AC1: CW Weekday=3 | AD1: CW Weekday=4 | AE1: CW Weekday=5 | AF1: CW Weekday=6 | AG1: CW Event | AH1: NW | AI1: Prev_flat_DD | AJ1: Prev_flat_loss_streak
A2: Logistic | B2: -0.825285 | C2: 0.050052271 | D2: 0.043475306 | E2: 0.11199904 | F2: 0.10016707 | G2: 0.091166772 | H2: -0.016447586 | I2: 0.067826429 | J2: 0.042447783 | K2: -0.023891896 | L2: 0.01413694 | M2: 0.012858494 | N2: -0.029499704 | O2: -0.15560095 | P2: -0.084096632 | Q2: -0.11511118 | R2: -0.11388731 | S2: -0.11255641 | T2: 0.022458537 | U2: -0.0075626854 | V2: 0.18458601 | W2: 0.0027184808 | X2: -0.1598374 | Y2: -0.0082355465 | Z2: -0.24094798 | AA2: -0.067528763 | AB2: -0.011447837 | AC2: 0.17494556 | AD2: -0.11277511 | AE2: 0.0075608231 | AF2: 0.023146783 | AG2: 0.046548159 | AH2: 0.167332 | AI2: -0.1304963 | AJ2: 0.0071564013
A3: Downside | B3: 8.9258375 | C3: 0.84123462 | D3: 1.1260159 | E3: 0.73811106 | F3: 0.96900885 | G3: 1.2820613 | H3: 0.1121499 | I3: 0.33149545 | J3: 0.0053762573 | K3: -0.15083915 | L3: 1.1129773 | M3: 0.50988288 | N3: -1.0223048 | O3: -0.51833687 | P3: -0.52489903 | Q3: -0.77538854 | R3: -0.53940361 | S3: -0.31224646 | T3: -1.0022299 | U3: 0.32000388 | V3: 2.3929591 | W3: -0.37432944 | X3: -1.7825546 | Y3: -1.0906223 | Z3: -1.8918557 | AA3: -1.1385839 | AB3: 0.14007409 | AC3: 2.0511637 | AD3: 0.18068036 | AE3: -0.12158081 | AF3: -0.020436761 | AG3: -2.1693747 | AH3: 1.5039026 | AI3: -1.5177996 | AJ3: 0.83974704

Sheet Risk_Rank_Keys
A1: Date | B1: U_order_key | C1: Straddle_order_key | D1: Spread_order_key | E1: U_raw_17digits | F1: Straddle_raw_17digits | G1: Spread_raw_17digits
A2: 2021-01-01 | B2: 210 | C2: 87 | D2: 541 | E2: 6.7846238997304011 | F2: 1.4535454724022965 | G2: 0.31428010214103208
A3: 2021-01-04 | B3: 683 | C3: 396 | D3: 563 | E3: 39.395248997260289 | F3: 3.6389083275017535 | G3: 0.3265686960578506
A4: 2021-01-05 | B4: 304 | C4: 403 | D4: 617 | E4: 8.5577827885583311 | F4: 3.7188872620790758 | G4: 0.38067349926793892
A5: 2021-01-06 | B5: 336 | C5: 125 | D5: 546 | E5: 9.3975038540327365 | F5: 1.6491228070175601 | G5: 0.31578947368421251
A6: 2021-01-07 | B6: 150 | C6: 322 | D6: 539 | E6: 5.8006271708420538 | F6: 2.8500619578686459 | G6: 0.30978934324658791
A7: 2021-01-11 | B7: 377 | C7: 327 | D7: 452 | E7: 10.382917842991466 | F7: 2.8862077123255241 | G7: 0.260231842914602
A8: 2021-01-12 | B8: 167 | C8: 144 | D8: 540 | E8: 6.1259240800733474 | F8: 1.7466110531803931 | G8: 0.31282586027112019
A9: 2021-01-13 | B9: 54 | C9: 306 | D9: 557 | E9: 4.0768782760634004 | F9: 2.7191413237924742 | G9: 0.3220035778175333
A10: 2021-01-14 | B10: 193 | C10: 366 | D10: 666 | E10: 6.4240637871747959 | F10: 3.3197437390797999 | G10: 0.46592894583575839
A11: 2021-01-15 | B11: 505 | C11: 151 | D11: 579 | E11: 14.895066822351504 | F11: 1.7880670054583101 | G11: 0.33879164313947141
A12: 2021-01-18 | B12: 100 | C12: 45 | D12: 414 | E12: 5.10773143756479 | F12: 1.1741682974559726 | G12: 0.2490660024906661
A13: 2021-01-19 | B13: 383 | C13: 505 | D13: 690 | E13: 10.614307390343289 | F13: 5.2358490566037839 | G13: 0.56603773584906458
A14: 2021-01-20 | B14: 295 | C14: 575 | D14: 671 | E14: 8.4278745932260524 | F14: 7.4086603518268044 | G14: 0.47361299052773248
A15: 2021-01-21
A16: 2021-01-22 | B16: 253 | C16: 123 | D16: 510 | E16: 7.4583317507392879 | F16: 1.6354746248524583 | G16: 0.28662957342775058
A17: 2021-01-25 | B17: 531 | C17: 235 | D17: 554 | E17: 16.728850325378602 | F17: 2.268620758883749 | G17: 0.32122063842601772
A18: 2021-01-27 | B18: 675 | C18: 627 | D18: 713 | E18: 37.435211680069074 | F18: 9.6825396825396712 | G18: 1.3756613756613727
A19: 2021-01-28 | B19: 610 | C19: 481 | D19: 663 | E19: 24.560100115768659 | F19: 4.7879616963064295 | G19: 0.4559963520291837
A20: 2021-01-29 | B20: 710 | C20: 590 | D20: 556 | E20: 59.808182765185535 | F20: 8.0519182173213899 | G20: 0.32161727544222501
A21: 2021-02-01 | B21: 405 | C21: 119 | D21: 660 | E21: 11.383308360368233 | F21: 1.623073330219521 | G21: 0.45539467538533129
A22: 2021-02-03 | B22: 669 | C22: 350 | D22: 700 | E22: 35.667553800269026 | F22: 3.1544136352073204 | G22: 0.6359704909692262
A23: 2021-02-04 | B23: 624 | C23: 649 | D23: 621 | E23: 26.100975816715422 | F23: 12.252811167119049 | G23: 0.387747188832892
A24: 2021-02-05 | B24: 553 | C24: 603 | D24: 699 | E24: 18.371403521688112 | F24: 8.5873433390066527 | G24: 0.61890762803651556
A25: 2021-02-08 | B25: 635 | C25: 534 | D25: 684 | E25: 27.113598001036213 | F25: 6.0065213660545922 | G25: 0.5148446885189536
A26: 2021-02-09 | B26: 457 | C26: 619 | D26: 633 | E26: 12.9522550801258 | F26: 9.4184027777777715 | G26: 0.41232638888889012
A27: 2021-02-10
A28: 2021-02-11 | B28: 370 | C28: 482 | D28: 619 | E28: 10.214775606584974 | F28: 4.7881355932203444 | G28: 0.3813559322034043
A29: 2021-02-12 | B29: 156 | C29: 85 | D29: 680 | E29: 5.8863571341654763 | F29: 1.4448257178977786 | G29: 0.50568900126421423
A30: 2021-02-16 | B30: 240 | C30: 241 | D30: 530 | E30: 7.2777366239104371 | F30: 2.2838499184339405 | G30: 0.29907558455682282
A31: 2021-02-17 | B31: 329 | C31: 252 | D31: 673 | E31: 9.2322500171879405 | F31: 2.3499523658304518 | G31: 0.47634169577643698
A32: 2021-02-18 | B32: 468 | C32: 475 | D32: 650 | E32: 13.27776828322448 | F32: 4.6783625730994132 | G32: 0.4385964912280661
A33: 2021-02-19 | B33: 612 | C33: 422 | D33: 711 | E33: 24.591662097271204 | F33: 3.9421587192287793 | G33: 0.91237734549836658
A34: 2021-02-22 | B34: 605 | C34: 460 | D34: 698 | E34: 23.928002112081369 | F34: 4.4529019980970457 | G34: 0.60894386298763414
A35: 2021-02-23 | B35: 338 | C35: 132 | D35: 640 | E35: 9.4079469882634328 | F35: 1.6845651716150771 | G35: 0.42114129290376928
A36: 2021-02-24 | B36: 552 | C36: 635 | D36: 654 | E36: 18.363758562400179 | F36: 10.077734591893396 | G36: 0.44419766796224941
A37: 2021-02-25 | B37: 650 | C37: 699 | D37: 667 | E37: 30.73736591692688 | F37: 23.69158878504674 | G37: 0.46728971962616161
A38: 2021-02-26 | B38: 562 | C38: 377 | D38: 629 | E38: 19.738240563602684 | F38: 3.4904493610004241 | G38: 0.39851587192524851
A39: 2021-03-02 | B39: 571 | C39: 560 | D39: 636 | E39: 20.563695117051477 | F39: 6.883468834688351 | G39: 0.41553748870822238
A40: 2021-03-03
A41: 2021-03-04 | B41: 489 | C41: 518 | D41: 674 | E41: 14.249035948091596 | F41: 5.5443140428976072 | G41: 0.48563334682314963
A42: 2021-03-05 | B42: 701 | C42: 632 | D42: 705 | E42: 52.152024154621465 | F42: 9.9749202006383939 | G42: 0.75239398084814935
A43: 2021-03-08 | B43: 662 | C43: 365 | D43: 451 | E43: 34.625577647857881 | F43: 3.3057851239669631 | G43: 0.26017753290480389
A44: 2021-03-09 | B44: 420 | C44: 313 | D44: 516 | E44: 11.663082698546001 | F44: 2.7582869586257042 | G44: 0.29034599564481411
A45: 2021-03-10 | B45: 70 | C45: 357 | D45: 609 | E45: 4.4736400627632564 | F45: 3.2189973614775691 | G45: 0.36939313984168259
A46: 2021-03-16 | B46: 451 | C46: 273 | D46: 611 | E46: 12.804097311140049 | F46: 2.4607113316790685 | G46: 0.37220843672456222
A47: 2021-03-17 | B47: 703 | C47: 628 | D47: 658 | E47: 53.071322352057287 | F47: 9.8265895953757294 | G47: 0.45237496858506732
A48: 2021-03-18 | B48: 685 | C48: 687 | D48: 613 | E48: 40.447243458053599 | F48: 19.061032863849764 | G48: 0.37558685446009921
A49: 2021-03-19 | B49: 582 | C49: 512 | D49: 471 | E49: 21.081032591070123 | F49: 5.3749680061428213 | G49: 0.2687484003071367
A50: 2021-03-22 | B50: 697 | C50: 574 | D50: 648 | E50: 48.012630962873473 | F50: 7.3976833976833936 | G50: 0.43243243243243418
A51: 2021-03-23 | B51: 661 | C51: 665 | D51: 592 | E51: 34.467814239474421 | F51: 14.920757634325458 | G51: 0.3478933127174299
A52: 2021-03-24 | B52: 606 | C52: 680 | D52: 534 | E52: 24.055320460913489 | F52: 17.182389937106919 | G52: 0.3018867924528344
... A80: 2021-05-24 | B80: 456 | C80: 215 | D80: 616 | E80: 12.946387497864652 | F80: 2.1262309758281108 | G80: 0.38048343777977101
A81: 2021-05-26
A82: 2021-05-27 | B82: 519 | C82: 705 | D82: 685 | E82: 15.779517989631554 | F82: 28.497409326424872 | G82: 0.51813471502590192
A83: 2021-05-28 | B83: 184 | C83: 244 | D83: 475 | E83: 6.3524165110979904 | F83: 2.306733167082299 | G83: 0.27015793848711789
A84: 2021-06-01 | B84: 61 | C84: 303 | D84: 628 | E84: 4.2348411934554786 | F84: 2.6654411764706025 | G84: 0.39828431372549372
A85: 2021-06-02 | B85: 310 | C85: 416 | D85: 615 | E85: 8.648155113824977 | F85: 3.87096774193548 | G85: 0.37950664136622392
A86: 2021-06-03
A87: 2021-06-04 | B87: 578 | C87: 605 | D87: 638 | E87: 20.813943110680221 | F87: 8.75494940607126 | G87: 0.4179498460184789
A88: 2021-06-07 | B88: 175 | C88: 64 | D88: 60 | E88: 6.2351676178473854 | F88: 1.3245033112582971 | G88: 0.13796909492273729
A89: 2021-06-08 | B89: 157 | C89: 148 | D89: 604 | E89: 5.9093768466809582 | F89: 1.7647058823529338 | G89: 0.35947712418301397
A90: 2021-06-09 | B90: 142 | C90: 289 | D90: 456 | E90: 5.7460682290041669 | F90: 2.5719267654751432 | G90: 0.26155187445510403
A91: 2021-06-10 | B91: 226 | C91: 465 | D91: 607 | E91: 7.01660383616752 | F91: 4.5454545454545459 | G91: 0.36363636363637741
A92: 2021-06-11 | B92: 151 | C92: 55 | D92: 316 | E92: 5.8534486304512212 | F92: 1.2275963663147558 | G92: 0.2209673459366574
A93: 2021-06-14 | B93: 608 | C93: 540 | D93: 578 | E93: 24.36115734629124 | F93: 6.2662506500259925 | G93: 0.33801352054081718
A94: 2021-06-15 | B94: 96 | C94: 46 | D94: 493 | E94: 5.0770385413454413 | F94: 1.1830201809324905 | G94: 0.27835768963118002
A95: 2021-06-16 | B95: 245 | C95: 277 | D95: 512 | E95: 7.3566557211414718 | F95: 2.4650780608052592 | G95: 0.2875924404272755
A96: 2021-06-17 | B96: 417 | C96: 553 | D96: 675 | E96: 11.639550235023243 | F96: 6.6192560175054664 | G96: 0.49234135667396361
A97: 2021-06-18 | B97: 527 | C97: 486 | D97: 506 | E97: 16.485930829654496 | F97: 4.826144784343537 | G97: 0.28500855025650768
A98: 2021-06-21 | B98: 387 | C98: 181 | D98: 449 | E98: 10.859337741515771 | F98: 1.9259900454447163 | G98: 0.25968405107120041
... A109: 2021-07-28 | B109: 43 | C109: 406 | D109: 566 | E109: 3.759482338398942 | F109: 3.7813399095766496 | G109: 0.32881216605014851
A110: 2021-07-29
A111: 2021-08-03 | B111: 4 | C111: 16 | D111: 170 | E111: 2.004033116646569 | F111: 0.92867756315009542 | G111: 0.18573551263000959
A112: 2021-08-04 | B112: 659 | C112: 693 | D112: 695 | E112: 33.745642987136499 | F112: 21.806167400881041 | G112: 0.58737151248164787
A113: 2021-08-05
A114: 2021-08-11 | B114: 260 | C114: 492 | D114: 439 | E114: 7.6155147688792333 | F114: 4.890604890604906 | G114: 0.25740025740026717
A115: 2021-08-12
A116: 2021-08-16 | B116: 300 | C116: 190 | D116: 187 | E116: 8.5192820761576957 | F116: 1.980830670926514 | G116: 0.19169329073482241
A117: 2021-08-17 | B117: 418 | C117: 592 | D117: 531 | E117: 11.651308124137191 | F117: 8.0796692972566913 | G117: 0.30063885757234549
A118: 2021-08-30 | B118: 238 | C118: 86 | D118: 278 | E118: 7.2375925920418984 | F118: 1.4523449319213519 | G118: 0.21180030257185739
A119: 2021-08-31 | B119: 222 | C119: 425 | D119: 358 | E119: 6.9609332369810026 | F119: 3.9737274220032921 | G119: 0.22988505747126989
A120: 2021-09-02
A121: 2021-09-03 | B121: 498 | C121: 587 | D121: 622 | E121: 14.548378419807673 | F121: 7.9282782458414438 | G121: 0.38885288399221918
A122: 2021-09-06 | B122: 218 | C122: 476 | D122: 498 | E122: 6.9019661976205464 | F122: 4.6926804386636007 | G122: 0.28054067839837349
A123: 2021-09-07 | B123: 124 | C123: 43 | D123: 349 | E123: 5.549868298462977 | F123: 1.1707595659623136 | G123: 0.22844089091947781
A124: 2021-09-08 | B124: 373 | C124: 355 | D124: 576 | E124: 10.31521927044399 | F124: 3.2089552238806052 | G124: 0.33582089552239019
A125: 2021-09-09
A126: 2021-09-13 | B126: 586 | C126: 423 | D126: 533 | E126: 21.583626453214499 | F126: 3.946706887883356 | G126: 0.30165912518854121
A127: 2021-09-22
A128: 2021-09-23
A129: 2021-09-24 | B129: 715 | C129: 588 | D129: 447 | E129: 69.572117507027073 | F129: 7.9473879214524077 | G129: 0.25935531678398988
A130: 2021-09-27 | B130: 321 | C130: 25 | D130: 472 | E130: 9.0414399330267763 | F130: 1.054284432480918 | G130: 0.26917900403768252
A131: 2021-09-28 | B131: 364 | C131: 197 | D131: 154 | E131: 10.034043076508651 | F131: 2.0207253886010541 | G131: 0.18134715025907169
A132: 2021-09-29 | B132: 642 | C132: 647 | D132: 644 | E132: 28.146418063595288 | F132: 11.673261729790845 | G132: 0.42396834369700392
A133: 2021-09-30 | B133: 343 | C133: 479 | D133: 496 | E133: 9.5242670977563897 | F133: 4.7486033519553015 | G133: 0.2793296089385448
A134: 2021-10-01 | B134: 508 | C134: 68 | D134: 400 | E134: 15.153117968452923 | F134: 1.3371827989667158 | G134: 0.24312414526667159
A135: 2021-10-05 | B135: 524 | C135: 301 | D135: 583 | E135: 16.094025376425346 | F135: 2.6571954748750386 | G135: 0.34201525914232639
A136: 2021-10-06 | B136: 379 | C136: 129 | D136: 555 | E136: 10.479742433708395 | F136: 1.6779721528025662 | G136: 0.32131381649410101
A137: 2021-10-07
...

Sheet Risk_Excel_Formulas
A1: Date | B1: Leg | C1: Net_PnL | D1: Logit_formula | E1: Probability_formula | F1: Downside_raw_formula | G1: Downside_formula | H1: Loss_rank_formula | I1: Downside_rank_formula | J1: U_range | K1: Str_range | L1: Spread | M1: U_rank_formula | N1: Str_rank_formula | O1: Spread_rank_formula | P1: Instability_formula | Q1: Risk_formula | R1: Threshold_formula | S1: Dicey_formula | T1: Saved_probability | U1: Saved_downside | V1: Saved_risk | W1: Risk_error_formula
A2: 2021-01-01 | B2: CW | C2: 34.787837 | D2: =SUMPRODUCT(Risk_Inputs!B2:AJ2,Risk_Coefs!$B$2:$AJ$2) -> -1.185084 | E2: =1/(1+EXP(-MAX(-25,MIN(25,D2)))) -> 0.23413931 | F2: =SUMPRODUCT(Risk_Inputs!B2:AJ2,Risk_Coefs!$B$3:$AJ$3) -> 8.1936412 | G2: =MAX(0,F2) -> 8.1936412 | H2: =(SUMPRODUCT(--ISNUMBER($E$2:$E$800),--($E$2:$E$800<E2))+(SUMPRODUCT(--ISNUMBER($E$2:$E$800),--($E$2:$E$800=E2))+1)/2)/COUNT($E$2:$E$800) -> 0.19524406 | I2: =(SUMPRODUCT(--ISNUMBER($G$2:$G$800),--($G$2:$G$800<G2))+(SUMPRODUCT(--ISNUMBER($G$2:$G$800),--($G$2:$G$800=G2))+1)/2)/COUNT($G$2:$G$800) -> 0.56195244 | J2: 6.7846239 | K2: 1.4535455 | L2: 0.3142801 | M2: =IF(OR(B2="NW",COUNT(Risk_Rank_Keys!B2)=0),0.5,(SUMPRODUCT(--ISNUMBER(Risk_Rank_Keys!$B$2:$B$800),--(Risk_Rank_Keys!$B$2:$B$800<Risk_Rank_Keys!B2))+(SUMPRODUCT(--ISNUMBER(Risk_Rank_Keys!$B$2:$B$800),--(Risk_Rank_Keys!$B$2:$B$800=Risk_Rank_Keys!B2))+1)/2)/COUNT(Risk_Rank_Keys!$B$2:$B$800)) -> 0.29288703 | N2: =IF(OR(B2="NW",COUNT(Risk_Rank_Keys!C2)=0),0.5,(SUMPRODUCT(--ISNUMBER(Risk_Rank_Keys!$C$2:$C$800),--(Risk_Rank_Keys!$C$2:$C$800<Risk_Rank_Keys!C2))+(SUMPRODUCT(--ISNUMBER(Risk_Rank_Keys!$C$2:$C$800),--(Risk_Rank_Keys!$C$2:$C$800=Risk_Rank_Keys!C2))+1)/2)/COUNT(Risk_Rank_Keys!$C$2:$C$800)) -> 0.12133891 | O2: =IF(OR(B2="NW",COUNT(Risk_Rank_Keys!D2)=0),0.5,(SUMPRODUCT(--ISNUMBER(Risk_Rank_Keys!$D$2:$D$800),--(Risk_Rank_Keys!$D$2:$D$800<Risk_Rank_Keys!D2))+(SUMPRODUCT(--ISNUMBER(Risk_Rank_Keys!$D$2:$D$800),--(Risk_Rank_Keys!$D$2:$D$800=Risk_Rank_Keys!D2))+1)/2)/COUNT(Risk_Rank_Keys!$D$2:$D$800)) -> 0.76011158 | P2: =AVERAGE(M2:O2) -> 0.39144584 | Q2: =0.4*H2+0.4*I2+0.2*P2 -> 0.38116777 | R2: =PERCENTILE($Q$2:$Q$800,0.75) -> 0.66771572 | S2: =OR(Q2>=R2,AND(B2="CW",COUNT(J2:L2)<3)) -> FALSE | T2: 0.23413931 | U2: 8.1936412 | V2: 0.38116777 | W2: =Q2-V2 -> 0
A3: 2021-01-04 | B3: CW | C3: 44.500267 | D3: =SUMPRODUCT(Risk_Inputs!B3:AJ3,Risk_Coefs!$B$2:$AJ$2) -> -0.9626899 | E3: =1/(1+EXP(-MAX(-25,MIN(25,D3)))) -> 0.27633996 | F3: =SUMPRODUCT(Risk_Inputs!B3:AJ3,Risk_Coefs!$B$3:$AJ$3) -> 10.931965 | G3: =MAX(0,F3) -> 10.931965 | H3: =(SUMPRODUCT(--ISNUMBER($E$2:$E$800),--($E$2:$E$800<E3))+(SUMPRODUCT(--ISNUMBER($E$2:$E$800),--($E$2:$E$800=E3))+1)/2)/COUNT($E$2:$E$800) -> 0.43679599 | I3: =(SUMPRODUCT(--ISNUMBER($G$2:$G$800),--($G$2:$G$800<G3))+(SUMPRODUCT(--ISNUMBER($G$2:$G$800),--($G$2:$G$800=G3))+1)/2)/COUNT($G$2:$G$800) -> 0.87484355 | J3: 39.395249 | K3: 3.6389083 | L3: 0.3265687 | M3: =IF(OR(B3="NW",COUNT(Risk_Rank_Keys!B3)=0),0.5,(SUMPRODUCT(--ISNUMBER(Risk_Rank_Keys!$B$2:$B$800),--(Risk_Rank_Keys!$B$2:$B$800<Risk_Rank_Keys!B3))+(SUMPRODUCT(--ISNUMBER(Risk_Rank_Keys!$B$2:$B$800),--(Risk_Rank_Keys!$B$2:$B$800=Risk_Rank_Keys!B3))+1)/2)/COUNT(Risk_Rank_Keys!$B$2:$B$800)) -> 0.9525802 | N3: =IF(OR(B3="NW",COUNT(Risk_Rank_Keys!C3)=0),0.5,(SUMPRODUCT(--ISNUMBER(Risk_Rank_Keys!$C$2:$C$800),--(Risk_Rank_Keys!$C$2:$C$800<Risk_Rank_Keys!C3))+(SUMPRODUCT(--ISNUMBER(Risk_Rank_Keys!$C$2:$C$800),--(Risk_Rank_Keys!$C$2:$C$800=Risk_Rank_Keys!C3))+1)/2)/COUNT(Risk_Rank_Keys!$C$2:$C$800)) -> 0.55230126 | O3: =IF(OR(B3="NW",COUNT(Risk_Rank_Keys!D3)=0),0.5,(SUMPRODUCT(--ISNUMBER(Risk_Rank_Keys!$D$2:$D$800),--(Risk_Rank_Keys!$D$2:$D$800<Risk_Rank_Keys!D3))+(SUMPRODUCT(--ISNUMBER(Risk_Rank_Keys!$D$2:$D$800),--(Risk_Rank_Keys!$D$2:$D$800=Risk_Rank_Keys!D3))+1)/2)/COUNT(Risk_Rank_Keys!$D$2:$D$800)) -> 0.79079498 | P3: =AVERAGE(M3:O3) -> 0.76522548 | Q3: =0.4*H3+0.4*I3+0.2*P3 -> 0.67770092 | R3: =PERCENTILE($Q$2:$Q$800,0.75) -> 0.66771572 | S3: =OR(Q3>=R3,AND(B3="CW",COUNT(J3:L3)<3)) -> TRUE | T3: 0.27633996 | U3: 10.931965 | V3: 0.67770092 | W3: =Q3-V3 -> 0
A4: 2021-01-05 | B4: CW | C4: -10.68427 | D4: =SUMPRODUCT(Risk_Inputs!B4:AJ4,Risk_Coefs!$B$2:$AJ$2) -> -1.433381 | E4: =1/(1+EXP(-MAX(-25,MIN(25,D4)))) -> 0.19257243 | F4: =SUMPRODUCT(Risk_Inputs!B4:AJ4,Risk_Coefs!$B$3:$AJ$3) -> 3.2210256 | G4: =MAX(0,F4) -> 3.2210256 | H4: =(SUMPRODUCT(--ISNUMBER($E$2:$E$800),--($E$2:$E$800<E4))+(SUMPRODUCT(--ISNUMBER($E$2:$E$800),--($E$2:$E$800=E4))+1)/2)/COUNT($E$2:$E$800) -> 0.09261577 | I4: =(SUMPRODUCT(--ISNUMBER($G$2:$G$800),--($G$2:$G$800<G4))+(SUMPRODUCT(--ISNUMBER($G$2:$G$800),--($G$2:$G$800=G4))+1)/2)/COUNT($G$2:$G$800) -> 0.030037547 | J4: 8.5577828 | K4: 3.7188873 | L4: 0.3806735 | M4: =IF(OR(B4="NW",COUNT(Risk_Rank_Keys!B4)=0),0.5,(SUMPRODUCT(--ISNUMBER(Risk_Rank_Keys!$B$2:$B$800),--(Risk_Rank_Keys!$B$2:$B$800<Risk_Rank_Keys!B4))+(SUMPRODUCT(--ISNUMBER(Risk_Rank_Keys!$B$2:$B$800),--(Risk_Rank_Keys!$B$2:$B$800=Risk_Rank_Keys!B4))+1)/2)/COUNT(Risk_Rank_Keys!$B$2:$B$800)) -> 0.42398884 | N4: =IF(OR(B4="NW",COUNT(Risk_Rank_Keys!C4)=0),0.5,(SUMPRODUCT(--ISNUMBER(Risk_Rank_Keys!$C$2:$C$800),--(Risk_Rank_Keys!$C$2:$C$800<Risk_Rank_Keys!C4))+(SUMPRODUCT(--ISNUMBER(Risk_Rank_Keys!$C$2:$C$800),--(Risk_Rank_Keys!$C$2:$C$800=Risk_Rank_Keys!C4))+1)/2)/COUNT(Risk_Rank_Keys!$C$2:$C$800)) -> 0.56206416 | O4: =IF(OR(B4="NW",COUNT(Risk_Rank_Keys!D4)=0),0.5,(SUMPRODUCT(--ISNUMBER(Risk_Rank_Keys!$D$2:$D$800),--(Risk_Rank_Keys!$D$2:$D$800<Risk_Rank_Keys!D4))+(SUMPRODUCT(--ISNUMBER(Risk_Rank_Keys!$D$2:$D$800),--(Risk_Rank_Keys!$D$2:$D$800=Risk_Rank_Keys!D4))+1)/2)/COUNT(Risk_Rank_Keys!$D$2:$D$800)) -> 0.86610879 | P4: =AVERAGE(M4:O4) -> 0.61738726 | Q4: =0.4*H4+0.4*I4+0.2*P4 -> 0.17253878 | R4: =PERCENTILE($Q$2:$Q$800,0.75) -> 0.66771572 | S4: =OR(Q4>=R4,AND(B4="CW",COUNT(J4:L4)<3)) -> FALSE | T4: 0.19257243 | U4: 3.2210256 | V4: 0.17253878 | W4: =Q4-V4 -> 0
A5: 2021-01-06 | B5: CW | C5: -45.306747 | D5: =SUMPRODUCT(Risk_Inputs!B5:AJ5,Risk_Coefs!$B$2:$AJ$2) -> -0.71682957 | E5: =1/(1+EXP(-MAX(-25,MIN(25,D5)))) -> 0.32809152 | F5: =SUMPRODUCT(Risk_Inputs!B5:AJ5,Risk_Coefs!$B$3:$AJ$3) -> 10.811768 | G5: =MAX(0,F5) -> 10.811768 | H5: =(SUMPRODUCT(--ISNUMBER($E$2:$E$800),--($E$2:$E$800<E5))+(SUMPRODUCT(--ISNUMBER($E$2:$E$800),--($E$2:$E$800=E5))+1)/2)/COUNT($E$2:$E$800) -> 0.72090113 | I5: =(SUMPRODUCT(--ISNUMBER($G$2:$G$800),--($G$2:$G$800<G5))+(SUMPRODUCT(--ISNUMBER($G$2:$G$800),--($G$2:$G$800=G5))+1)/2)/COUNT($G$2:$G$800) -> 0.86232791 | J5: 9.3975039 | K5: 1.6491228 | L5: 0.31578947 | M5: =IF(OR(B5="NW",COUNT(Risk_Rank_Keys!B5)=0),0.5,(SUMPRODUCT(--ISNUMBER(Risk_Rank_Keys!$B$2:$B$800),--(Risk_Rank_Keys!$B$2:$B$800<Risk_Rank_Keys!B5))+(SUMPRODUCT(--ISNUMBER(Risk_Rank_Keys!$B$2:$B$800),--(Risk_Rank_Keys!$B$2:$B$800=Risk_Rank_Keys!B5))+1)/2)/COUNT(Risk_Rank_Keys!$B$2:$B$800)) -> 0.46861925 | N5: =IF(OR(B5="NW",COUNT(Risk_Rank_Keys!C5)=0),0.5,(SUMPRODUCT(--ISNUMBER(Risk_Rank_Keys!$C$2:$C$800),--(Risk_Rank_Keys!$C$2:$C$800<Risk_Rank_Keys!C5))+(SUMPRODUCT(--ISNUMBER(Risk_Rank_Keys!$C$2:$C$800),--(Risk_Rank_Keys!$C$2:$C$800=Risk_Rank_Keys!C5))+1)/2)/COUNT(Risk_Rank_Keys!$C$2:$C$800)) -> 0.17433752 | O5: =IF(OR(B5="NW",COUNT(Risk_Rank_Keys!D5)=0),0.5,(SUMPRODUCT(--ISNUMBER(Risk_Rank_Keys!$D$2:$D$800),--(Risk_Rank_Keys!$D$2:$D$800<Risk_Rank_Keys!D5))+(SUMPRODUCT(--ISNUMBER(Risk_Rank_Keys!$D$2:$D$800),--(Risk_Rank_Keys!$D$2:$D$800=Risk_Rank_Keys!D5))+1)/2)/COUNT(Risk_Rank_Keys!$D$2:$D$800)) -> 0.76708508 | P5: =AVERAGE(M5:O5) -> 0.47001395 | Q5: =0.4*H5+0.4*I5+0.2*P5 -> 0.7272944 | R5: =PERCENTILE($Q$2:$Q$800,0.75) -> 0.66771572 | S5: =OR(Q5>=R5,AND(B5="CW",COUNT(J5:L5)<3)) -> TRUE | T5: 0.32809152 | U5: 10.811768 | V5: 0.7272944 | W5: =Q5-V5 -> 0
A6: 2021-01-07 | B6: CW | C6: 40.429445 | D6: =SUMPRODUCT(Risk_Inputs!B6:AJ6,Risk_Coefs!$B$2:$AJ$2) -> -0.81892913 | E6: =1/(1+EXP(-MAX(-25,MIN(25,D6)))) -> 0.30599102 | F6: =SUMPRODUCT(Risk_Inputs!B6:AJ6,Risk_Coefs!$B$3:$AJ$3) -> 8.8015052 | G6: =MAX(0,F6) -> 8.8015052 | H6: =(SUMPRODUCT(--ISNUMBER($E$2:$E$800),--($E$2:$E$800<E6))+(SUMPRODUCT(--ISNUMBER($E$2:$E$800),--($E$2:$E$800=E6))+1)/2)/COUNT($E$2:$E$800) -> 0.59824781 | I6: =(SUMPRODUCT(--ISNUMBER($G$2:$G$800),--($G$2:$G$800<G6))+(SUMPRODUCT(--ISNUMBER($G$2:$G$800),--($G$2:$G$800=G6))+1)/2)/COUNT($G$2:$G$800) -> 0.65206508 | J6: 5.8006272 | K6: 2.850062 | L6: 0.30978934 | M6: =IF(OR(B6="NW",COUNT(Risk_Rank_Keys!B6)=0),0.5,(SUMPRODUCT(--ISNUMBER(Risk_Rank_Keys!$B$2:$B$800),--(Risk_Rank_Keys!$B$2:$B$800<Risk_Rank_Keys!B6))+(SUMPRODUCT(--ISNUMBER(Risk_Rank_Keys!$B$2:$B$800),--(Risk_Rank_Keys!$B$2:$B$800=Risk_Rank_Keys!B6))+1)/2)/COUNT(Risk_Rank_Keys!$B$2:$B$800)) -> 0.20920502 | N6: =IF(OR(B6="NW",COUNT(Risk_Rank_Keys!C6)=0),0.5,(SUMPRODUCT(--ISNUMBER(Risk_Rank_Keys!$C$2:$C$800),--(Risk_Rank_Keys!$C$2:$C$800<Risk_Rank_Keys!C6))+(SUMPRODUCT(--ISNUMBER(Risk_Rank_Keys!$C$2:$C$800),--(Risk_Rank_Keys!$C$2:$C$800=Risk_Rank_Keys!C6))+1)/2)/COUNT(Risk_Rank_Keys!$C$2:$C$800)) -> 0.44909344 | O6: =IF(OR(B6="NW",COUNT(Risk_Rank_Keys!D6)=0),0.5,(SUMPRODUCT(--ISNUMBER(Risk_Rank_Keys!$D$2:$D$800),--(Risk_Rank_Keys!$D$2:$D$800<Risk_Rank_Keys!D6))+(SUMPRODUCT(--ISNUMBER(Risk_Rank_Keys!$D$2:$D$800),--(Risk_Rank_Keys!$D$2:$D$800=Risk_Rank_Keys!D6))+1)/2)/COUNT(Risk_Rank_Keys!$D$2:$D$800)) -> 0.75732218 | P6: =AVERAGE(M6:O6) -> 0.47187355 | Q6: =0.4*H6+0.4*I6+0.2*P6 -> 0.59449987 | R6: =PERCENTILE($Q$2:$Q$800,0.75) -> 0.66771572 | S6: =OR(Q6>=R6,AND(B6="CW",COUNT(J6:L6)<3)) -> FALSE | T6: 0.30599102 | U6: 8.8015052 | V6: 0.59449987 | W6: =Q6-V6 -> 0
A7: 2021-01-11 | B7: CW | C7: -37.921812 | D7: =SUMPRODUCT(Risk_Inputs!B7:AJ7,Risk_Coefs!$B$2:$AJ$2) -> -0.5881178 | E7: =1/(1+EXP(-MAX(-25,MIN(25,D7)))) -> 0.35706683 | F7: =SUMPRODUCT(Risk_Inputs!B7:AJ7,Risk_Coefs!$B$3:$AJ$3) -> 10.277981 | G7: =MAX(0,F7) -> 10.277981 | H7: =(SUMPRODUCT(--ISNUMBER($E$2:$E$800),--($E$2:$E$800<E7))+(SUMPRODUCT(--ISNUMBER($E$2:$E$800),--($E$2:$E$800=E7))+1)/2)/COUNT($E$2:$E$800) -> 0.83354193 | I7: =(SUMPRODUCT(--ISNUMBER($G$2:$G$800),--($G$2:$G$800<G7))+(SUMPRODUCT(--ISNUMBER($G$2:$G$800),--($G$2:$G$800=G7))+1)/2)/COUNT($G$2:$G$800) -> 0.81977472 | J7: 10.382918 | K7: 2.8862077 | L7: 0.26023184 | M7: =IF(OR(B7="NW",COUNT(Risk_Rank_Keys!B7)=0),0.5,(SUMPRODUCT(--ISNUMBER(Risk_Rank_Keys!$B$2:$B$800),--(Risk_Rank_Keys!$B$2:$B$800<Risk_Rank_Keys!B7))+(SUMPRODUCT(--ISNUMBER(Risk_Rank_Keys!$B$2:$B$800),--(Risk_Rank_Keys!$B$2:$B$800=Risk_Rank_Keys!B7))+1)/2)/COUNT(Risk_Rank_Keys!$B$2:$B$800)) -> 0.52580195 | N7: =IF(OR(B7="NW",COUNT(Risk_Rank_Keys!C7)=0),0.5,(SUMPRODUCT(--ISNUMBER(Risk_Rank_Keys!$C$2:$C$800),--(Risk_Rank_Keys!$C$2:$C$800<Risk_Rank_Keys!C7))+(SUMPRODUCT(--ISNUMBER(Risk_Rank_Keys!$C$2:$C$800),--(Risk_Rank_Keys!$C$2:$C$800=Risk_Rank_Keys!C7))+1)/2)/COUNT(Risk_Rank_Keys!$C$2:$C$800)) -> 0.45606695 | O7: =IF(OR(B7="NW",COUNT(Risk_Rank_Keys!D7)=0),0.5,(SUMPRODUCT(--ISNUMBER(Risk_Rank_Keys!$D$2:$D$800),--(Risk_Rank_Keys!$D$2:$D$800<Risk_Rank_Keys!D7))+(SUMPRODUCT(--ISNUMBER(Risk_Rank_Keys!$D$2:$D$800),--(Risk_Rank_Keys!$D$2:$D$800=Risk_Rank_Keys!D7))+1)/2)/COUNT(Risk_Rank_Keys!$D$2:$D$800)) -> 0.63458856 | P7: =AVERAGE(M7:O7) -> 0.53881915 | Q7: =0.4*H7+0.4*I7+0.2*P7 -> 0.76909049 | R7: =PERCENTILE($Q$2:$Q$800,0.75) -> 0.66771572 | S7: =OR(Q7>=R7,AND(B7="CW",COUNT(J7:L7)<3)) -> TRUE | T7: 0.35706683 | U7: 10.277981 | V7: 0.76909049 | W7: =Q7-V7 -> 0
A8: 2021-01-12 | B8: CW | C8: 18.445431 | D8: =SUMPRODUCT(Risk_Inputs!B8:AJ8,Risk_Coefs!$B$2:$AJ$2) -> -0.90353874 | E8: =1/(1+EXP(-MAX(-25,MIN(25,D8)))) -> 0.28832383 | F8: =SUMPRODUCT(Risk_Inputs!B8:AJ8,Risk_Coefs!$B$3:$AJ$3) -> 7.1082222 | G8: =MAX(0,F8) -> 7.1082222 | H8: =(SUMPRODUCT(--ISNUMBER($E$2:$E$800),--($E$2:$E$800<E8))+(SUMPRODUCT(--ISNUMBER($E$2:$E$800),--($E$2:$E$800=E8))+1)/2)/COUNT($E$2:$E$800) -> 0.51188986 | I8: =(SUMPRODUCT(--ISNUMBER($G$2:$G$800),--($G$2:$G$800<G8))+(SUMPRODUCT(--ISNUMBER($G$2:$G$800),--($G$2:$G$800=G8))+1)/2)/COUNT($G$2:$G$800) -> 0.42928661 | J8: 6.1259241 | K8: 1.7466111 | L8: 0.31282586 | M8: =IF(OR(B8="NW",COUNT(Risk_Rank_Keys!B8)=0),0.5,(SUMPRODUCT(--ISNUMBER(Risk_Rank_Keys!$B$2:$B$800),--(Risk_Rank_Keys!$B$2:$B$800<Risk_Rank_Keys!B8))+(SUMPRODUCT(--ISNUMBER(Risk_Rank_Keys!$B$2:$B$800),--(Risk_Rank_Keys!$B$2:$B$800=Risk_Rank_Keys!B8))+1)/2)/COUNT(Risk_Rank_Keys!$B$2:$B$800)) -> 0.23291492 | N8: =IF(OR(B8="NW",COUNT(Risk_Rank_Keys!C8)=0),0.5,(SUMPRODUCT(--ISNUMBER(Risk_Rank_Keys!$C$2:$C$800),--(Risk_Rank_Keys!$C$2:$C$800<Risk_Rank_Keys!C8))+(SUMPRODUCT(--ISNUMBER(Risk_Rank_Keys!$C$2:$C$800),--(Risk_Rank_Keys!$C$2:$C$800=Risk_Rank_Keys!C8))+1)/2)/COUNT(Risk_Rank_Keys!$C$2:$C$800)) -> 0.20083682 | O8: =IF(OR(B8="NW",COUNT(Risk_Rank_Keys!D8)=0),0.5,(SUMPRODUCT(--ISNUMBER(Risk_Rank_Keys!$D$2:$D$800),--(Risk_Rank_Keys!$D$2:$D$800<Risk_Rank_Keys!D8))+(SUMPRODUCT(--ISNUMBER(Risk_Rank_Keys!$D$2:$D$800),--(Risk_Rank_Keys!$D$2:$D$800=Risk_Rank_Keys!D8))+1)/2)/COUNT(Risk_Rank_Keys!$D$2:$D$800)) -> 0.75871688 | P8: =AVERAGE(M8:O8) -> 0.39748954 | Q8: =0.4*H8+0.4*I8+0.2*P8 -> 0.4559685 | R8: =PERCENTILE($Q$2:$Q$800,0.75) -> 0.66771572 | S8: =OR(Q8>=R8,AND(B8="CW",COUNT(J8:L8)<3)) -> FALSE | T8: 0.28832383 | U8: 7.1082222 | V8: 0.4559685 | W8: =Q8-V8 -> 0
A9: 2021-01-13 | B9: CW | C9: 21.297182 | D9: =SUMPRODUCT(Risk_Inputs!B9:AJ9,Risk_Coefs!$B$2:$AJ$2) -> -0.72010648 | E9: =1/(1+EXP(-MAX(-25,MIN(25,D9)))) -> 0.32736954 | F9: =SUMPRODUCT(Risk_Inputs!B9:AJ9,Risk_Coefs!$B$3:$AJ$3) -> 9.4583689 | G9: =MAX(0,F9) -> 9.4583689 | H9: =(SUMPRODUCT(--ISNUMBER($E$2:$E$800),--($E$2:$E$800<E9))+(SUMPRODUCT(--ISNUMBER($E$2:$E$800),--($E$2:$E$800=E9))+1)/2)/COUNT($E$2:$E$800) -> 0.71714643 | I9: =(SUMPRODUCT(--ISNUMBER($G$2:$G$800),--($G$2:$G$800<G9))+(SUMPRODUCT(--ISNUMBER($G$2:$G$800),--($G$2:$G$800=G9))+1)/2)/COUNT($G$2:$G$800) -> 0.72340426 | J9: 4.0768783 | K9: 2.7191413 | L9: 0.32200358 | M9: =IF(OR(B9="NW",COUNT(Risk_Rank_Keys!B9)=0),0.5,(SUMPRODUCT(--ISNUMBER(Risk_Rank_Keys!$B$2:$B$800),--(Risk_Rank_Keys!$B$2:$B$800<Risk_Rank_Keys!B9))+(SUMPRODUCT(--ISNUMBER(Risk_Rank_Keys!$B$2:$B$800),--(Risk_Rank_Keys!$B$2:$B$800=Risk_Rank_Keys!B9))+1)/2)/COUNT(Risk_Rank_Keys!$B$2:$B$800)) -> 0.075313808 | N9: =IF(OR(B9="NW",COUNT(Risk_Rank_Keys!C9)=0),0.5,(SUMPRODUCT(--ISNUMBER(Risk_Rank_Keys!$C$2:$C$800),--(Risk_Rank_Keys!$C$2:$C$800<Risk_Rank_Keys!C9))+(SUMPRODUCT(--ISNUMBER(Risk_Rank_Keys!$C$2:$C$800),--(Risk_Rank_Keys!$C$2:$C$800=Risk_Rank_Keys!C9))+1)/2)/COUNT(Risk_Rank_Keys!$C$2:$C$800)) -> 0.42677824 | O9: =IF(OR(B9="NW",COUNT(Risk_Rank_Keys!D9)=0),0.5,(SUMPRODUCT(--ISNUMBER(Risk_Rank_Keys!$D$2:$D$800),--(Risk_Rank_Keys!$D$2:$D$800<Risk_Rank_Keys!D9))+(SUMPRODUCT(--ISNUMBER(Risk_Rank_Keys!$D$2:$D$800),--(Risk_Rank_Keys!$D$2:$D$800=Risk_Rank_Keys!D9))+1)/2)/COUNT(Risk_Rank_Keys!$D$2:$D$800)) -> 0.78242678 | P9: =AVERAGE(M9:O9) -> 0.42817294 | Q9: =0.4*H9+0.4*I9+0.2*P9 -> 0.66185486 | R9: =PERCENTILE($Q$2:$Q$800,0.75) -> 0.66771572 | S9: =OR(Q9>=R9,AND(B9="CW",COUNT(J9:L9)<3)) -> FALSE | T9: 0.32736954 | U9: 9.4583689 | V9: 0.66185486 | W9: =Q9-V9 -> 0
A10: 2021-01-14 | B10: CW | C10: 25.737829 | D10: =SUMPRODUCT(Risk_Inputs!B10:AJ10,Risk_Coefs!$B$2:$AJ$2) -> -0.96906545 | E10: =1/(1+EXP(-MAX(-25,MIN(25,D10)))) -> 0.27506682 | F10: =SUMPRODUCT(Risk_Inputs!B10:AJ10,Risk_Coefs!$B$3:$AJ$3) -> 7.4153155 | G10: =MAX(0,F10) -> 7.4153155 | H10: =(SUMPRODUCT(--ISNUMBER($E$2:$E$800),--($E$2:$E$800<E10))+(SUMPRODUCT(--ISNUMBER($E$2:$E$800),--($E$2:$E$800=E10))+1)/2)/COUNT($E$2:$E$800) -> 0.42428035 | I10: =(SUMPRODUCT(--ISNUMBER($G$2:$G$800),--($G$2:$G$800<G10))+(SUMPRODUCT(--ISNUMBER($G$2:$G$800),--($G$2:$G$800=G10))+1)/2)/COUNT($G$2:$G$800) -> 0.46057572 | J10: 6.4240638 | K10: 3.3197437 | L10: 0.46592895 | M10: =IF(OR(B10="NW",COUNT(Risk_Rank_Keys!B10)=0),0.5,(SUMPRODUCT(--ISNUMBER(Risk_Rank_Keys!$B$2:$B$800),--(Risk_Rank_Keys!$B$2:$B$800<Risk_Rank_Keys!B10))+(SUMPRODUCT(--ISNUMBER(Risk_Rank_Keys!$B$2:$B$800),--(Risk_Rank_Keys!$B$2:$B$800=Risk_Rank_Keys!B10))+1)/2)/COUNT(Risk_Rank_Keys!$B$2:$B$800)) -> 0.26917713 | N10: =IF(OR(B10="NW",COUNT(Risk_Rank_Keys!C10)=0),0.5,(SUMPRODUCT(--ISNUMBER(Risk_Rank_Keys!$C$2:$C$800),--(Risk_Rank_Keys!$C$2:$C$800<Risk_Rank_Keys!C10))+(SUMPRODUCT(--ISNUMBER(Risk_Rank_Keys!$C$2:$C$800),--(Risk_Rank_Keys!$C$2:$C$800=Risk_Rank_Keys!C10))+1)/2)/COUNT(Risk_Rank_Keys!$C$2:$C$800)) -> 0.51046025 | O10: =IF(OR(B10="NW",COUNT(Risk_Rank_Keys!D10)=0),0.5,(SUMPRODUCT(--ISNUMBER(Risk_Rank_Keys!$D$2:$D$800),--(Risk_Rank_Keys!$D$2:$D$800<Risk_Rank_Keys!D10))+(SUMPRODUCT(--ISNUMBER(Risk_Rank_Keys!$D$2:$D$800),--(Risk_Rank_Keys!$D$2:$D$800=Risk_Rank_Keys!D10))+1)/2)/COUNT(Risk_Rank_Keys!$D$2:$D$800)) -> 0.93444909 | P10: =AVERAGE(M10:O10) -> 0.57136216 | Q10: =0.4*H10+0.4*I10+0.2*P10 -> 0.46821486 | R10: =PERCENTILE($Q$2:$Q$800,0.75) -> 0.66771572 | S10: =OR(Q10>=R10,AND(B10="CW",COUNT(J10:L10)<3)) -> FALSE | T10: 0.27506682 | U10: 7.4153155 | V10: 0.46821486 | W10: =Q10-V10 -> 0
A11: 2021-01-15 | B11: CW | C11: -45.133894 | D11: =SUMPRODUCT(Risk_Inputs!B11:AJ11,Risk_Coefs!$B$2:$AJ$2) -> -1.0623525 | E11: =1/(1+EXP(-MAX(-25,MIN(25,D11)))) -> 0.25686015 | F11: =SUMPRODUCT(Risk_Inputs!B11:AJ11,Risk_Coefs!$B$3:$AJ$3) -> 8.2013316 | G11: =MAX(0,F11) -> 8.2013316 | H11: =(SUMPRODUCT(--ISNUMBER($E$2:$E$800),--($E$2:$E$800<E11))+(SUMPRODUCT(--ISNUMBER($E$2:$E$800),--($E$2:$E$800=E11))+1)/2)/COUNT($E$2:$E$800) -> 0.30913642 | I11: =(SUMPRODUCT(--ISNUMBER($G$2:$G$800),--($G$2:$G$800<G11))+(SUMPRODUCT(--ISNUMBER($G$2:$G$800),--($G$2:$G$800=G11))+1)/2)/COUNT($G$2:$G$800) -> 0.56320401 | J11: 14.895067 | K11: 1.788067 | L11: 0.33879164 | M11: =IF(OR(B11="NW",COUNT(Risk_Rank_Keys!B11)=0),0.5,(SUMPRODUCT(--ISNUMBER(Risk_Rank_Keys!$B$2:$B$800),--(Risk_Rank_Keys!$B$2:$B$800<Risk_Rank_Keys!B11))+(SUMPRODUCT(--ISNUMBER(Risk_Rank_Keys!$B$2:$B$800),--(Risk_Rank_Keys!$B$2:$B$800=Risk_Rank_Keys!B11))+1)/2)/COUNT(Risk_Rank_Keys!$B$2:$B$800)) -> 0.70432357 | N11: =IF(OR(B11="NW",COUNT(Risk_Rank_Keys!C11)=0),0.5,(SUMPRODUCT(--ISNUMBER(Risk_Rank_Keys!$C$2:$C$800),--(Risk_Rank_Keys!$C$2:$C$800<Risk_Rank_Keys!C11))+(SUMPRODUCT(--ISNUMBER(Risk_Rank_Keys!$C$2:$C$800),--(Risk_Rank_Keys!$C$2:$C$800=Risk_Rank_Keys!C11))+1)/2)/COUNT(Risk_Rank_Keys!$C$2:$C$800)) -> 0.21059972 | O11: =IF(OR(B11="NW",COUNT(Risk_Rank_Keys!D11)=0),0.5,(SUMPRODUCT(--ISNUMBER(Risk_Rank_Keys!$D$2:$D$800),--(Risk_Rank_Keys!$D$2:$D$800<Risk_Rank_Keys!D11))+(SUMPRODUCT(--ISNUMBER(Risk_Rank_Keys!$D$2:$D$800),--(Risk_Rank_Keys!$D$2:$D$800=Risk_Rank_Keys!D11))+1)/2)/COUNT(Risk_Rank_Keys!$D$2:$D$800)) -> 0.81311018 | P11: =AVERAGE(M11:O11) -> 0.57601116 | Q11: =0.4*H11+0.4*I11+0.2*P11 -> 0.4641384 | R11: =PERCENTILE($Q$2:$Q$800,0.75) -> 0.66771572 | S11: =OR(Q11>=R11,AND(B11="CW",COUNT(J11:L11)<3)) -> FALSE | T11: 0.25686015 | U11: 8.2013316 | V11: 0.4641384 | W11: =Q11-V11 -> 0
A12: 2021-01-18 | B12: CW | C12: 11.478606 | D12: =SUMPRODUCT(Risk_Inputs!B12:AJ12,Risk_Coefs!$B$2:$AJ$2) -> -0.36923127 | E12: =1/(1+EXP(-MAX(-25,MIN(25,D12)))) -> 0.40872679 | F12: =SUMPRODUCT(Risk_Inputs!B12:AJ12,Risk_Coefs!$B$3:$AJ$3) -> 10.271132 | G12: =MAX(0,F12) -> 10.271132 | H12: =(SUMPRODUCT(--ISNUMBER($E$2:$E$800),--($E$2:$E$800<E12))+(SUMPRODUCT(--ISNUMBER($E$2:$E$800),--($E$2:$E$800=E12))+1)/2)/COUNT($E$2:$E$800) -> 0.95494368 | I12: =(SUMPRODUCT(--ISNUMBER($G$2:$G$800),--($G$2:$G$800<G12))+(SUMPRODUCT(--ISNUMBER($G$2:$G$800),--($G$2:$G$800=G12))+1)/2)/COUNT($G$2:$G$800) -> 0.81852315 | J12: 5.1077314 | K12: 1.1741683 | L12: 0.249066 | M12: =IF(OR(B12="NW",COUNT(Risk_Rank_Keys!B12)=0),0.5,(SUMPRODUCT(--ISNUMBER(Risk_Rank_Keys!$B$2:$B$800),--(Risk_Rank_Keys!$B$2:$B$800<Risk_Rank_Keys!B12))+(SUMPRODUCT(--ISNUMBER(Risk_Rank_Keys!$B$2:$B$800),--(Risk_Rank_Keys!$B$2:$B$800=Risk_Rank_Keys!B12))+1)/2)/COUNT(Risk_Rank_Keys!$B$2:$B$800)) -> 0.13947001 | N12: =IF(OR(B12="NW",COUNT(Risk_Rank_Keys!C12)=0),0.5,(SUMPRODUCT(--ISNUMBER(Risk_Rank_Keys!$C$2:$C$800),--(Risk_Rank_Keys!$C$2:$C$800<Risk_Rank_Keys!C12))+(SUMPRODUCT(--ISNUMBER(Risk_Rank_Keys!$C$2:$C$800),--(Risk_Rank_Keys!$C$2:$C$800=Risk_Rank_Keys!C12))+1)/2)/COUNT(Risk_Rank_Keys!$C$2:$C$800)) -> 0.062761506 | O12: =IF(OR(B12="NW",COUNT(Risk_Rank_Keys!D12)=0),0.5,(SUMPRODUCT(--ISNUMBER(Risk_Rank_Keys!$D$2:$D$800),--(Risk_Rank_Keys!$D$2:$D$800<Risk_Rank_Keys!D12))+(SUMPRODUCT(--ISNUMBER(Risk_Rank_Keys!$D$2:$D$800),--(Risk_Rank_Keys!$D$2:$D$800=Risk_Rank_Keys!D12))+1)/2)/COUNT(Risk_Rank_Keys!$D$2:$D$800)) -> 0.58158996 | P12: =AVERAGE(M12:O12) -> 0.26127383 | Q12: =0.4*H12+0.4*I12+0.2*P12 -> 0.7616415 | R12: =PERCENTILE($Q$2:$Q$800,0.75) -> 0.66771572 | S12: =OR(Q12>=R12,AND(B12="CW",COUNT(J12:L12)<3)) -> TRUE | T12: 0.40872679 | U12: 10.271132 | V12: 0.7616415 | W12: =Q12-V12 -> 0
A13: 2021-01-19 | B13: CW | C13: 39.151501 | D13: =SUMPRODUCT(Risk_Inputs!B13:AJ13,Risk_Coefs!$B$2:$AJ$2) -> -1.2949907 | E13: =1/(1+EXP(-MAX(-25,MIN(25,D13)))) -> 0.21500928 | F13: =SUMPRODUCT(Risk_Inputs!B13:AJ13,Risk_Coefs!$B$3:$AJ$3) -> 5.1535199 | G13: =MAX(0,F13) -> 5.1535199 | H13: =(SUMPRODUCT(--ISNUMBER($E$2:$E$800),--($E$2:$E$800<E13))+(SUMPRODUCT(--ISNUMBER($E$2:$E$800),--($E$2:$E$800=E13))+1)/2)/COUNT($E$2:$E$800) -> 0.1301627 | I13: =(SUMPRODUCT(--ISNUMBER($G$2:$G$800),--($G$2:$G$800<G13))+(SUMPRODUCT(--ISNUMBER($G$2:$G$800),--($G$2:$G$800=G13))+1)/2)/COUNT($G$2:$G$800) -> 0.15769712 | J13: 10.614307 | K13: 5.2358491 | L13: 0.56603774 | M13: =IF(OR(B13="NW",COUNT(Risk_Rank_Keys!B13)=0),0.5,(SUMPRODUCT(--ISNUMBER(Risk_Rank_Keys!$B$2:$B$800),--(Risk_Rank_Keys!$B$2:$B$800<Risk_Rank_Keys!B13))+(SUMPRODUCT(--ISNUMBER(Risk_Rank_Keys!$B$2:$B$800),--(Risk_Rank_Keys!$B$2:$B$800=Risk_Rank_Keys!B13))+1)/2)/COUNT(Risk_Rank_Keys!$B$2:$B$800)) -> 0.53417015 | N13: =IF(OR(B13="NW",COUNT(Risk_Rank_Keys!C13)=0),0.5,(SUMPRODUCT(--ISNUMBER(Risk_Rank_Keys!$C$2:$C$800),--(Risk_Rank_Keys!$C$2:$C$800<Risk_Rank_Keys!C13))+(SUMPRODUCT(--ISNUMBER(Risk_Rank_Keys!$C$2:$C$800),--(Risk_Rank_Keys!$C$2:$C$800=Risk_Rank_Keys!C13))+1)/2)/COUNT(Risk_Rank_Keys!$C$2:$C$800)) -> 0.70432357 | O13: =IF(OR(B13="NW",COUNT(Risk_Rank_Keys!D13)=0),0.5,(SUMPRODUCT(--ISNUMBER(Risk_Rank_Keys!$D$2:$D$800),--(Risk_Rank_Keys!$D$2:$D$800<Risk_Rank_Keys!D13))+(SUMPRODUCT(--ISNUMBER(Risk_Rank_Keys!$D$2:$D$800),--(Risk_Rank_Keys!$D$2:$D$800=Risk_Rank_Keys!D13))+1)/2)/COUNT(Risk_Rank_Keys!$D$2:$D$800)) -> 0.9679219 | P13: =AVERAGE(M13:O13) -> 0.73547187 | Q13: =0.4*H13+0.4*I13+0.2*P13 -> 0.2622383 | R13: =PERCENTILE($Q$2:$Q$800,0.75) -> 0.66771572 | S13: =OR(Q13>=R13,AND(B13="CW",COUNT(J13:L13)<3)) -> FALSE | T13: 0.21500928 | U13: 5.1535199 | V13: 0.2622383 | W13: =Q13-V13 -> 0
A14: 2021-01-20 | B14: CW | C14: 55.067721 | D14: =SUMPRODUCT(Risk_Inputs!B14:AJ14,Risk_Coefs!$B$2:$AJ$2) -> -1.1016783 | E14: =1/(1+EXP(-MAX(-25,MIN(25,D14)))) -> 0.24942557 | F14: =SUMPRODUCT(Risk_Inputs!B14:AJ14,Risk_Coefs!$B$3:$AJ$3) -> 6.6720597 | G14: =MAX(0,F14) -> 6.6720597 | H14: =(SUMPRODUCT(--ISNUMBER($E$2:$E$800),--($E$2:$E$800<E14))+(SUMPRODUCT(--ISNUMBER($E$2:$E$800),--($E$2:$E$800=E14))+1)/2)/COUNT($E$2:$E$800) -> 0.26157697 | I14: =(SUMPRODUCT(--ISNUMBER($G$2:$G$800),--($G$2:$G$800<G14))+(SUMPRODUCT(--ISNUMBER($G$2:$G$800),--($G$2:$G$800=G14))+1)/2)/COUNT($G$2:$G$800) -> 0.37546934 | J14: 8.4278746 | K14: 7.4086604 | L14: 0.47361299 | M14: =IF(OR(B14="NW",COUNT(Risk_Rank_Keys!B14)=0),0.5,(SUMPRODUCT(--ISNUMBER(Risk_Rank_Keys!$B$2:$B$800),--(Risk_Rank_Keys!$B$2:$B$800<Risk_Rank_Keys!B14))+(SUMPRODUCT(--ISNUMBER(Risk_Rank_Keys!$B$2:$B$800),--(Risk_Rank_Keys!$B$2:$B$800=Risk_Rank_Keys!B14))+1)/2)/COUNT(Risk_Rank_Keys!$B$2:$B$800)) -> 0.41143654 | N14: =IF(OR(B14="NW",COUNT(Risk_Rank_Keys!C14)=0),0.5,(SUMPRODUCT(--ISNUMBER(Risk_Rank_Keys!$C$2:$C$800),--(Risk_Rank_Keys!$C$2:$C$800<Risk_Rank_Keys!C14))+(SUMPRODUCT(--ISNUMBER(Risk_Rank_Keys!$C$2:$C$800),--(Risk_Rank_Keys!$C$2:$C$800=Risk_Rank_Keys!C14))+1)/2)/COUNT(Risk_Rank_Keys!$C$2:$C$800)) -> 0.80195258 | O14: =IF(OR(B14="NW",COUNT(Risk_Rank_Keys!D14)=0),0.5,(SUMPRODUCT(--ISNUMBER(Risk_Rank_Keys!$D$2:$D$800),--(Risk_Rank_Keys!$D$2:$D$800<Risk_Rank_Keys!D14))+(SUMPRODUCT(--ISNUMBER(Risk_Rank_Keys!$D$2:$D$800),--(Risk_Rank_Keys!$D$2:$D$800=Risk_Rank_Keys!D14))+1)/2)/COUNT(Risk_Rank_Keys!$D$2:$D$800)) -> 0.94142259 | P14: =AVERAGE(M14:O14) -> 0.71827057 | Q14: =0.4*H14+0.4*I14+0.2*P14 -> 0.39847264 | R14: =PERCENTILE($Q$2:$Q$800,0.75) -> 0.66771572 | S14: =OR(Q14>=R14,AND(B14="CW",COUNT(J14:L14)<3)) -> FALSE | T14: 0.24942557 | U14: 6.6720597 | V14: 0.39847264 | W14: =Q14-V14 -> 0
A15: 2021-01-21 | B15: CW | C15: 36.437411 | D15: =SUMPRODUCT(Risk_Inputs!B15:AJ15,Risk_Coefs!$B$2:$AJ$2) -> -0.33964602 | E15: =1/(1+EXP(-MAX(-25,MIN(25,D15)))) -> 0.41589546 | F15: =SUMPRODUCT(Risk_Inputs!B15:AJ15,Risk_Coefs!$B$3:$AJ$3) -> 13.543477 | G15: =MAX(0,F15) -> 13.543477 | H15: =(SUMPRODUCT(--ISNUMBER($E$2:$E$800),--($E$2:$E$800<E15))+(SUMPRODUCT(--ISNUMBER($E$2:$E$800),--($E$2:$E$800=E15))+1)/2)/COUNT($E$2:$E$800) -> 0.96245307 | I15: =(SUMPRODUCT(--ISNUMBER($G$2:$G$800),--($G$2:$G$800<G15))+(SUMPRODUCT(--ISNUMBER($G$2:$G$800),--($G$2:$G$800=G15))+1)/2)/COUNT($G$2:$G$800) -> 0.96370463 | M15: =IF(OR(B15="NW",COUNT(Risk_Rank_Keys!B15)=0),0.5,(SUMPRODUCT(--ISNUMBER(Risk_Rank_Keys!$B$2:$B$800),--(Risk_Rank_Keys!$B$2:$B$800<Risk_Rank_Keys!B15))+(SUMPRODUCT(--ISNUMBER(Risk_Rank_Keys!$B$2:$B$800),--(Risk_Rank_Keys!$B$2:$B$800=Risk_Rank_Keys!B15))+1)/2)/COUNT(Risk_Rank_Keys!$B$2:$B$800)) -> 0.5 | N15: =IF(OR(B15="NW",COUNT(Risk_Rank_Keys!C15)=0),0.5,(SUMPRODUCT(--ISNUMBER(Risk_Rank_Keys!$C$2:$C$800),--(Risk_Rank_Keys!$C$2:$C$800<Risk_Rank_Keys!C15))+(SUMPRODUCT(--ISNUMBER(Risk_Rank_Keys!$C$2:$C$800),--(Risk_Rank_Keys!$C$2:$C$800=Risk_Rank_Keys!C15))+1)/2)/COUNT(Risk_Rank_Keys!$C$2:$C$800)) -> 0.5 | O15: =IF(OR(B15="NW",COUNT(Risk_Rank_Keys!D15)=0),0.5,(SUMPRODUCT(--ISNUMBER(Risk_Rank_Keys!$D$2:$D$800),--(Risk_Rank_Keys!$D$2:$D$800<Risk_Rank_Keys!D15))+(SUMPRODUCT(--ISNUMBER(Risk_Rank_Keys!$D$2:$D$800),--(Risk_Rank_Keys!$D$2:$D$800=Risk_Rank_Keys!D15))+1)/2)/COUNT(Risk_Rank_Keys!$D$2:$D$800)) -> 0.5 | P15: =AVERAGE(M15:O15) -> 0.5 | Q15: =0.4*H15+0.4*I15+0.2*P15 -> 0.87046308 | R15: =PERCENTILE($Q$2:$Q$800,0.75) -> 0.66771572 | S15: =OR(Q15>=R15,AND(B15="CW",COUNT(J15:L15)<3)) -> TRUE | T15: 0.41589546 | U15: 13.543477 | V15: 0.87046308 | W15: =Q15-V15 -> 0
A16: 2021-01-22 | B16: CW | C16: -40.91495 | D16: =SUMPRODUCT(Risk_Inputs!B16:AJ16,Risk_Coefs!$B$2:$AJ$2) -> -0.53908671 | E16: =1/(1+EXP(-MAX(-25,MIN(25,D16)))) -> 0.36840006 | F16: =SUMPRODUCT(Risk_Inputs!B16:AJ16,Risk_Coefs!$B$3:$AJ$3) -> 13.782778 | G16: =MAX(0,F16) -> 13.782778 | H16: =(SUMPRODUCT(--ISNUMBER($E$2:$E$800),--($E$2:$E$800<E16))+(SUMPRODUCT(--ISNUMBER($E$2:$E$800),--($E$2:$E$800=E16))+1)/2)/COUNT($E$2:$E$800) -> 0.8660826 | I16: =(SUMPRODUCT(--ISNUMBER($G$2:$G$800),--($G$2:$G$800<G16))+(SUMPRODUCT(--ISNUMBER($G$2:$G$800),--($G$2:$G$800=G16))+1)/2)/COUNT($G$2:$G$800) -> 0.96620776 | J16: 7.4583318 | K16: 1.6354746 | L16: 0.28662957 | M16: =IF(OR(B16="NW",COUNT(Risk_Rank_Keys!B16)=0),0.5,(SUMPRODUCT(--ISNUMBER(Risk_Rank_Keys!$B$2:$B$800),--(Risk_Rank_Keys!$B$2:$B$800<Risk_Rank_Keys!B16))+(SUMPRODUCT(--ISNUMBER(Risk_Rank_Keys!$B$2:$B$800),--(Risk_Rank_Keys!$B$2:$B$800=Risk_Rank_Keys!B16))+1)/2)/COUNT(Risk_Rank_Keys!$B$2:$B$800)) -> 0.35285914 | N16: =IF(OR(B16="NW",COUNT(Risk_Rank_Keys!C16)=0),0.5,(SUMPRODUCT(--ISNUMBER(Risk_Rank_Keys!$C$2:$C$800),--(Risk_Rank_Keys!$C$2:$C$800<Risk_Rank_Keys!C16))+(SUMPRODUCT(--ISNUMBER(Risk_Rank_Keys!$C$2:$C$800),--(Risk_Rank_Keys!$C$2:$C$800=Risk_Rank_Keys!C16))+1)/2)/COUNT(Risk_Rank_Keys!$C$2:$C$800)) -> 0.17154812 | O16: =IF(OR(B16="NW",COUNT(Risk_Rank_Keys!D16)=0),0.5,(SUMPRODUCT(--ISNUMBER(Risk_Rank_Keys!$D$2:$D$800),--(Risk_Rank_Keys!$D$2:$D$800<Risk_Rank_Keys!D16))+(SUMPRODUCT(--ISNUMBER(Risk_Rank_Keys!$D$2:$D$800),--(Risk_Rank_Keys!$D$2:$D$800=Risk_Rank_Keys!D16))+1)/2)/COUNT(Risk_Rank_Keys!$D$2:$D$800)) -> 0.71687587 | P16: =AVERAGE(M16:O16) -> 0.41376104 | Q16: =0.4*H16+0.4*I16+0.2*P16 -> 0.81566835 | R16: =PERCENTILE($Q$2:$Q$800,0.75) -> 0.66771572 | S16: =OR(Q16>=R16,AND(B16="CW",COUNT(J16:L16)<3)) -> TRUE | T16: 0.36840006 | U16: 13.782778 | V16: 0.81566835 | W16: =Q16-V16 -> 0
A17: 2021-01-25 | B17: CW | C17: -38.683927 | D17: =SUMPRODUCT(Risk_Inputs!B17:AJ17,Risk_Coefs!$B$2:$AJ$2) -> -0.6189083 | E17: =1/(1+EXP(-MAX(-25,MIN(25,D17)))) -> 0.35002978 | F17: =SUMPRODUCT(Risk_Inputs!B17:AJ17,Risk_Coefs!$B$3:$AJ$3) -> 12.185686 | G17: =MAX(0,F17) -> 12.185686 | H17: =(SUMPRODUCT(--ISNUMBER($E$2:$E$800),--($E$2:$E$800<E17))+(SUMPRODUCT(--ISNUMBER($E$2:$E$800),--($E$2:$E$800=E17))+1)/2)/COUNT($E$2:$E$800) -> 0.81602003 | I17: =(SUMPRODUCT(--ISNUMBER($G$2:$G$800),--($G$2:$G$800<G17))+(SUMPRODUCT(--ISNUMBER($G$2:$G$800),--($G$2:$G$800=G17))+1)/2)/COUNT($G$2:$G$800) -> 0.92866083 | J17: 16.72885 | K17: 2.2686208 | L17: 0.32122064 | M17: =IF(OR(B17="NW",COUNT(Risk_Rank_Keys!B17)=0),0.5,(SUMPRODUCT(--ISNUMBER(Risk_Rank_Keys!$B$2:$B$800),--(Risk_Rank_Keys!$B$2:$B$800<Risk_Rank_Keys!B17))+(SUMPRODUCT(--ISNUMBER(Risk_Rank_Keys!$B$2:$B$800),--(Risk_Rank_Keys!$B$2:$B$800=Risk_Rank_Keys!B17))+1)/2)/COUNT(Risk_Rank_Keys!$B$2:$B$800)) -> 0.74058577 | N17: =IF(OR(B17="NW",COUNT(Risk_Rank_Keys!C17)=0),0.5,(SUMPRODUCT(--ISNUMBER(Risk_Rank_Keys!$C$2:$C$800),--(Risk_Rank_Keys!$C$2:$C$800<Risk_Rank_Keys!C17))+(SUMPRODUCT(--ISNUMBER(Risk_Rank_Keys!$C$2:$C$800),--(Risk_Rank_Keys!$C$2:$C$800=Risk_Rank_Keys!C17))+1)/2)/COUNT(Risk_Rank_Keys!$C$2:$C$800)) -> 0.32775453 | O17: =IF(OR(B17="NW",COUNT(Risk_Rank_Keys!D17)=0),0.5,(SUMPRODUCT(--ISNUMBER(Risk_Rank_Keys!$D$2:$D$800),--(Risk_Rank_Keys!$D$2:$D$800<Risk_Rank_Keys!D17))+(SUMPRODUCT(--ISNUMBER(Risk_Rank_Keys!$D$2:$D$800),--(Risk_Rank_Keys!$D$2:$D$800=Risk_Rank_Keys!D17))+1)/2)/COUNT(Risk_Rank_Keys!$D$2:$D$800)) -> 0.77824268 | P17: =AVERAGE(M17:O17) -> 0.61552766 | Q17: =0.4*H17+0.4*I17+0.2*P17 -> 0.82097787 | R17: =PERCENTILE($Q$2:$Q$800,0.75) -> 0.66771572 | S17: =OR(Q17>=R17,AND(B17="CW",COUNT(J17:L17)<3)) -> TRUE | T17: 0.35002978 | U17: 12.185686 | V17: 0.82097787 | W17: =Q17-V17 -> 0
A18: 2021-01-27 | B18: CW | C18: 48.260157 | D18: =SUMPRODUCT(Risk_Inputs!B18:AJ18,Risk_Coefs!$B$2:$AJ$2) -> -1.4721172 | E18: =1/(1+EXP(-MAX(-25,MIN(25,D18)))) -> 0.18662102 | F18: =SUMPRODUCT(Risk_Inputs!B18:AJ18,Risk_Coefs!$B$3:$AJ$3) -> 5.8428267 | G18: =MAX(0,F18) -> 5.8428267 | H18: =(SUMPRODUCT(--ISNUMBER($E$2:$E$800),--($E$2:$E$800<E18))+(SUMPRODUCT(--ISNUMBER($E$2:$E$800),--($E$2:$E$800=E18))+1)/2)/COUNT($E$2:$E$800) -> 0.075093867 | I18: =(SUMPRODUCT(--ISNUMBER($G$2:$G$800),--($G$2:$G$800<G18))+(SUMPRODUCT(--ISNUMBER($G$2:$G$800),--($G$2:$G$800=G18))+1)/2)/COUNT($G$2:$G$800) -> 0.24530663 | J18: 37.435212 | K18: 9.6825397 | L18: 1.3756614 | M18: =IF(OR(B18="NW",COUNT(Risk_Rank_Keys!B18)=0),0.5,(SUMPRODUCT(--ISNUMBER(Risk_Rank_Keys!$B$2:$B$800),--(Risk_Rank_Keys!$B$2:$B$800<Risk_Rank_Keys!B18))+(SUMPRODUCT(--ISNUMBER(Risk_Rank_Keys!$B$2:$B$800),--(Risk_Rank_Keys!$B$2:$B$800=Risk_Rank_Keys!B18))+1)/2)/COUNT(Risk_Rank_Keys!$B$2:$B$800)) -> 0.94142259 | N18: =IF(OR(B18="NW",COUNT(Risk_Rank_Keys!C18)=0),0.5,(SUMPRODUCT(--ISNUMBER(Risk_Rank_Keys!$C$2:$C$800),--(Risk_Rank_Keys!$C$2:$C$800<Risk_Rank_Keys!C18))+(SUMPRODUCT(--ISNUMBER(Risk_Rank_Keys!$C$2:$C$800),--(Risk_Rank_Keys!$C$2:$C$800=Risk_Rank_Keys!C18))+1)/2)/COUNT(Risk_Rank_Keys!$C$2:$C$800)) -> 0.87447699 | O18: =IF(OR(B18="NW",COUNT(Risk_Rank_Keys!D18)=0),0.5,(SUMPRODUCT(--ISNUMBER(Risk_Rank_Keys!$D$2:$D$800),--(Risk_Rank_Keys!$D$2:$D$800<Risk_Rank_Keys!D18))+(SUMPRODUCT(--ISNUMBER(Risk_Rank_Keys!$D$2:$D$800),--(Risk_Rank_Keys!$D$2:$D$800=Risk_Rank_Keys!D18))+1)/2)/COUNT(Risk_Rank_Keys!$D$2:$D$800)) -> 1 | P18: =AVERAGE(M18:O18) -> 0.93863319 | Q18: =0.4*H18+0.4*I18+0.2*P18 -> 0.31588684 | R18: =PERCENTILE($Q$2:$Q$800,0.75) -> 0.66771572 | S18: =OR(Q18>=R18,AND(B18="CW",COUNT(J18:L18)<3)) -> FALSE | T18: 0.18662102 | U18: 5.8428267 | V18: 0.31588684 | W18: =Q18-V18 -> 0
A19: 2021-01-28 | B19: CW | C19: -12.881305 | D19: =SUMPRODUCT(Risk_Inputs!B19:AJ19,Risk_Coefs!$B$2:$AJ$2) -> -1.092653 | E19: =1/(1+EXP(-MAX(-25,MIN(25,D19)))) -> 0.25111903 | F19: =SUMPRODUCT(Risk_Inputs!B19:AJ19,Risk_Coefs!$B$3:$AJ$3) -> 7.1241508 | G19: =MAX(0,F19) -> 7.1241508 | H19: =(SUMPRODUCT(--ISNUMBER($E$2:$E$800),--($E$2:$E$800<E19))+(SUMPRODUCT(--ISNUMBER($E$2:$E$800),--($E$2:$E$800=E19))+1)/2)/COUNT($E$2:$E$800) -> 0.27158949 | I19: =(SUMPRODUCT(--ISNUMBER($G$2:$G$800),--($G$2:$G$800<G19))+(SUMPRODUCT(--ISNUMBER($G$2:$G$800),--($G$2:$G$800=G19))+1)/2)/COUNT($G$2:$G$800) -> 0.43178974 | J19: 24.5601 | K19: 4.7879617 | L19: 0.45599635 | M19: =IF(OR(B19="NW",COUNT(Risk_Rank_Keys!B19)=0),0.5,(SUMPRODUCT(--ISNUMBER(Risk_Rank_Keys!$B$2:$B$800),--(Risk_Rank_Keys!$B$2:$B$800<Risk_Rank_Keys!B19))+(SUMPRODUCT(--ISNUMBER(Risk_Rank_Keys!$B$2:$B$800),--(Risk_Rank_Keys!$B$2:$B$800=Risk_Rank_Keys!B19))+1)/2)/COUNT(Risk_Rank_Keys!$B$2:$B$800)) -> 0.85076709 | N19: =IF(OR(B19="NW",COUNT(Risk_Rank_Keys!C19)=0),0.5,(SUMPRODUCT(--ISNUMBER(Risk_Rank_Keys!$C$2:$C$800),--(Risk_Rank_Keys!$C$2:$C$800<Risk_Rank_Keys!C19))+(SUMPRODUCT(--ISNUMBER(Risk_Rank_Keys!$C$2:$C$800),--(Risk_Rank_Keys!$C$2:$C$800=Risk_Rank_Keys!C19))+1)/2)/COUNT(Risk_Rank_Keys!$C$2:$C$800)) -> 0.67085077 | O19: =IF(OR(B19="NW",COUNT(Risk_Rank_Keys!D19)=0),0.5,(SUMPRODUCT(--ISNUMBER(Risk_Rank_Keys!$D$2:$D$800),--(Risk_Rank_Keys!$D$2:$D$800<Risk_Rank_Keys!D19))+(SUMPRODUCT(--ISNUMBER(Risk_Rank_Keys!$D$2:$D$800),--(Risk_Rank_Keys!$D$2:$D$800=Risk_Rank_Keys!D19))+1)/2)/COUNT(Risk_Rank_Keys!$D$2:$D$800)) -> 0.93026499 | P19: =AVERAGE(M19:O19) -> 0.81729428 | Q19: =0.4*H19+0.4*I19+0.2*P19 -> 0.44481055 | R19: =PERCENTILE($Q$2:$Q$800,0.75) -> 0.66771572 | S19: =OR(Q19>=R19,AND(B19="CW",COUNT(J19:L19)<3)) -> FALSE | T19: 0.25111903 | U19: 7.1241508 | V19: 0.44481055 | W19: =Q19-V19 -> 0
A20: 2021-01-29 | B20: CW | C20: -42.994228 | D20: =SUMPRODUCT(Risk_Inputs!B20:AJ20,Risk_Coefs!$B$2:$AJ$2) -> -1.5354063 | E20: =1/(1+EXP(-MAX(-25,MIN(25,D20)))) -> 0.17720405 | F20: =SUMPRODUCT(Risk_Inputs!B20:AJ20,Risk_Coefs!$B$3:$AJ$3) -> 9.7457964 | G20: =MAX(0,F20) -> 9.7457964 | H20: =(SUMPRODUCT(--ISNUMBER($E$2:$E$800),--($E$2:$E$800<E20))+(SUMPRODUCT(--ISNUMBER($E$2:$E$800),--($E$2:$E$800=E20))+1)/2)/COUNT($E$2:$E$800) -> 0.058823529 | I20: =(SUMPRODUCT(--ISNUMBER($G$2:$G$800),--($G$2:$G$800<G20))+(SUMPRODUCT(--ISNUMBER($G$2:$G$800),--($G$2:$G$800=G20))+1)/2)/COUNT($G$2:$G$800) -> 0.7571965 | J20: 59.808183 | K20: 8.0519182 | L20: 0.32161728 | M20: =IF(OR(B20="NW",COUNT(Risk_Rank_Keys!B20)=0),0.5,(SUMPRODUCT(--ISNUMBER(Risk_Rank_Keys!$B$2:$B$800),--(Risk_Rank_Keys!$B$2:$B$800<Risk_Rank_Keys!B20))+(SUMPRODUCT(--ISNUMBER(Risk_Rank_Keys!$B$2:$B$800),--(Risk_Rank_Keys!$B$2:$B$800=Risk_Rank_Keys!B20))+1)/2)/COUNT(Risk_Rank_Keys!$B$2:$B$800)) -> 0.9902371 | N20: =IF(OR(B20="NW",COUNT(Risk_Rank_Keys!C20)=0),0.5,(SUMPRODUCT(--ISNUMBER(Risk_Rank_Keys!$C$2:$C$800),--(Risk_Rank_Keys!$C$2:$C$800<Risk_Rank_Keys!C20))+(SUMPRODUCT(--ISNUMBER(Risk_Rank_Keys!$C$2:$C$800),--(Risk_Rank_Keys!$C$2:$C$800=Risk_Rank_Keys!C20))+1)/2)/COUNT(Risk_Rank_Keys!$C$2:$C$800)) -> 0.82287308 | O20: =IF(OR(B20="NW",COUNT(Risk_Rank_Keys!D20)=0),0.5,(SUMPRODUCT(--ISNUMBER(Risk_Rank_Keys!$D$2:$D$800),--(Risk_Rank_Keys!$D$2:$D$800<Risk_Rank_Keys!D20))+(SUMPRODUCT(--ISNUMBER(Risk_Rank_Keys!$D$2:$D$800),--(Risk_Rank_Keys!$D$2:$D$800=Risk_Rank_Keys!D20))+1)/2)/COUNT(Risk_Rank_Keys!$D$2:$D$800)) -> 0.78103208 | P20: =AVERAGE(M20:O20) -> 0.86471409 | Q20: =0.4*H20+0.4*I20+0.2*P20 -> 0.49935083 | R20: =PERCENTILE($Q$2:$Q$800,0.75) -> 0.66771572 | S20: =OR(Q20>=R20,AND(B20="CW",COUNT(J20:L20)<3)) -> FALSE | T20: 0.17720405 | U20: 9.7457964 | V20: 0.49935083 | W20: =Q20-V20 -> 0
A21: 2021-02-01 | B21: CW | C21: 31.538393 | D21: =SUMPRODUCT(Risk_Inputs!B21:AJ21,Risk_Coefs!$B$2:$AJ$2) -> -0.53136278 | E21: =1/(1+EXP(-MAX(-25,MIN(25,D21)))) -> 0.3701991 | F21: =SUMPRODUCT(Risk_Inputs!B21:AJ21,Risk_Coefs!$B$3:$AJ$3) -> 9.7479156 | G21: =MAX(0,F21) -> 9.7479156 | H21: =(SUMPRODUCT(--ISNUMBER($E$2:$E$800),--($E$2:$E$800<E21))+(SUMPRODUCT(--ISNUMBER($E$2:$E$800),--($E$2:$E$800=E21))+1)/2)/COUNT($E$2:$E$800) -> 0.87359199 | I21: =(SUMPRODUCT(--ISNUMBER($G$2:$G$800),--($G$2:$G$800<G21))+(SUMPRODUCT(--ISNUMBER($G$2:$G$800),--($G$2:$G$800=G21))+1)/2)/COUNT($G$2:$G$800) -> 0.75969962 | J21: 11.383308 | K21: 1.6230733 | L21: 0.45539468 | M21: =IF(OR(B21="NW",COUNT(Risk_Rank_Keys!B21)=0),0.5,(SUMPRODUCT(--ISNUMBER(Risk_Rank_Keys!$B$2:$B$800),--(Risk_Rank_Keys!$B$2:$B$800<Risk_Rank_Keys!B21))+(SUMPRODUCT(--ISNUMBER(Risk_Rank_Keys!$B$2:$B$800),--(Risk_Rank_Keys!$B$2:$B$800=Risk_Rank_Keys!B21))+1)/2)/COUNT(Risk_Rank_Keys!$B$2:$B$800)) -> 0.56485356 | N21: =IF(OR(B21="NW",COUNT(Risk_Rank_Keys!C21)=0),0.5,(SUMPRODUCT(--ISNUMBER(Risk_Rank_Keys!$C$2:$C$800),--(Risk_Rank_Keys!$C$2:$C$800<Risk_Rank_Keys!C21))+(SUMPRODUCT(--ISNUMBER(Risk_Rank_Keys!$C$2:$C$800),--(Risk_Rank_Keys!$C$2:$C$800=Risk_Rank_Keys!C21))+1)/2)/COUNT(Risk_Rank_Keys!$C$2:$C$800)) -> 0.16596932 | O21: =IF(OR(B21="NW",COUNT(Risk_Rank_Keys!D21)=0),0.5,(SUMPRODUCT(--ISNUMBER(Risk_Rank_Keys!$D$2:$D$800),--(Risk_Rank_Keys!$D$2:$D$800<Risk_Rank_Keys!D21))+(SUMPRODUCT(--ISNUMBER(Risk_Rank_Keys!$D$2:$D$800),--(Risk_Rank_Keys!$D$2:$D$800=Risk_Rank_Keys!D21))+1)/2)/COUNT(Risk_Rank_Keys!$D$2:$D$800)) -> 0.92608089 | P21: =AVERAGE(M21:O21) -> 0.55230126 | Q21: =0.4*H21+0.4*I21+0.2*P21 -> 0.7637769 | R21: =PERCENTILE($Q$2:$Q$800,0.75) -> 0.66771572 | S21: =OR(Q21>=R21,AND(B21="CW",COUNT(J21:L21)<3)) -> TRUE | T21: 0.3701991 | U21: 9.7479156 | V21: 0.7637769 | W21: =Q21-V21 -> 0
A22: 2021-02-03 | B22: CW | C22: 54.112966 | D22: =SUMPRODUCT(Risk_Inputs!B22:AJ22,Risk_Coefs!$B$2:$AJ$2) -> -1.3198278 | E22: =1/(1+EXP(-MAX(-25,MIN(25,D22)))) -> 0.21084695 | F22: =SUMPRODUCT(Risk_Inputs!B22:AJ22,Risk_Coefs!$B$3:$AJ$3) -> 5.3059622 | G22: =MAX(0,F22) -> 5.3059622 | H22: =(SUMPRODUCT(--ISNUMBER($E$2:$E$800),--($E$2:$E$800<E22))+(SUMPRODUCT(--ISNUMBER($E$2:$E$800),--($E$2:$E$800=E22))+1)/2)/COUNT($E$2:$E$800) -> 0.12390488 | I22: =(SUMPRODUCT(--ISNUMBER($G$2:$G$800),--($G$2:$G$800<G22))+(SUMPRODUCT(--ISNUMBER($G$2:$G$800),--($G$2:$G$800=G22))+1)/2)/COUNT($G$2:$G$800) -> 0.17396746 | J22: 35.667554 | K22: 3.1544136 | L22: 0.63597049 | M22: =IF(OR(B22="NW",COUNT(Risk_Rank_Keys!B22)=0),0.5,(SUMPRODUCT(--ISNUMBER(Risk_Rank_Keys!$B$2:$B$800),--(Risk_Rank_Keys!$B$2:$B$800<Risk_Rank_Keys!B22))+(SUMPRODUCT(--ISNUMBER(Risk_Rank_Keys!$B$2:$B$800),--(Risk_Rank_Keys!$B$2:$B$800=Risk_Rank_Keys!B22))+1)/2)/COUNT(Risk_Rank_Keys!$B$2:$B$800)) -> 0.93305439 | N22: =IF(OR(B22="NW",COUNT(Risk_Rank_Keys!C22)=0),0.5,(SUMPRODUCT(--ISNUMBER(Risk_Rank_Keys!$C$2:$C$800),--(Risk_Rank_Keys!$C$2:$C$800<Risk_Rank_Keys!C22))+(SUMPRODUCT(--ISNUMBER(Risk_Rank_Keys!$C$2:$C$800),--(Risk_Rank_Keys!$C$2:$C$800=Risk_Rank_Keys!C22))+1)/2)/COUNT(Risk_Rank_Keys!$C$2:$C$800)) -> 0.48814505 | O22: =IF(OR(B22="NW",COUNT(Risk_Rank_Keys!D22)=0),0.5,(SUMPRODUCT(--ISNUMBER(Risk_Rank_Keys!$D$2:$D$800),--(Risk_Rank_Keys!$D$2:$D$800<Risk_Rank_Keys!D22))+(SUMPRODUCT(--ISNUMBER(Risk_Rank_Keys!$D$2:$D$800),--(Risk_Rank_Keys!$D$2:$D$800=Risk_Rank_Keys!D22))+1)/2)/COUNT(Risk_Rank_Keys!$D$2:$D$800)) -> 0.9818689 | P22: =AVERAGE(M22:O22) -> 0.80102278 | Q22: =0.4*H22+0.4*I22+0.2*P22 -> 0.27935349 | R22: =PERCENTILE($Q$2:$Q$800,0.75) -> 0.66771572 | S22: =OR(Q22>=R22,AND(B22="CW",COUNT(J22:L22)<3)) -> FALSE | T22: 0.21084695 | U22: 5.3059622 | V22: 0.27935349 | W22: =Q22-V22 -> 0
A23: 2021-02-04 | B23: CW | C23: 47.128969 | D23: =SUMPRODUCT(Risk_Inputs!B23:AJ23,Risk_Coefs!$B$2:$AJ$2) -> -0.90374821 | E23: =1/(1+EXP(-MAX(-25,MIN(25,D23)))) -> 0.28828085 | F23: =SUMPRODUCT(Risk_Inputs!B23:AJ23,Risk_Coefs!$B$3:$AJ$3) -> 9.7978301 | G23: =MAX(0,F23) -> 9.7978301 | H23: =(SUMPRODUCT(--ISNUMBER($E$2:$E$800),--($E$2:$E$800<E23))+(SUMPRODUCT(--ISNUMBER($E$2:$E$800),--($E$2:$E$800=E23))+1)/2)/COUNT($E$2:$E$800) -> 0.5106383 | I23: =(SUMPRODUCT(--ISNUMBER($G$2:$G$800),--($G$2:$G$800<G23))+(SUMPRODUCT(--ISNUMBER($G$2:$G$800),--($G$2:$G$800=G23))+1)/2)/COUNT($G$2:$G$800) -> 0.76470588 | J23: 26.100976 | K23: 12.252811 | L23: 0.38774719 | M23: =IF(OR(B23="NW",COUNT(Risk_Rank_Keys!B23)=0),0.5,(SUMPRODUCT(--ISNUMBER(Risk_Rank_Keys!$B$2:$B$800),--(Risk_Rank_Keys!$B$2:$B$800<Risk_Rank_Keys!B23))+(SUMPRODUCT(--ISNUMBER(Risk_Rank_Keys!$B$2:$B$800),--(Risk_Rank_Keys!$B$2:$B$800=Risk_Rank_Keys!B23))+1)/2)/COUNT(Risk_Rank_Keys!$B$2:$B$800)) -> 0.87029289 | N23: =IF(OR(B23="NW",COUNT(Risk_Rank_Keys!C23)=0),0.5,(SUMPRODUCT(--ISNUMBER(Risk_Rank_Keys!$C$2:$C$800),--(Risk_Rank_Keys!$C$2:$C$800<Risk_Rank_Keys!C23))+(SUMPRODUCT(--ISNUMBER(Risk_Rank_Keys!$C$2:$C$800),--(Risk_Rank_Keys!$C$2:$C$800=Risk_Rank_Keys!C23))+1)/2)/COUNT(Risk_Rank_Keys!$C$2:$C$800)) -> 0.90516039 | O23: =IF(OR(B23="NW",COUNT(Risk_Rank_Keys!D23)=0),0.5,(SUMPRODUCT(--ISNUMBER(Risk_Rank_Keys!$D$2:$D$800),--(Risk_Rank_Keys!$D$2:$D$800<Risk_Rank_Keys!D23))+(SUMPRODUCT(--ISNUMBER(Risk_Rank_Keys!$D$2:$D$800),--(Risk_Rank_Keys!$D$2:$D$800=Risk_Rank_Keys!D23))+1)/2)/COUNT(Risk_Rank_Keys!$D$2:$D$800)) -> 0.87168759 | P23: =AVERAGE(M23:O23) -> 0.88238029 | Q23: =0.4*H23+0.4*I23+0.2*P23 -> 0.68661373 | R23: =PERCENTILE($Q$2:$Q$800,0.75) -> 0.66771572 | S23: =OR(Q23>=R23,AND(B23="CW",COUNT(J23:L23)<3)) -> TRUE | T23: 0.28828085 | U23: 9.7978301 | V23: 0.68661373 | W23: =Q23-V23 -> 0
A24: 2021-02-05 | B24: CW | C24: -33.663103 | D24: =SUMPRODUCT(Risk_Inputs!B24:AJ24,Risk_Coefs!$B$2:$AJ$2) -> -1.4679131 | E24: =1/(1+EXP(-MAX(-25,MIN(25,D24)))) -> 0.18726001 | F24: =SUMPRODUCT(Risk_Inputs!B24:AJ24,Risk_Coefs!$B$3:$AJ$3) -> 7.5789464 | G24: =MAX(0,F24) -> 7.5789464 | H24: =(SUMPRODUCT(--ISNUMBER($E$2:$E$800),--($E$2:$E$800<E24))+(SUMPRODUCT(--ISNUMBER($E$2:$E$800),--($E$2:$E$800=E24))+1)/2)/COUNT($E$2:$E$800) -> 0.078848561 | I24: =(SUMPRODUCT(--ISNUMBER($G$2:$G$800),--($G$2:$G$800<G24))+(SUMPRODUCT(--ISNUMBER($G$2:$G$800),--($G$2:$G$800=G24))+1)/2)/COUNT($G$2:$G$800) -> 0.49561952 | J24: 18.371404 | K24: 8.5873433 | L24: 0.61890763 | M24: =IF(OR(B24="NW",COUNT(Risk_Rank_Keys!B24)=0),0.5,(SUMPRODUCT(--ISNUMBER(Risk_Rank_Keys!$B$2:$B$800),--(Risk_Rank_Keys!$B$2:$B$800<Risk_Rank_Keys!B24))+(SUMPRODUCT(--ISNUMBER(Risk_Rank_Keys!$B$2:$B$800),--(Risk_Rank_Keys!$B$2:$B$800=Risk_Rank_Keys!B24))+1)/2)/COUNT(Risk_Rank_Keys!$B$2:$B$800)) -> 0.77126918 | N24: =IF(OR(B24="NW",COUNT(Risk_Rank_Keys!C24)=0),0.5,(SUMPRODUCT(--ISNUMBER(Risk_Rank_Keys!$C$2:$C$800),--(Risk_Rank_Keys!$C$2:$C$800<Risk_Rank_Keys!C24))+(SUMPRODUCT(--ISNUMBER(Risk_Rank_Keys!$C$2:$C$800),--(Risk_Rank_Keys!$C$2:$C$800=Risk_Rank_Keys!C24))+1)/2)/COUNT(Risk_Rank_Keys!$C$2:$C$800)) -> 0.84100418 | O24: =IF(OR(B24="NW",COUNT(Risk_Rank_Keys!D24)=0),0.5,(SUMPRODUCT(--ISNUMBER(Risk_Rank_Keys!$D$2:$D$800),--(Risk_Rank_Keys!$D$2:$D$800<Risk_Rank_Keys!D24))+(SUMPRODUCT(--ISNUMBER(Risk_Rank_Keys!$D$2:$D$800),--(Risk_Rank_Keys!$D$2:$D$800=Risk_Rank_Keys!D24))+1)/2)/COUNT(Risk_Rank_Keys!$D$2:$D$800)) -> 0.9804742 | P24: =AVERAGE(M24:O24) -> 0.86424919 | Q24: =0.4*H24+0.4*I24+0.2*P24 -> 0.40263707 | R24: =PERCENTILE($Q$2:$Q$800,0.75) -> 0.66771572 | S24: =OR(Q24>=R24,AND(B24="CW",COUNT(J24:L24)<3)) -> FALSE | T24: 0.18726001 | U24: 7.5789464 | V24: 0.40263707 | W24: =Q24-V24 -> 0
A25: 2021-02-08 | B25: CW | C25: 57.129349 | D25: =SUMPRODUCT(Risk_Inputs!B25:AJ25,Risk_Coefs!$B$2:$AJ$2) -> -1.1363517 | E25: =1/(1+EXP(-MAX(-25,MIN(25,D25)))) -> 0.24299082 | F25: =SUMPRODUCT(Risk_Inputs!B25:AJ25,Risk_Coefs!$B$3:$AJ$3) -> 9.1953713 | G25: =MAX(0,F25) -> 9.1953713 | H25: =(SUMPRODUCT(--ISNUMBER($E$2:$E$800),--($E$2:$E$800<E25))+(SUMPRODUCT(--ISNUMBER($E$2:$E$800),--($E$2:$E$800=E25))+1)/2)/COUNT($E$2:$E$800) -> 0.23529412 | I25: =(SUMPRODUCT(--ISNUMBER($G$2:$G$800),--($G$2:$G$800<G25))+(SUMPRODUCT(--ISNUMBER($G$2:$G$800),--($G$2:$G$800=G25))+1)/2)/COUNT($G$2:$G$800) -> 0.70212766 | J25: 27.113598 | K25: 6.0065214 | L25: 0.51484469 | M25: =IF(OR(B25="NW",COUNT(Risk_Rank_Keys!B25)=0),0.5,(SUMPRODUCT(--ISNUMBER(Risk_Rank_Keys!$B$2:$B$800),--(Risk_Rank_Keys!$B$2:$B$800<Risk_Rank_Keys!B25))+(SUMPRODUCT(--ISNUMBER(Risk_Rank_Keys!$B$2:$B$800),--(Risk_Rank_Keys!$B$2:$B$800=Risk_Rank_Keys!B25))+1)/2)/COUNT(Risk_Rank_Keys!$B$2:$B$800)) -> 0.88563459 | N25: =IF(OR(B25="NW",COUNT(Risk_Rank_Keys!C25)=0),0.5,(SUMPRODUCT(--ISNUMBER(Risk_Rank_Keys!$C$2:$C$800),--(Risk_Rank_Keys!$C$2:$C$800<Risk_Rank_Keys!C25))+(SUMPRODUCT(--ISNUMBER(Risk_Rank_Keys!$C$2:$C$800),--(Risk_Rank_Keys!$C$2:$C$800=Risk_Rank_Keys!C25))+1)/2)/COUNT(Risk_Rank_Keys!$C$2:$C$800)) -> 0.74476987 | O25: =IF(OR(B25="NW",COUNT(Risk_Rank_Keys!D25)=0),0.5,(SUMPRODUCT(--ISNUMBER(Risk_Rank_Keys!$D$2:$D$800),--(Risk_Rank_Keys!$D$2:$D$800<Risk_Rank_Keys!D25))+(SUMPRODUCT(--ISNUMBER(Risk_Rank_Keys!$D$2:$D$800),--(Risk_Rank_Keys!$D$2:$D$800=Risk_Rank_Keys!D25))+1)/2)/COUNT(Risk_Rank_Keys!$D$2:$D$800)) -> 0.9595537 | P25: =AVERAGE(M25:O25) -> 0.86331939 | Q25: =0.4*H25+0.4*I25+0.2*P25 -> 0.54763259 | R25: =PERCENTILE($Q$2:$Q$800,0.75) -> 0.66771572 | S25: =OR(Q25>=R25,AND(B25="CW",COUNT(J25:L25)<3)) -> FALSE | T25: 0.24299082 | U25: 9.1953713 | V25: 0.54763259 | W25: =Q25-V25 -> 0
A26: 2021-02-09 | B26: CW | C26: 24.589284 | D26: =SUMPRODUCT(Risk_Inputs!B26:AJ26,Risk_Coefs!$B$2:$AJ$2) -> -1.3181206 | E26: =1/(1+EXP(-MAX(-25,MIN(25,D26)))) -> 0.21113115 | F26: =SUMPRODUCT(Risk_Inputs!B26:AJ26,Risk_Coefs!$B$3:$AJ$3) -> 5.060391 | G26: =MAX(0,F26) -> 5.060391 | H26: =(SUMPRODUCT(--ISNUMBER($E$2:$E$800),--($E$2:$E$800<E26))+(SUMPRODUCT(--ISNUMBER($E$2:$E$800),--($E$2:$E$800=E26))+1)/2)/COUNT($E$2:$E$800) -> 0.12515645 | I26: =(SUMPRODUCT(--ISNUMBER($G$2:$G$800),--($G$2:$G$800<G26))+(SUMPRODUCT(--ISNUMBER($G$2:$G$800),--($G$2:$G$800=G26))+1)/2)/COUNT($G$2:$G$800) -> 0.14392991 | J26: 12.952255 | K26: 9.4184028 | L26: 0.41232639 | M26: =IF(OR(B26="NW",COUNT(Risk_Rank_Keys!B26)=0),0.5,(SUMPRODUCT(--ISNUMBER(Risk_Rank_Keys!$B$2:$B$800),--(Risk_Rank_Keys!$B$2:$B$800<Risk_Rank_Keys!B26))+(SUMPRODUCT(--ISNUMBER(Risk_Rank_Keys!$B$2:$B$800),--(Risk_Rank_Keys!$B$2:$B$800=Risk_Rank_Keys!B26))+1)/2)/COUNT(Risk_Rank_Keys!$B$2:$B$800)) -> 0.63737796 | N26: =IF(OR(B26="NW",COUNT(Risk_Rank_Keys!C26)=0),0.5,(SUMPRODUCT(--ISNUMBER(Risk_Rank_Keys!$C$2:$C$800),--(Risk_Rank_Keys!$C$2:$C$800<Risk_Rank_Keys!C26))+(SUMPRODUCT(--ISNUMBER(Risk_Rank_Keys!$C$2:$C$800),--(Risk_Rank_Keys!$C$2:$C$800=Risk_Rank_Keys!C26))+1)/2)/COUNT(Risk_Rank_Keys!$C$2:$C$800)) -> 0.86331939 | O26: =IF(OR(B26="NW",COUNT(Risk_Rank_Keys!D26)=0),0.5,(SUMPRODUCT(--ISNUMBER(Risk_Rank_Keys!$D$2:$D$800),--(Risk_Rank_Keys!$D$2:$D$800<Risk_Rank_Keys!D26))+(SUMPRODUCT(--ISNUMBER(Risk_Rank_Keys!$D$2:$D$800),--(Risk_Rank_Keys!$D$2:$D$800=Risk_Rank_Keys!D26))+1)/2)/COUNT(Risk_Rank_Keys!$D$2:$D$800)) -> 0.88842399 | P26: =AVERAGE(M26:O26) -> 0.79637378 | Q26: =0.4*H26+0.4*I26+0.2*P26 -> 0.2669093 | R26: =PERCENTILE($Q$2:$Q$800,0.75) -> 0.66771572 | S26: =OR(Q26>=R26,AND(B26="CW",COUNT(J26:L26)<3)) -> FALSE | T26: 0.21113115 | U26: 5.060391 | V26: 0.2669093 | W26: =Q26-V26 -> 0
A27: 2021-02-10 | B27: NW | C27: 48.687314 | D27: =SUMPRODUCT(Risk_Inputs!B27:AJ27,Risk_Coefs!$B$2:$AJ$2) -> -0.42378312 | E27: =1/(1+EXP(-MAX(-25,MIN(25,D27)))) -> 0.39561184 | F27: =SUMPRODUCT(Risk_Inputs!B27:AJ27,Risk_Coefs!$B$3:$AJ$3) -> 13.923191 | G27: =MAX(0,F27) -> 13.923191 | H27: =(SUMPRODUCT(--ISNUMBER($E$2:$E$800),--($E$2:$E$800<E27))+(SUMPRODUCT(--ISNUMBER($E$2:$E$800),--($E$2:$E$800=E27))+1)/2)/COUNT($E$2:$E$800) -> 0.93241552 | I27: =(SUMPRODUCT(--ISNUMBER($G$2:$G$800),--($G$2:$G$800<G27))+(SUMPRODUCT(--ISNUMBER($G$2:$G$800),--($G$2:$G$800=G27))+1)/2)/COUNT($G$2:$G$800) -> 0.97246558 | M27: =IF(OR(B27="NW",COUNT(Risk_Rank_Keys!B27)=0),0.5,(SUMPRODUCT(--ISNUMBER(Risk_Rank_Keys!$B$2:$B$800),--(Risk_Rank_Keys!$B$2:$B$800<Risk_Rank_Keys!B27))+(SUMPRODUCT(--ISNUMBER(Risk_Rank_Keys!$B$2:$B$800),--(Risk_Rank_Keys!$B$2:$B$800=Risk_Rank_Keys!B27))+1)/2)/COUNT(Risk_Rank_Keys!$B$2:$B$800)) -> 0.5 | N27: =IF(OR(B27="NW",COUNT(Risk_Rank_Keys!C27)=0),0.5,(SUMPRODUCT(--ISNUMBER(Risk_Rank_Keys!$C$2:$C$800),--(Risk_Rank_Keys!$C$2:$C$800<Risk_Rank_Keys!C27))+(SUMPRODUCT(--ISNUMBER(Risk_Rank_Keys!$C$2:$C$800),--(Risk_Rank_Keys!$C$2:$C$800=Risk_Rank_Keys!C27))+1)/2)/COUNT(Risk_Rank_Keys!$C$2:$C$800)) -> 0.5 | O27: =IF(OR(B27="NW",COUNT(Risk_Rank_Keys!D27)=0),0.5,(SUMPRODUCT(--ISNUMBER(Risk_Rank_Keys!$D$2:$D$800),--(Risk_Rank_Keys!$D$2:$D$800<Risk_Rank_Keys!D27))+(SUMPRODUCT(--ISNUMBER(Risk_Rank_Keys!$D$2:$D$800),--(Risk_Rank_Keys!$D$2:$D$800=Risk_Rank_Keys!D27))+1)/2)/COUNT(Risk_Rank_Keys!$D$2:$D$800)) -> 0.5 | P27: =AVERAGE(M27:O27) -> 0.5 | Q27: =0.4*H27+0.4*I27+0.2*P27 -> 0.86195244 | R27: =PERCENTILE($Q$2:$Q$800,0.75) -> 0.66771572 | S27: =OR(Q27>=R27,AND(B27="CW",COUNT(J27:L27)<3)) -> TRUE | T27: 0.39561184 | U27: 13.923191 | V27: 0.86195244 | W27: =Q27-V27 -> 0
A28: 2021-02-11 | B28: CW | C28: 73.874482 | D28: =SUMPRODUCT(Risk_Inputs!B28:AJ28,Risk_Coefs!$B$2:$AJ$2) -> -0.99116311 | E28: =1/(1+EXP(-MAX(-25,MIN(25,D28)))) -> 0.2706824 | F28: =SUMPRODUCT(Risk_Inputs!B28:AJ28,Risk_Coefs!$B$3:$AJ$3) -> 8.4971484 | G28: =MAX(0,F28) -> 8.4971484 | H28: =(SUMPRODUCT(--ISNUMBER($E$2:$E$800),--($E$2:$E$800<E28))+(SUMPRODUCT(--ISNUMBER($E$2:$E$800),--($E$2:$E$800=E28))+1)/2)/COUNT($E$2:$E$800) -> 0.39549437 | I28: =(SUMPRODUCT(--ISNUMBER($G$2:$G$800),--($G$2:$G$800<G28))+(SUMPRODUCT(--ISNUMBER($G$2:$G$800),--($G$2:$G$800=G28))+1)/2)/COUNT($G$2:$G$800) -> 0.6020025 | J28: 10.214776 | K28: 4.7881356 | L28: 0.38135593 | M28: =IF(OR(B28="NW",COUNT(Risk_Rank_Keys!B28)=0),0.5,(SUMPRODUCT(--ISNUMBER(Risk_Rank_Keys!$B$2:$B$800),--(Risk_Rank_Keys!$B$2:$B$800<Risk_Rank_Keys!B28))+(SUMPRODUCT(--ISNUMBER(Risk_Rank_Keys!$B$2:$B$800),--(Risk_Rank_Keys!$B$2:$B$800=Risk_Rank_Keys!B28))+1)/2)/COUNT(Risk_Rank_Keys!$B$2:$B$800)) -> 0.51603905 | N28: =IF(OR(B28="NW",COUNT(Risk_Rank_Keys!C28)=0),0.5,(SUMPRODUCT(--ISNUMBER(Risk_Rank_Keys!$C$2:$C$800),--(Risk_Rank_Keys!$C$2:$C$800<Risk_Rank_Keys!C28))+(SUMPRODUCT(--ISNUMBER(Risk_Rank_Keys!$C$2:$C$800),--(Risk_Rank_Keys!$C$2:$C$800=Risk_Rank_Keys!C28))+1)/2)/COUNT(Risk_Rank_Keys!$C$2:$C$800)) -> 0.67224547 | O28: =IF(OR(B28="NW",COUNT(Risk_Rank_Keys!D28)=0),0.5,(SUMPRODUCT(--ISNUMBER(Risk_Rank_Keys!$D$2:$D$800),--(Risk_Rank_Keys!$D$2:$D$800<Risk_Rank_Keys!D28))+(SUMPRODUCT(--ISNUMBER(Risk_Rank_Keys!$D$2:$D$800),--(Risk_Rank_Keys!$D$2:$D$800=Risk_Rank_Keys!D28))+1)/2)/COUNT(Risk_Rank_Keys!$D$2:$D$800)) -> 0.86889819 | P28: =AVERAGE(M28:O28) -> 0.68572757 | Q28: =0.4*H28+0.4*I28+0.2*P28 -> 0.53614426 | R28: =PERCENTILE($Q$2:$Q$800,0.75) -> 0.66771572 | S28: =OR(Q28>=R28,AND(B28="CW",COUNT(J28:L28)<3)) -> FALSE | T28: 0.2706824 | U28: 8.4971484 | V28: 0.53614426 | W28: =Q28-V28 -> 0
A29: 2021-02-12 | B29: CW | C29: 34.587247 | D29: =SUMPRODUCT(Risk_Inputs!B29:AJ29,Risk_Coefs!$B$2:$AJ$2) -> -1.331405 | E29: =1/(1+EXP(-MAX(-25,MIN(25,D29)))) -> 0.20892706 | F29: =SUMPRODUCT(Risk_Inputs!B29:AJ29,Risk_Coefs!$B$3:$AJ$3) -> 6.557642 | G29: =MAX(0,F29) -> 6.557642 | H29: =(SUMPRODUCT(--ISNUMBER($E$2:$E$800),--($E$2:$E$800<E29))+(SUMPRODUCT(--ISNUMBER($E$2:$E$800),--($E$2:$E$800=E29))+1)/2)/COUNT($E$2:$E$800) -> 0.12015019 | I29: =(SUMPRODUCT(--ISNUMBER($G$2:$G$800),--($G$2:$G$800<G29))+(SUMPRODUCT(--ISNUMBER($G$2:$G$800),--($G$2:$G$800=G29))+1)/2)/COUNT($G$2:$G$800) -> 0.35419274 | J29: 5.8863571 | K29: 1.4448257 | L29: 0.505689 | M29: =IF(OR(B29="NW",COUNT(Risk_Rank_Keys!B29)=0),0.5,(SUMPRODUCT(--ISNUMBER(Risk_Rank_Keys!$B$2:$B$800),--(Risk_Rank_Keys!$B$2:$B$800<Risk_Rank_Keys!B29))+(SUMPRODUCT(--ISNUMBER(Risk_Rank_Keys!$B$2:$B$800),--(Risk_Rank_Keys!$B$2:$B$800=Risk_Rank_Keys!B29))+1)/2)/COUNT(Risk_Rank_Keys!$B$2:$B$800)) -> 0.21757322 | N29: =IF(OR(B29="NW",COUNT(Risk_Rank_Keys!C29)=0),0.5,(SUMPRODUCT(--ISNUMBER(Risk_Rank_Keys!$C$2:$C$800),--(Risk_Rank_Keys!$C$2:$C$800<Risk_Rank_Keys!C29))+(SUMPRODUCT(--ISNUMBER(Risk_Rank_Keys!$C$2:$C$800),--(Risk_Rank_Keys!$C$2:$C$800=Risk_Rank_Keys!C29))+1)/2)/COUNT(Risk_Rank_Keys!$C$2:$C$800)) -> 0.11854951 | O29: =IF(OR(B29="NW",COUNT(Risk_Rank_Keys!D29)=0),0.5,(SUMPRODUCT(--ISNUMBER(Risk_Rank_Keys!$D$2:$D$800),--(Risk_Rank_Keys!$D$2:$D$800<Risk_Rank_Keys!D29))+(SUMPRODUCT(--ISNUMBER(Risk_Rank_Keys!$D$2:$D$800),--(Risk_Rank_Keys!$D$2:$D$800=Risk_Rank_Keys!D29))+1)/2)/COUNT(Risk_Rank_Keys!$D$2:$D$800)) -> 0.9539749 | P29: =AVERAGE(M29:O29) -> 0.43003254 | Q29: =0.4*H29+0.4*I29+0.2*P29 -> 0.27574368 | R29: =PERCENTILE($Q$2:$Q$800,0.75) -> 0.66771572 | S29: =OR(Q29>=R29,AND(B29="CW",COUNT(J29:L29)<3)) -> FALSE | T29: 0.20892706 | U29: 6.557642 | V29: 0.27574368 | W29: =Q29-V29 -> 0
A30: 2021-02-16 | B30: CW | C30: 17.759223 | D30: =SUMPRODUCT(Risk_Inputs!B30:AJ30,Risk_Coefs!$B$2:$AJ$2) -> -1.0676191 | E30: =1/(1+EXP(-MAX(-25,MIN(25,D30)))) -> 0.25585613 | F30: =SUMPRODUCT(Risk_Inputs!B30:AJ30,Risk_Coefs!$B$3:$AJ$3) -> 5.0479009 | G30: =MAX(0,F30) -> 5.0479009 | H30: =(SUMPRODUCT(--ISNUMBER($E$2:$E$800),--($E$2:$E$800<E30))+(SUMPRODUCT(--ISNUMBER($E$2:$E$800),--($E$2:$E$800=E30))+1)/2)/COUNT($E$2:$E$800) -> 0.30162703 | I30: =(SUMPRODUCT(--ISNUMBER($G$2:$G$800),--($G$2:$G$800<G30))+(SUMPRODUCT(--ISNUMBER($G$2:$G$800),--($G$2:$G$800=G30))+1)/2)/COUNT($G$2:$G$800) -> 0.14017522 | J30: 7.2777366 | K30: 2.2838499 | L30: 0.29907558 | M30: =IF(OR(B30="NW",COUNT(Risk_Rank_Keys!B30)=0),0.5,(SUMPRODUCT(--ISNUMBER(Risk_Rank_Keys!$B$2:$B$800),--(Risk_Rank_Keys!$B$2:$B$800<Risk_Rank_Keys!B30))+(SUMPRODUCT(--ISNUMBER(Risk_Rank_Keys!$B$2:$B$800),--(Risk_Rank_Keys!$B$2:$B$800=Risk_Rank_Keys!B30))+1)/2)/COUNT(Risk_Rank_Keys!$B$2:$B$800)) -> 0.33472803 | N30: =IF(OR(B30="NW",COUNT(Risk_Rank_Keys!C30)=0),0.5,(SUMPRODUCT(--ISNUMBER(Risk_Rank_Keys!$C$2:$C$800),--(Risk_Rank_Keys!$C$2:$C$800<Risk_Rank_Keys!C30))+(SUMPRODUCT(--ISNUMBER(Risk_Rank_Keys!$C$2:$C$800),--(Risk_Rank_Keys!$C$2:$C$800=Risk_Rank_Keys!C30))+1)/2)/COUNT(Risk_Rank_Keys!$C$2:$C$800)) -> 0.33612273 | O30: =IF(OR(B30="NW",COUNT(Risk_Rank_Keys!D30)=0),0.5,(SUMPRODUCT(--ISNUMBER(Risk_Rank_Keys!$D$2:$D$800),--(Risk_Rank_Keys!$D$2:$D$800<Risk_Rank_Keys!D30))+(SUMPRODUCT(--ISNUMBER(Risk_Rank_Keys!$D$2:$D$800),--(Risk_Rank_Keys!$D$2:$D$800=Risk_Rank_Keys!D30))+1)/2)/COUNT(Risk_Rank_Keys!$D$2:$D$800)) -> 0.74476987 | P30: =AVERAGE(M30:O30) -> 0.47187355 | Q30: =0.4*H30+0.4*I30+0.2*P30 -> 0.27109561 | R30: =PERCENTILE($Q$2:$Q$800,0.75) -> 0.66771572 | S30: =OR(Q30>=R30,AND(B30="CW",COUNT(J30:L30)<3)) -> FALSE | T30: 0.25585613 | U30: 5.0479009 | V30: 0.27109561 | W30: =Q30-V30 -> 0
A31: 2021-02-17 | B31: CW | C31: -40.839714 | D31: =SUMPRODUCT(Risk_Inputs!B31:AJ31,Risk_Coefs!$B$2:$AJ$2) -> -0.93197116 | E31: =1/(1+EXP(-MAX(-25,MIN(25,D31)))) -> 0.28252498 | F31: =SUMPRODUCT(Risk_Inputs!B31:AJ31,Risk_Coefs!$B$3:$AJ$3) -> 6.7752354 | G31: =MAX(0,F31) -> 6.7752354 | H31: =(SUMPRODUCT(--ISNUMBER($E$2:$E$800),--($E$2:$E$800<E31))+(SUMPRODUCT(--ISNUMBER($E$2:$E$800),--($E$2:$E$800=E31))+1)/2)/COUNT($E$2:$E$800) -> 0.47309136 | I31: =(SUMPRODUCT(--ISNUMBER($G$2:$G$800),--($G$2:$G$800<G31))+(SUMPRODUCT(--ISNUMBER($G$2:$G$800),--($G$2:$G$800=G31))+1)/2)/COUNT($G$2:$G$800) -> 0.39048811 | J31: 9.23225 | K31: 2.3499524 | L31: 0.4763417 | M31: =IF(OR(B31="NW",COUNT(Risk_Rank_Keys!B31)=0),0.5,(SUMPRODUCT(--ISNUMBER(Risk_Rank_Keys!$B$2:$B$800),--(Risk_Rank_Keys!$B$2:$B$800<Risk_Rank_Keys!B31))+(SUMPRODUCT(--ISNUMBER(Risk_Rank_Keys!$B$2:$B$800),--(Risk_Rank_Keys!$B$2:$B$800=Risk_Rank_Keys!B31))+1)/2)/COUNT(Risk_Rank_Keys!$B$2:$B$800)) -> 0.45885635 | N31: =IF(OR(B31="NW",COUNT(Risk_Rank_Keys!C31)=0),0.5,(SUMPRODUCT(--ISNUMBER(Risk_Rank_Keys!$C$2:$C$800),--(Risk_Rank_Keys!$C$2:$C$800<Risk_Rank_Keys!C31))+(SUMPRODUCT(--ISNUMBER(Risk_Rank_Keys!$C$2:$C$800),--(Risk_Rank_Keys!$C$2:$C$800=Risk_Rank_Keys!C31))+1)/2)/COUNT(Risk_Rank_Keys!$C$2:$C$800)) -> 0.35146444 | O31: =IF(OR(B31="NW",COUNT(Risk_Rank_Keys!D31)=0),0.5,(SUMPRODUCT(--ISNUMBER(Risk_Rank_Keys!$D$2:$D$800),--(Risk_Rank_Keys!$D$2:$D$800<Risk_Rank_Keys!D31))+(SUMPRODUCT(--ISNUMBER(Risk_Rank_Keys!$D$2:$D$800),--(Risk_Rank_Keys!$D$2:$D$800=Risk_Rank_Keys!D31))+1)/2)/COUNT(Risk_Rank_Keys!$D$2:$D$800)) -> 0.94421199 | P31: =AVERAGE(M31:O31) -> 0.58484426 | Q31: =0.4*H31+0.4*I31+0.2*P31 -> 0.46240064 | R31: =PERCENTILE($Q$2:$Q$800,0.75) -> 0.66771572 | S31: =OR(Q31>=R31,AND(B31="CW",COUNT(J31:L31)<3)) -> FALSE | T31: 0.28252498 | U31: 6.7752354 | V31: 0.46240064 | W31: =Q31-V31 -> 0
A32: 2021-02-18 | B32: CW | C32: 31.684993 | D32: =SUMPRODUCT(Risk_Inputs!B32:AJ32,Risk_Coefs!$B$2:$AJ$2) -> -0.96796851 | E32: =1/(1+EXP(-MAX(-25,MIN(25,D32)))) -> 0.27528561 | F32: =SUMPRODUCT(Risk_Inputs!B32:AJ32,Risk_Coefs!$B$3:$AJ$3) -> 8.2989169 | G32: =MAX(0,F32) -> 8.2989169 | H32: =(SUMPRODUCT(--ISNUMBER($E$2:$E$800),--($E$2:$E$800<E32))+(SUMPRODUCT(--ISNUMBER($E$2:$E$800),--($E$2:$E$800=E32))+1)/2)/COUNT($E$2:$E$800) -> 0.42678348 | I32: =(SUMPRODUCT(--ISNUMBER($G$2:$G$800),--($G$2:$G$800<G32))+(SUMPRODUCT(--ISNUMBER($G$2:$G$800),--($G$2:$G$800=G32))+1)/2)/COUNT($G$2:$G$800) -> 0.57947434 | J32: 13.277768 | K32: 4.6783626 | L32: 0.43859649 | M32: =IF(OR(B32="NW",COUNT(Risk_Rank_Keys!B32)=0),0.5,(SUMPRODUCT(--ISNUMBER(Risk_Rank_Keys!$B$2:$B$800),--(Risk_Rank_Keys!$B$2:$B$800<Risk_Rank_Keys!B32))+(SUMPRODUCT(--ISNUMBER(Risk_Rank_Keys!$B$2:$B$800),--(Risk_Rank_Keys!$B$2:$B$800=Risk_Rank_Keys!B32))+1)/2)/COUNT(Risk_Rank_Keys!$B$2:$B$800)) -> 0.65271967 | N32: =IF(OR(B32="NW",COUNT(Risk_Rank_Keys!C32)=0),0.5,(SUMPRODUCT(--ISNUMBER(Risk_Rank_Keys!$C$2:$C$800),--(Risk_Rank_Keys!$C$2:$C$800<Risk_Rank_Keys!C32))+(SUMPRODUCT(--ISNUMBER(Risk_Rank_Keys!$C$2:$C$800),--(Risk_Rank_Keys!$C$2:$C$800=Risk_Rank_Keys!C32))+1)/2)/COUNT(Risk_Rank_Keys!$C$2:$C$800)) -> 0.66248257 | O32: =IF(OR(B32="NW",COUNT(Risk_Rank_Keys!D32)=0),0.5,(SUMPRODUCT(--ISNUMBER(Risk_Rank_Keys!$D$2:$D$800),--(Risk_Rank_Keys!$D$2:$D$800<Risk_Rank_Keys!D32))+(SUMPRODUCT(--ISNUMBER(Risk_Rank_Keys!$D$2:$D$800),--(Risk_Rank_Keys!$D$2:$D$800=Risk_Rank_Keys!D32))+1)/2)/COUNT(Risk_Rank_Keys!$D$2:$D$800)) -> 0.91213389 | P32: =AVERAGE(M32:O32) -> 0.74244537 | Q32: =0.4*H32+0.4*I32+0.2*P32 -> 0.5509922 | R32: =PERCENTILE($Q$2:$Q$800,0.75) -> 0.66771572 | S32: =OR(Q32>=R32,AND(B32="CW",COUNT(J32:L32)<3)) -> FALSE | T32: 0.27528561 | U32: 8.2989169 | V32: 0.5509922 | W32: =Q32-V32 -> 0
A33: 2021-02-19 | B33: CW | C33: -43.152314 | D33: =SUMPRODUCT(Risk_Inputs!B33:AJ33,Risk_Coefs!$B$2:$AJ$2) -> -1.4422134 | E33: =1/(1+EXP(-MAX(-25,MIN(25,D33)))) -> 0.19120283 | F33: =SUMPRODUCT(Risk_Inputs!B33:AJ33,Risk_Coefs!$B$3:$AJ$3) -> 4.5833101 | G33: =MAX(0,F33) -> 4.5833101 | H33: =(SUMPRODUCT(--ISNUMBER($E$2:$E$800),--($E$2:$E$800<E33))+(SUMPRODUCT(--ISNUMBER($E$2:$E$800),--($E$2:$E$800=E33))+1)/2)/COUNT($E$2:$E$800) -> 0.091364205 | I33: =(SUMPRODUCT(--ISNUMBER($G$2:$G$800),--($G$2:$G$800<G33))+(SUMPRODUCT(--ISNUMBER($G$2:$G$800),--($G$2:$G$800=G33))+1)/2)/COUNT($G$2:$G$800) -> 0.090112641 | J33: 24.591662 | K33: 3.9421587 | L33: 0.91237735 | M33: =IF(OR(B33="NW",COUNT(Risk_Rank_Keys!B33)=0),0.5,(SUMPRODUCT(--ISNUMBER(Risk_Rank_Keys!$B$2:$B$800),--(Risk_Rank_Keys!$B$2:$B$800<Risk_Rank_Keys!B33))+(SUMPRODUCT(--ISNUMBER(Risk_Rank_Keys!$B$2:$B$800),--(Risk_Rank_Keys!$B$2:$B$800=Risk_Rank_Keys!B33))+1)/2)/COUNT(Risk_Rank_Keys!$B$2:$B$800)) -> 0.85355649 | N33: =IF(OR(B33="NW",COUNT(Risk_Rank_Keys!C33)=0),0.5,(SUMPRODUCT(--ISNUMBER(Risk_Rank_Keys!$C$2:$C$800),--(Risk_Rank_Keys!$C$2:$C$800<Risk_Rank_Keys!C33))+(SUMPRODUCT(--ISNUMBER(Risk_Rank_Keys!$C$2:$C$800),--(Risk_Rank_Keys!$C$2:$C$800=Risk_Rank_Keys!C33))+1)/2)/COUNT(Risk_Rank_Keys!$C$2:$C$800)) -> 0.58856346 | O33: =IF(OR(B33="NW",COUNT(Risk_Rank_Keys!D33)=0),0.5,(SUMPRODUCT(--ISNUMBER(Risk_Rank_Keys!$D$2:$D$800),--(Risk_Rank_Keys!$D$2:$D$800<Risk_Rank_Keys!D33))+(SUMPRODUCT(--ISNUMBER(Risk_Rank_Keys!$D$2:$D$800),--(Risk_Rank_Keys!$D$2:$D$800=Risk_Rank_Keys!D33))+1)/2)/COUNT(Risk_Rank_Keys!$D$2:$D$800)) -> 0.9972106 | P33: =AVERAGE(M33:O33) -> 0.81311018 | Q33: =0.4*H33+0.4*I33+0.2*P33 -> 0.23521277 | R33: =PERCENTILE($Q$2:$Q$800,0.75) -> 0.66771572 | S33: =OR(Q33>=R33,AND(B33="CW",COUNT(J33:L33)<3)) -> FALSE | T33: 0.19120283 | U33: 4.5833101 | V33: 0.23521277 | W33: =Q33-V33 -> 0
A34: 2021-02-22 | B34: CW | C34: -26.685873 | D34: =SUMPRODUCT(Risk_Inputs!B34:AJ34,Risk_Coefs!$B$2:$AJ$2) -> -1.2122558 | E34: =1/(1+EXP(-MAX(-25,MIN(25,D34)))) -> 0.22930215 | F34: =SUMPRODUCT(Risk_Inputs!B34:AJ34,Risk_Coefs!$B$3:$AJ$3) -> 5.1477267 | G34: =MAX(0,F34) -> 5.1477267 | H34: =(SUMPRODUCT(--ISNUMBER($E$2:$E$800),--($E$2:$E$800<E34))+(SUMPRODUCT(--ISNUMBER($E$2:$E$800),--($E$2:$E$800=E34))+1)/2)/COUNT($E$2:$E$800) -> 0.1689612 | I34: =(SUMPRODUCT(--ISNUMBER($G$2:$G$800),--($G$2:$G$800<G34))+(SUMPRODUCT(--ISNUMBER($G$2:$G$800),--($G$2:$G$800=G34))+1)/2)/COUNT($G$2:$G$800) -> 0.15394243 | J34: 23.928002 | K34: 4.452902 | L34: 0.60894386 | M34: =IF(OR(B34="NW",COUNT(Risk_Rank_Keys!B34)=0),0.5,(SUMPRODUCT(--ISNUMBER(Risk_Rank_Keys!$B$2:$B$800),--(Risk_Rank_Keys!$B$2:$B$800<Risk_Rank_Keys!B34))+(SUMPRODUCT(--ISNUMBER(Risk_Rank_Keys!$B$2:$B$800),--(Risk_Rank_Keys!$B$2:$B$800=Risk_Rank_Keys!B34))+1)/2)/COUNT(Risk_Rank_Keys!$B$2:$B$800)) -> 0.84379358 | N34: =IF(OR(B34="NW",COUNT(Risk_Rank_Keys!C34)=0),0.5,(SUMPRODUCT(--ISNUMBER(Risk_Rank_Keys!$C$2:$C$800),--(Risk_Rank_Keys!$C$2:$C$800<Risk_Rank_Keys!C34))+(SUMPRODUCT(--ISNUMBER(Risk_Rank_Keys!$C$2:$C$800),--(Risk_Rank_Keys!$C$2:$C$800=Risk_Rank_Keys!C34))+1)/2)/COUNT(Risk_Rank_Keys!$C$2:$C$800)) -> 0.64156206 | O34: =IF(OR(B34="NW",COUNT(Risk_Rank_Keys!D34)=0),0.5,(SUMPRODUCT(--ISNUMBER(Risk_Rank_Keys!$D$2:$D$800),--(Risk_Rank_Keys!$D$2:$D$800<Risk_Rank_Keys!D34))+(SUMPRODUCT(--ISNUMBER(Risk_Rank_Keys!$D$2:$D$800),--(Risk_Rank_Keys!$D$2:$D$800=Risk_Rank_Keys!D34))+1)/2)/COUNT(Risk_Rank_Keys!$D$2:$D$800)) -> 0.9790795 | P34: =AVERAGE(M34:O34) -> 0.82147838 | Q34: =0.4*H34+0.4*I34+0.2*P34 -> 0.29345713 | R34: =PERCENTILE($Q$2:$Q$800,0.75) -> 0.66771572 | S34: =OR(Q34>=R34,AND(B34="CW",COUNT(J34:L34)<3)) -> FALSE | T34: 0.22930215 | U34: 5.1477267 | V34: 0.29345713 | W34: =Q34-V34 -> 0
A35: 2021-02-23 | B35: CW | C35: 32.421688 | D35: =SUMPRODUCT(Risk_Inputs!B35:AJ35,Risk_Coefs!$B$2:$AJ$2) -> -0.82078899 | E35: =1/(1+EXP(-MAX(-25,MIN(25,D35)))) -> 0.3055962 | F35: =SUMPRODUCT(Risk_Inputs!B35:AJ35,Risk_Coefs!$B$3:$AJ$3) -> 9.0714525 | G35: =MAX(0,F35) -> 9.0714525 | H35: =(SUMPRODUCT(--ISNUMBER($E$2:$E$800),--($E$2:$E$800<E35))+(SUMPRODUCT(--ISNUMBER($E$2:$E$800),--($E$2:$E$800=E35))+1)/2)/COUNT($E$2:$E$800) -> 0.59449312 | I35: =(SUMPRODUCT(--ISNUMBER($G$2:$G$800),--($G$2:$G$800<G35))+(SUMPRODUCT(--ISNUMBER($G$2:$G$800),--($G$2:$G$800=G35))+1)/2)/COUNT($G$2:$G$800) -> 0.68836045 | J35: 9.407947 | K35: 1.6845652 | L35: 0.42114129 | M35: =IF(OR(B35="NW",COUNT(Risk_Rank_Keys!B35)=0),0.5,(SUMPRODUCT(--ISNUMBER(Risk_Rank_Keys!$B$2:$B$800),--(Risk_Rank_Keys!$B$2:$B$800<Risk_Rank_Keys!B35))+(SUMPRODUCT(--ISNUMBER(Risk_Rank_Keys!$B$2:$B$800),--(Risk_Rank_Keys!$B$2:$B$800=Risk_Rank_Keys!B35))+1)/2)/COUNT(Risk_Rank_Keys!$B$2:$B$800)) -> 0.47140865 | N35: =IF(OR(B35="NW",COUNT(Risk_Rank_Keys!C35)=0),0.5,(SUMPRODUCT(--ISNUMBER(Risk_Rank_Keys!$C$2:$C$800),--(Risk_Rank_Keys!$C$2:$C$800<Risk_Rank_Keys!C35))+(SUMPRODUCT(--ISNUMBER(Risk_Rank_Keys!$C$2:$C$800),--(Risk_Rank_Keys!$C$2:$C$800=Risk_Rank_Keys!C35))+1)/2)/COUNT(Risk_Rank_Keys!$C$2:$C$800)) -> 0.18410042 | O35: =IF(OR(B35="NW",COUNT(Risk_Rank_Keys!D35)=0),0.5,(SUMPRODUCT(--ISNUMBER(Risk_Rank_Keys!$D$2:$D$800),--(Risk_Rank_Keys!$D$2:$D$800<Risk_Rank_Keys!D35))+(SUMPRODUCT(--ISNUMBER(Risk_Rank_Keys!$D$2:$D$800),--(Risk_Rank_Keys!$D$2:$D$800=Risk_Rank_Keys!D35))+1)/2)/COUNT(Risk_Rank_Keys!$D$2:$D$800)) -> 0.89818689 | P35: =AVERAGE(M35:O35) -> 0.51789865 | Q35: =0.4*H35+0.4*I35+0.2*P35 -> 0.61672116 | R35: =PERCENTILE($Q$2:$Q$800,0.75) -> 0.66771572 | S35: =OR(Q35>=R35,AND(B35="CW",COUNT(J35:L35)<3)) -> FALSE | T35: 0.3055962 | U35: 9.0714525 | V35: 0.61672116 | W35: =Q35-V35 -> 0
A36: 2021-02-24 | B36: CW | C36: 279.43684 | D36: =SUMPRODUCT(Risk_Inputs!B36:AJ36,Risk_Coefs!$B$2:$AJ$2) -> -1.3679138 | E36: =1/(1+EXP(-MAX(-25,MIN(25,D36)))) -> 0.20295711 | F36: =SUMPRODUCT(Risk_Inputs!B36:AJ36,Risk_Coefs!$B$3:$AJ$3) -> 4.1121012 | G36: =MAX(0,F36) -> 4.1121012 | H36: =(SUMPRODUCT(--ISNUMBER($E$2:$E$800),--($E$2:$E$800<E36))+(SUMPRODUCT(--ISNUMBER($E$2:$E$800),--($E$2:$E$800=E36))+1)/2)/COUNT($E$2:$E$800) -> 0.10763454 | I36: =(SUMPRODUCT(--ISNUMBER($G$2:$G$800),--($G$2:$G$800<G36))+(SUMPRODUCT(--ISNUMBER($G$2:$G$800),--($G$2:$G$800=G36))+1)/2)/COUNT($G$2:$G$800) -> 0.058823529 | J36: 18.363759 | K36: 10.077735 | L36: 0.44419767 | M36: =IF(OR(B36="NW",COUNT(Risk_Rank_Keys!B36)=0),0.5,(SUMPRODUCT(--ISNUMBER(Risk_Rank_Keys!$B$2:$B$800),--(Risk_Rank_Keys!$B$2:$B$800<Risk_Rank_Keys!B36))+(SUMPRODUCT(--ISNUMBER(Risk_Rank_Keys!$B$2:$B$800),--(Risk_Rank_Keys!$B$2:$B$800=Risk_Rank_Keys!B36))+1)/2)/COUNT(Risk_Rank_Keys!$B$2:$B$800)) -> 0.76987448 | N36: =IF(OR(B36="NW",COUNT(Risk_Rank_Keys!C36)=0),0.5,(SUMPRODUCT(--ISNUMBER(Risk_Rank_Keys!$C$2:$C$800),--(Risk_Rank_Keys!$C$2:$C$800<Risk_Rank_Keys!C36))+(SUMPRODUCT(--ISNUMBER(Risk_Rank_Keys!$C$2:$C$800),--(Risk_Rank_Keys!$C$2:$C$800=Risk_Rank_Keys!C36))+1)/2)/COUNT(Risk_Rank_Keys!$C$2:$C$800)) -> 0.88563459 | O36: =IF(OR(B36="NW",COUNT(Risk_Rank_Keys!D36)=0),0.5,(SUMPRODUCT(--ISNUMBER(Risk_Rank_Keys!$D$2:$D$800),--(Risk_Rank_Keys!$D$2:$D$800<Risk_Rank_Keys!D36))+(SUMPRODUCT(--ISNUMBER(Risk_Rank_Keys!$D$2:$D$800),--(Risk_Rank_Keys!$D$2:$D$800=Risk_Rank_Keys!D36))+1)/2)/COUNT(Risk_Rank_Keys!$D$2:$D$800)) -> 0.91771269 | P36: =AVERAGE(M36:O36) -> 0.85774059 | Q36: =0.4*H36+0.4*I36+0.2*P36 -> 0.23813135 | R36: =PERCENTILE($Q$2:$Q$800,0.75) -> 0.66771572 | S36: =OR(Q36>=R36,AND(B36="CW",COUNT(J36:L36)<3)) -> FALSE | T36: 0.20295711 | U36: 4.1121012 | V36: 0.23813135 | W36: =Q36-V36 -> 0
A37: 2021-02-25 | B37: CW | C37: 64.43832 | D37: =SUMPRODUCT(Risk_Inputs!B37:AJ37,Risk_Coefs!$B$2:$AJ$2) -> -1.4112946 | E37: =1/(1+EXP(-MAX(-25,MIN(25,D37)))) -> 0.19602994 | F37: =SUMPRODUCT(Risk_Inputs!B37:AJ37,Risk_Coefs!$B$3:$AJ$3) -> 7.2051459 | G37: =MAX(0,F37) -> 7.2051459 | H37: =(SUMPRODUCT(--ISNUMBER($E$2:$E$800),--($E$2:$E$800<E37))+(SUMPRODUCT(--ISNUMBER($E$2:$E$800),--($E$2:$E$800=E37))+1)/2)/COUNT($E$2:$E$800) -> 0.096370463 | I37: =(SUMPRODUCT(--ISNUMBER($G$2:$G$800),--($G$2:$G$800<G37))+(SUMPRODUCT(--ISNUMBER($G$2:$G$800),--($G$2:$G$800=G37))+1)/2)/COUNT($G$2:$G$800) -> 0.44555695 | J37: 30.737366 | K37: 23.691589 | L37: 0.46728972 | M37: =IF(OR(B37="NW",COUNT(Risk_Rank_Keys!B37)=0),0.5,(SUMPRODUCT(--ISNUMBER(Risk_Rank_Keys!$B$2:$B$800),--(Risk_Rank_Keys!$B$2:$B$800<Risk_Rank_Keys!B37))+(SUMPRODUCT(--ISNUMBER(Risk_Rank_Keys!$B$2:$B$800),--(Risk_Rank_Keys!$B$2:$B$800=Risk_Rank_Keys!B37))+1)/2)/COUNT(Risk_Rank_Keys!$B$2:$B$800)) -> 0.90655509 | N37: =IF(OR(B37="NW",COUNT(Risk_Rank_Keys!C37)=0),0.5,(SUMPRODUCT(--ISNUMBER(Risk_Rank_Keys!$C$2:$C$800),--(Risk_Rank_Keys!$C$2:$C$800<Risk_Rank_Keys!C37))+(SUMPRODUCT(--ISNUMBER(Risk_Rank_Keys!$C$2:$C$800),--(Risk_Rank_Keys!$C$2:$C$800=Risk_Rank_Keys!C37))+1)/2)/COUNT(Risk_Rank_Keys!$C$2:$C$800)) -> 0.9748954 | O37: =IF(OR(B37="NW",COUNT(Risk_Rank_Keys!D37)=0),0.5,(SUMPRODUCT(--ISNUMBER(Risk_Rank_Keys!$D$2:$D$800),--(Risk_Rank_Keys!$D$2:$D$800<Risk_Rank_Keys!D37))+(SUMPRODUCT(--ISNUMBER(Risk_Rank_Keys!$D$2:$D$800),--(Risk_Rank_Keys!$D$2:$D$800=Risk_Rank_Keys!D37))+1)/2)/COUNT(Risk_Rank_Keys!$D$2:$D$800)) -> 0.93584379 | P37: =AVERAGE(M37:O37) -> 0.93909809 | Q37: =0.4*H37+0.4*I37+0.2*P37 -> 0.40459058 | R37: =PERCENTILE($Q$2:$Q$800,0.75) -> 0.66771572 | S37: =OR(Q37>=R37,AND(B37="CW",COUNT(J37:L37)<3)) -> FALSE | T37: 0.19602994 | U37: 7.2051459 | V37: 0.40459058 | W37: =Q37-V37 -> 0
A38: 2021-02-26 | B38: CW | C38: -37.300896 | D38: =SUMPRODUCT(Risk_Inputs!B38:AJ38,Risk_Coefs!$B$2:$AJ$2) -> -1.1961027 | E38: =1/(1+EXP(-MAX(-25,MIN(25,D38)))) -> 0.23216925 | F38: =SUMPRODUCT(Risk_Inputs!B38:AJ38,Risk_Coefs!$B$3:$AJ$3) -> 4.7590229 | G38: =MAX(0,F38) -> 4.7590229 | H38: =(SUMPRODUCT(--ISNUMBER($E$2:$E$800),--($E$2:$E$800<E38))+(SUMPRODUCT(--ISNUMBER($E$2:$E$800),--($E$2:$E$800=E38))+1)/2)/COUNT($E$2:$E$800) -> 0.18523154 | I38: =(SUMPRODUCT(--ISNUMBER($G$2:$G$800),--($G$2:$G$800<G38))+(SUMPRODUCT(--ISNUMBER($G$2:$G$800),--($G$2:$G$800=G38))+1)/2)/COUNT($G$2:$G$800) -> 0.10513141 | J38: 19.738241 | K38: 3.4904494 | L38: 0.39851587 | M38: =IF(OR(B38="NW",COUNT(Risk_Rank_Keys!B38)=0),0.5,(SUMPRODUCT(--ISNUMBER(Risk_Rank_Keys!$B$2:$B$800),--(Risk_Rank_Keys!$B$2:$B$800<Risk_Rank_Keys!B38))+(SUMPRODUCT(--ISNUMBER(Risk_Rank_Keys!$B$2:$B$800),--(Risk_Rank_Keys!$B$2:$B$800=Risk_Rank_Keys!B38))+1)/2)/COUNT(Risk_Rank_Keys!$B$2:$B$800)) -> 0.78382148 | N38: =IF(OR(B38="NW",COUNT(Risk_Rank_Keys!C38)=0),0.5,(SUMPRODUCT(--ISNUMBER(Risk_Rank_Keys!$C$2:$C$800),--(Risk_Rank_Keys!$C$2:$C$800<Risk_Rank_Keys!C38))+(SUMPRODUCT(--ISNUMBER(Risk_Rank_Keys!$C$2:$C$800),--(Risk_Rank_Keys!$C$2:$C$800=Risk_Rank_Keys!C38))+1)/2)/COUNT(Risk_Rank_Keys!$C$2:$C$800)) -> 0.52580195 | O38: =IF(OR(B38="NW",COUNT(Risk_Rank_Keys!D38)=0),0.5,(SUMPRODUCT(--ISNUMBER(Risk_Rank_Keys!$D$2:$D$800),--(Risk_Rank_Keys!$D$2:$D$800<Risk_Rank_Keys!D38))+(SUMPRODUCT(--ISNUMBER(Risk_Rank_Keys!$D$2:$D$800),--(Risk_Rank_Keys!$D$2:$D$800=Risk_Rank_Keys!D38))+1)/2)/COUNT(Risk_Rank_Keys!$D$2:$D$800)) -> 0.88284519 | P38: =AVERAGE(M38:O38) -> 0.73082287 | Q38: =0.4*H38+0.4*I38+0.2*P38 -> 0.26230976 | R38: =PERCENTILE($Q$2:$Q$800,0.75) -> 0.66771572 | S38: =OR(Q38>=R38,AND(B38="CW",COUNT(J38:L38)<3)) -> FALSE | T38: 0.23216925 | U38: 4.7590229 | V38: 0.26230976 | W38: =Q38-V38 -> 0
A39: 2021-03-02 | B39: CW | C39: 78.624104 | D39: =SUMPRODUCT(Risk_Inputs!B39:AJ39,Risk_Coefs!$B$2:$AJ$2) -> -1.1689727 | E39: =1/(1+EXP(-MAX(-25,MIN(25,D39)))) -> 0.23704073 | F39: =SUMPRODUCT(Risk_Inputs!B39:AJ39,Risk_Coefs!$B$3:$AJ$3) -> 5.9511005 | G39: =MAX(0,F39) -> 5.9511005 | H39: =(SUMPRODUCT(--ISNUMBER($E$2:$E$800),--($E$2:$E$800<E39))+(SUMPRODUCT(--ISNUMBER($E$2:$E$800),--($E$2:$E$800=E39))+1)/2)/COUNT($E$2:$E$800) -> 0.20901126 | I39: =(SUMPRODUCT(--ISNUMBER($G$2:$G$800),--($G$2:$G$800<G39))+(SUMPRODUCT(--ISNUMBER($G$2:$G$800),--($G$2:$G$800=G39))+1)/2)/COUNT($G$2:$G$800) -> 0.26032541 | J39: 20.563695 | K39: 6.8834688 | L39: 0.41553749 | M39: =IF(OR(B39="NW",COUNT(Risk_Rank_Keys!B39)=0),0.5,(SUMPRODUCT(--ISNUMBER(Risk_Rank_Keys!$B$2:$B$800),--(Risk_Rank_Keys!$B$2:$B$800<Risk_Rank_Keys!B39))+(SUMPRODUCT(--ISNUMBER(Risk_Rank_Keys!$B$2:$B$800),--(Risk_Rank_Keys!$B$2:$B$800=Risk_Rank_Keys!B39))+1)/2)/COUNT(Risk_Rank_Keys!$B$2:$B$800)) -> 0.79637378 | N39: =IF(OR(B39="NW",COUNT(Risk_Rank_Keys!C39)=0),0.5,(SUMPRODUCT(--ISNUMBER(Risk_Rank_Keys!$C$2:$C$800),--(Risk_Rank_Keys!$C$2:$C$800<Risk_Rank_Keys!C39))+(SUMPRODUCT(--ISNUMBER(Risk_Rank_Keys!$C$2:$C$800),--(Risk_Rank_Keys!$C$2:$C$800=Risk_Rank_Keys!C39))+1)/2)/COUNT(Risk_Rank_Keys!$C$2:$C$800)) -> 0.78103208 | O39: =IF(OR(B39="NW",COUNT(Risk_Rank_Keys!D39)=0),0.5,(SUMPRODUCT(--ISNUMBER(Risk_Rank_Keys!$D$2:$D$800),--(Risk_Rank_Keys!$D$2:$D$800<Risk_Rank_Keys!D39))+(SUMPRODUCT(--ISNUMBER(Risk_Rank_Keys!$D$2:$D$800),--(Risk_Rank_Keys!$D$2:$D$800=Risk_Rank_Keys!D39))+1)/2)/COUNT(Risk_Rank_Keys!$D$2:$D$800)) -> 0.89260809 | P39: =AVERAGE(M39:O39) -> 0.82333798 | Q39: =0.4*H39+0.4*I39+0.2*P39 -> 0.35240226 | R39: =PERCENTILE($Q$2:$Q$800,0.75) -> 0.66771572 | S39: =OR(Q39>=R39,AND(B39="CW",COUNT(J39:L39)<3)) -> FALSE | T39: 0.23704073 | U39: 5.9511005 | V39: 0.35240226 | W39: =Q39-V39 -> 0
A40: 2021-03-03 | B40: NW | C40: -40.566162 | D40: =SUMPRODUCT(Risk_Inputs!B40:AJ40,Risk_Coefs!$B$2:$AJ$2) -> -0.2116814 | E40: =1/(1+EXP(-MAX(-25,MIN(25,D40)))) -> 0.44727638 | F40: =SUMPRODUCT(Risk_Inputs!B40:AJ40,Risk_Coefs!$B$3:$AJ$3) -> 14.949919 | G40: =MAX(0,F40) -> 14.949919 | H40: =(SUMPRODUCT(--ISNUMBER($E$2:$E$800),--($E$2:$E$800<E40))+(SUMPRODUCT(--ISNUMBER($E$2:$E$800),--($E$2:$E$800=E40))+1)/2)/COUNT($E$2:$E$800) -> 0.97997497 | I40: =(SUMPRODUCT(--ISNUMBER($G$2:$G$800),--($G$2:$G$800<G40))+(SUMPRODUCT(--ISNUMBER($G$2:$G$800),--($G$2:$G$800=G40))+1)/2)/COUNT($G$2:$G$800) -> 0.98372966 | M40: =IF(OR(B40="NW",COUNT(Risk_Rank_Keys!B40)=0),0.5,(SUMPRODUCT(--ISNUMBER(Risk_Rank_Keys!$B$2:$B$800),--(Risk_Rank_Keys!$B$2:$B$800<Risk_Rank_Keys!B40))+(SUMPRODUCT(--ISNUMBER(Risk_Rank_Keys!$B$2:$B$800),--(Risk_Rank_Keys!$B$2:$B$800=Risk_Rank_Keys!B40))+1)/2)/COUNT(Risk_Rank_Keys!$B$2:$B$800)) -> 0.5 | N40: =IF(OR(B40="NW",COUNT(Risk_Rank_Keys!C40)=0),0.5,(SUMPRODUCT(--ISNUMBER(Risk_Rank_Keys!$C$2:$C$800),--(Risk_Rank_Keys!$C$2:$C$800<Risk_Rank_Keys!C40))+(SUMPRODUCT(--ISNUMBER(Risk_Rank_Keys!$C$2:$C$800),--(Risk_Rank_Keys!$C$2:$C$800=Risk_Rank_Keys!C40))+1)/2)/COUNT(Risk_Rank_Keys!$C$2:$C$800)) -> 0.5 | O40: =IF(OR(B40="NW",COUNT(Risk_Rank_Keys!D40)=0),0.5,(SUMPRODUCT(--ISNUMBER(Risk_Rank_Keys!$D$2:$D$800),--(Risk_Rank_Keys!$D$2:$D$800<Risk_Rank_Keys!D40))+(SUMPRODUCT(--ISNUMBER(Risk_Rank_Keys!$D$2:$D$800),--(Risk_Rank_Keys!$D$2:$D$800=Risk_Rank_Keys!D40))+1)/2)/COUNT(Risk_Rank_Keys!$D$2:$D$800)) -> 0.5 | P40: =AVERAGE(M40:O40) -> 0.5 | Q40: =0.4*H40+0.4*I40+0.2*P40 -> 0.88548185 | R40: =PERCENTILE($Q$2:$Q$800,0.75) -> 0.66771572 | S40: =OR(Q40>=R40,AND(B40="CW",COUNT(J40:L40)<3)) -> TRUE | T40: 0.44727638 | U40: 14.949919 | V40: 0.88548185 | W40: =Q40-V40 -> 0
A41: 2021-03-04 | B41: CW | C41: 44.098416 | D41: =SUMPRODUCT(Risk_Inputs!B41:AJ41,Risk_Coefs!$B$2:$AJ$2) -> -0.82693892 | E41: =1/(1+EXP(-MAX(-25,MIN(25,D41)))) -> 0.30429271 | F41: =SUMPRODUCT(Risk_Inputs!B41:AJ41,Risk_Coefs!$B$3:$AJ$3) -> 7.9293593 | G41: =MAX(0,F41) -> 7.9293593 | H41: =(SUMPRODUCT(--ISNUMBER($E$2:$E$800),--($E$2:$E$800<E41))+(SUMPRODUCT(--ISNUMBER($E$2:$E$800),--($E$2:$E$800=E41))+1)/2)/COUNT($E$2:$E$800) -> 0.58698373 | I41: =(SUMPRODUCT(--ISNUMBER($G$2:$G$800),--($G$2:$G$800<G41))+(SUMPRODUCT(--ISNUMBER($G$2:$G$800),--($G$2:$G$800=G41))+1)/2)/COUNT($G$2:$G$800) -> 0.5281602 | J41: 14.249036 | K41: 5.544314 | L41: 0.48563335 | M41: =IF(OR(B41="NW",COUNT(Risk_Rank_Keys!B41)=0),0.5,(SUMPRODUCT(--ISNUMBER(Risk_Rank_Keys!$B$2:$B$800),--(Risk_Rank_Keys!$B$2:$B$800<Risk_Rank_Keys!B41))+(SUMPRODUCT(--ISNUMBER(Risk_Rank_Keys!$B$2:$B$800),--(Risk_Rank_Keys!$B$2:$B$800=Risk_Rank_Keys!B41))+1)/2)/COUNT(Risk_Rank_Keys!$B$2:$B$800)) -> 0.68200837 | N41: =IF(OR(B41="NW",COUNT(Risk_Rank_Keys!C41)=0),0.5,(SUMPRODUCT(--ISNUMBER(Risk_Rank_Keys!$C$2:$C$800),--(Risk_Rank_Keys!$C$2:$C$800<Risk_Rank_Keys!C41))+(SUMPRODUCT(--ISNUMBER(Risk_Rank_Keys!$C$2:$C$800),--(Risk_Rank_Keys!$C$2:$C$800=Risk_Rank_Keys!C41))+1)/2)/COUNT(Risk_Rank_Keys!$C$2:$C$800)) -> 0.72245467 | O41: =IF(OR(B41="NW",COUNT(Risk_Rank_Keys!D41)=0),0.5,(SUMPRODUCT(--ISNUMBER(Risk_Rank_Keys!$D$2:$D$800),--(Risk_Rank_Keys!$D$2:$D$800<Risk_Rank_Keys!D41))+(SUMPRODUCT(--ISNUMBER(Risk_Rank_Keys!$D$2:$D$800),--(Risk_Rank_Keys!$D$2:$D$800=Risk_Rank_Keys!D41))+1)/2)/COUNT(Risk_Rank_Keys!$D$2:$D$800)) -> 0.94560669 | P41: =AVERAGE(M41:O41) -> 0.78335658 | Q41: =0.4*H41+0.4*I41+0.2*P41 -> 0.60272889 | R41: =PERCENTILE($Q$2:$Q$800,0.75) -> 0.66771572 | S41: =OR(Q41>=R41,AND(B41="CW",COUNT(J41:L41)<3)) -> FALSE | T41: 0.30429271 | U41: 7.9293593 | V41: 0.60272889 | W41: =Q41-V41 -> 0
A42: 2021-03-05 | B42: CW | C42: 52.496681 | D42: =SUMPRODUCT(Risk_Inputs!B42:AJ42,Risk_Coefs!$B$2:$AJ$2) -> -1.7228228 | E42: =1/(1+EXP(-MAX(-25,MIN(25,D42)))) -> 0.15150793 | F42: =SUMPRODUCT(Risk_Inputs!B42:AJ42,Risk_Coefs!$B$3:$AJ$3) -> 7.2413661 | G42: =MAX(0,F42) -> 7.2413661 | H42: =(SUMPRODUCT(--ISNUMBER($E$2:$E$800),--($E$2:$E$800<E42))+(SUMPRODUCT(--ISNUMBER($E$2:$E$800),--($E$2:$E$800=E42))+1)/2)/COUNT($E$2:$E$800) -> 0.023779725 | I42: =(SUMPRODUCT(--ISNUMBER($G$2:$G$800),--($G$2:$G$800<G42))+(SUMPRODUCT(--ISNUMBER($G$2:$G$800),--($G$2:$G$800=G42))+1)/2)/COUNT($G$2:$G$800) -> 0.44806008 | J42: 52.152024 | K42: 9.9749202 | L42: 0.75239398 | M42: =IF(OR(B42="NW",COUNT(Risk_Rank_Keys!B42)=0),0.5,(SUMPRODUCT(--ISNUMBER(Risk_Rank_Keys!$B$2:$B$800),--(Risk_Rank_Keys!$B$2:$B$800<Risk_Rank_Keys!B42))+(SUMPRODUCT(--ISNUMBER(Risk_Rank_Keys!$B$2:$B$800),--(Risk_Rank_Keys!$B$2:$B$800=Risk_Rank_Keys!B42))+1)/2)/COUNT(Risk_Rank_Keys!$B$2:$B$800)) -> 0.9776848 | N42: =IF(OR(B42="NW",COUNT(Risk_Rank_Keys!C42)=0),0.5,(SUMPRODUCT(--ISNUMBER(Risk_Rank_Keys!$C$2:$C$800),--(Risk_Rank_Keys!$C$2:$C$800<Risk_Rank_Keys!C42))+(SUMPRODUCT(--ISNUMBER(Risk_Rank_Keys!$C$2:$C$800),--(Risk_Rank_Keys!$C$2:$C$800=Risk_Rank_Keys!C42))+1)/2)/COUNT(Risk_Rank_Keys!$C$2:$C$800)) -> 0.88145049 | O42: =IF(OR(B42="NW",COUNT(Risk_Rank_Keys!D42)=0),0.5,(SUMPRODUCT(--ISNUMBER(Risk_Rank_Keys!$D$2:$D$800),--(Risk_Rank_Keys!$D$2:$D$800<Risk_Rank_Keys!D42))+(SUMPRODUCT(--ISNUMBER(Risk_Rank_Keys!$D$2:$D$800),--(Risk_Rank_Keys!$D$2:$D$800=Risk_Rank_Keys!D42))+1)/2)/COUNT(Risk_Rank_Keys!$D$2:$D$800)) -> 0.9888424 | P42: =AVERAGE(M42:O42) -> 0.94932589 | Q42: =0.4*H42+0.4*I42+0.2*P42 -> 0.3786011 | R42: =PERCENTILE($Q$2:$Q$800,0.75) -> 0.66771572 | S42: =OR(Q42>=R42,AND(B42="CW",COUNT(J42:L42)<3)) -> FALSE | T42: 0.15150793 | U42: 7.2413661 | V42: 0.3786011 | W42: =Q42-V42 -> 0
A43: 2021-03-08 | B43: CW | C43: 49.877717 | D43: =SUMPRODUCT(Risk_Inputs!B43:AJ43,Risk_Coefs!$B$2:$AJ$2) -> -0.92172195 | E43: =1/(1+EXP(-MAX(-25,MIN(25,D43)))) -> 0.28460716 | F43: =SUMPRODUCT(Risk_Inputs!B43:AJ43,Risk_Coefs!$B$3:$AJ$3) -> 10.578484 | G43: =MAX(0,F43) -> 10.578484 | H43: =(SUMPRODUCT(--ISNUMBER($E$2:$E$800),--($E$2:$E$800<E43))+(SUMPRODUCT(--ISNUMBER($E$2:$E$800),--($E$2:$E$800=E43))+1)/2)/COUNT($E$2:$E$800) -> 0.4893617 | I43: =(SUMPRODUCT(--ISNUMBER($G$2:$G$800),--($G$2:$G$800<G43))+(SUMPRODUCT(--ISNUMBER($G$2:$G$800),--($G$2:$G$800=G43))+1)/2)/COUNT($G$2:$G$800) -> 0.84730914 | J43: 34.625578 | K43: 3.3057851 | L43: 0.26017753 | M43: =IF(OR(B43="NW",COUNT(Risk_Rank_Keys!B43)=0),0.5,(SUMPRODUCT(--ISNUMBER(Risk_Rank_Keys!$B$2:$B$800),--(Risk_Rank_Keys!$B$2:$B$800<Risk_Rank_Keys!B43))+(SUMPRODUCT(--ISNUMBER(Risk_Rank_Keys!$B$2:$B$800),--(Risk_Rank_Keys!$B$2:$B$800=Risk_Rank_Keys!B43))+1)/2)/COUNT(Risk_Rank_Keys!$B$2:$B$800)) -> 0.92329149 | N43: =IF(OR(B43="NW",COUNT(Risk_Rank_Keys!C43)=0),0.5,(SUMPRODUCT(--ISNUMBER(Risk_Rank_Keys!$C$2:$C$800),--(Risk_Rank_Keys!$C$2:$C$800<Risk_Rank_Keys!C43))+(SUMPRODUCT(--ISNUMBER(Risk_Rank_Keys!$C$2:$C$800),--(Risk_Rank_Keys!$C$2:$C$800=Risk_Rank_Keys!C43))+1)/2)/COUNT(Risk_Rank_Keys!$C$2:$C$800)) -> 0.50906555 | O43: =IF(OR(B43="NW",COUNT(Risk_Rank_Keys!D43)=0),0.5,(SUMPRODUCT(--ISNUMBER(Risk_Rank_Keys!$D$2:$D$800),--(Risk_Rank_Keys!$D$2:$D$800<Risk_Rank_Keys!D43))+(SUMPRODUCT(--ISNUMBER(Risk_Rank_Keys!$D$2:$D$800),--(Risk_Rank_Keys!$D$2:$D$800=Risk_Rank_Keys!D43))+1)/2)/COUNT(Risk_Rank_Keys!$D$2:$D$800)) -> 0.63319386 | P43: =AVERAGE(M43:O43) -> 0.68851697 | Q43: =0.4*H43+0.4*I43+0.2*P43 -> 0.67237173 | R43: =PERCENTILE($Q$2:$Q$800,0.75) -> 0.66771572 | S43: =OR(Q43>=R43,AND(B43="CW",COUNT(J43:L43)<3)) -> TRUE | T43: 0.28460716 | U43: 10.578484 | V43: 0.67237173 | W43: =Q43-V43 -> 0
A44: 2021-03-09 | B44: CW | C44: 50.94682 | D44: =SUMPRODUCT(Risk_Inputs!B44:AJ44,Risk_Coefs!$B$2:$AJ$2) -> -0.91276969 | E44: =1/(1+EXP(-MAX(-25,MIN(25,D44)))) -> 0.28643341 | F44: =SUMPRODUCT(Risk_Inputs!B44:AJ44,Risk_Coefs!$B$3:$AJ$3) -> 8.9795211 | G44: =MAX(0,F44) -> 8.9795211 | H44: =(SUMPRODUCT(--ISNUMBER($E$2:$E$800),--($E$2:$E$800<E44))+(SUMPRODUCT(--ISNUMBER($E$2:$E$800),--($E$2:$E$800=E44))+1)/2)/COUNT($E$2:$E$800) -> 0.50312891 | I44: =(SUMPRODUCT(--ISNUMBER($G$2:$G$800),--($G$2:$G$800<G44))+(SUMPRODUCT(--ISNUMBER($G$2:$G$800),--($G$2:$G$800=G44))+1)/2)/COUNT($G$2:$G$800) -> 0.67834793 | J44: 11.663083 | K44: 2.758287 | L44: 0.290346 | M44: =IF(OR(B44="NW",COUNT(Risk_Rank_Keys!B44)=0),0.5,(SUMPRODUCT(--ISNUMBER(Risk_Rank_Keys!$B$2:$B$800),--(Risk_Rank_Keys!$B$2:$B$800<Risk_Rank_Keys!B44))+(SUMPRODUCT(--ISNUMBER(Risk_Rank_Keys!$B$2:$B$800),--(Risk_Rank_Keys!$B$2:$B$800=Risk_Rank_Keys!B44))+1)/2)/COUNT(Risk_Rank_Keys!$B$2:$B$800)) -> 0.58577406 | N44: =IF(OR(B44="NW",COUNT(Risk_Rank_Keys!C44)=0),0.5,(SUMPRODUCT(--ISNUMBER(Risk_Rank_Keys!$C$2:$C$800),--(Risk_Rank_Keys!$C$2:$C$800<Risk_Rank_Keys!C44))+(SUMPRODUCT(--ISNUMBER(Risk_Rank_Keys!$C$2:$C$800),--(Risk_Rank_Keys!$C$2:$C$800=Risk_Rank_Keys!C44))+1)/2)/COUNT(Risk_Rank_Keys!$C$2:$C$800)) -> 0.43654114 | O44: =IF(OR(B44="NW",COUNT(Risk_Rank_Keys!D44)=0),0.5,(SUMPRODUCT(--ISNUMBER(Risk_Rank_Keys!$D$2:$D$800),--(Risk_Rank_Keys!$D$2:$D$800<Risk_Rank_Keys!D44))+(SUMPRODUCT(--ISNUMBER(Risk_Rank_Keys!$D$2:$D$800),--(Risk_Rank_Keys!$D$2:$D$800=Risk_Rank_Keys!D44))+1)/2)/COUNT(Risk_Rank_Keys!$D$2:$D$800)) -> 0.72524407 | P44: =AVERAGE(M44:O44) -> 0.58251976 | Q44: =0.4*H44+0.4*I44+0.2*P44 -> 0.58909469 | R44: =PERCENTILE($Q$2:$Q$800,0.75) -> 0.66771572 | S44: =OR(Q44>=R44,AND(B44="CW",COUNT(J44:L44)<3)) -> FALSE | T44: 0.28643341 | U44: 8.9795211 | V44: 0.58909469 | W44: =Q44-V44 -> 0
A45: 2021-03-10 | B45: CW | C45: 49.754415 | D45: =SUMPRODUCT(Risk_Inputs!B45:AJ45,Risk_Coefs!$B$2:$AJ$2) -> -0.97550284 | E45: =1/(1+EXP(-MAX(-25,MIN(25,D45)))) -> 0.27378503 | F45: =SUMPRODUCT(Risk_Inputs!B45:AJ45,Risk_Coefs!$B$3:$AJ$3) -> 6.3261241 | G45: =MAX(0,F45) -> 6.3261241 | H45: =(SUMPRODUCT(--ISNUMBER($E$2:$E$800),--($E$2:$E$800<E45))+(SUMPRODUCT(--ISNUMBER($E$2:$E$800),--($E$2:$E$800=E45))+1)/2)/COUNT($E$2:$E$800) -> 0.41426783 | I45: =(SUMPRODUCT(--ISNUMBER($G$2:$G$800),--($G$2:$G$800<G45))+(SUMPRODUCT(--ISNUMBER($G$2:$G$800),--($G$2:$G$800=G45))+1)/2)/COUNT($G$2:$G$800) -> 0.31539424 | J45: 4.4736401 | K45: 3.2189974 | L45: 0.36939314 | M45: =IF(OR(B45="NW",COUNT(Risk_Rank_Keys!B45)=0),0.5,(SUMPRODUCT(--ISNUMBER(Risk_Rank_Keys!$B$2:$B$800),--(Risk_Rank_Keys!$B$2:$B$800<Risk_Rank_Keys!B45))+(SUMPRODUCT(--ISNUMBER(Risk_Rank_Keys!$B$2:$B$800),--(Risk_Rank_Keys!$B$2:$B$800=Risk_Rank_Keys!B45))+1)/2)/COUNT(Risk_Rank_Keys!$B$2:$B$800)) -> 0.09762901 | N45: =IF(OR(B45="NW",COUNT(Risk_Rank_Keys!C45)=0),0.5,(SUMPRODUCT(--ISNUMBER(Risk_Rank_Keys!$C$2:$C$800),--(Risk_Rank_Keys!$C$2:$C$800<Risk_Rank_Keys!C45))+(SUMPRODUCT(--ISNUMBER(Risk_Rank_Keys!$C$2:$C$800),--(Risk_Rank_Keys!$C$2:$C$800=Risk_Rank_Keys!C45))+1)/2)/COUNT(Risk_Rank_Keys!$C$2:$C$800)) -> 0.49790795 | O45: =IF(OR(B45="NW",COUNT(Risk_Rank_Keys!D45)=0),0.5,(SUMPRODUCT(--ISNUMBER(Risk_Rank_Keys!$D$2:$D$800),--(Risk_Rank_Keys!$D$2:$D$800<Risk_Rank_Keys!D45))+(SUMPRODUCT(--ISNUMBER(Risk_Rank_Keys!$D$2:$D$800),--(Risk_Rank_Keys!$D$2:$D$800=Risk_Rank_Keys!D45))+1)/2)/COUNT(Risk_Rank_Keys!$D$2:$D$800)) -> 0.85495119 | P45: =AVERAGE(M45:O45) -> 0.48349605 | Q45: =0.4*H45+0.4*I45+0.2*P45 -> 0.38856404 | R45: =PERCENTILE($Q$2:$Q$800,0.75) -> 0.66771572 | S45: =OR(Q45>=R45,AND(B45="CW",COUNT(J45:L45)<3)) -> FALSE | T45: 0.27378503 | U45: 6.3261241 | V45: 0.38856404 | W45: =Q45-V45 -> 0
A46: 2021-03-16 | B46: CW | C46: 27.188149 | D46: =SUMPRODUCT(Risk_Inputs!B46:AJ46,Risk_Coefs!$B$2:$AJ$2) -> -1.1775951 | E46: =1/(1+EXP(-MAX(-25,MIN(25,D46)))) -> 0.23548488 | F46: =SUMPRODUCT(Risk_Inputs!B46:AJ46,Risk_Coefs!$B$3:$AJ$3) -> 5.2971239 | G46: =MAX(0,F46) -> 5.2971239 | H46: =(SUMPRODUCT(--ISNUMBER($E$2:$E$800),--($E$2:$E$800<E46))+(SUMPRODUCT(--ISNUMBER($E$2:$E$800),--($E$2:$E$800=E46))+1)/2)/COUNT($E$2:$E$800) -> 0.20275344 | I46: =(SUMPRODUCT(--ISNUMBER($G$2:$G$800),--($G$2:$G$800<G46))+(SUMPRODUCT(--ISNUMBER($G$2:$G$800),--($G$2:$G$800=G46))+1)/2)/COUNT($G$2:$G$800) -> 0.17021277 | J46: 12.804097 | K46: 2.4607113 | L46: 0.37220844 | M46: =IF(OR(B46="NW",COUNT(Risk_Rank_Keys!B46)=0),0.5,(SUMPRODUCT(--ISNUMBER(Risk_Rank_Keys!$B$2:$B$800),--(Risk_Rank_Keys!$B$2:$B$800<Risk_Rank_Keys!B46))+(SUMPRODUCT(--ISNUMBER(Risk_Rank_Keys!$B$2:$B$800),--(Risk_Rank_Keys!$B$2:$B$800=Risk_Rank_Keys!B46))+1)/2)/COUNT(Risk_Rank_Keys!$B$2:$B$800)) -> 0.62900976 | N46: =IF(OR(B46="NW",COUNT(Risk_Rank_Keys!C46)=0),0.5,(SUMPRODUCT(--ISNUMBER(Risk_Rank_Keys!$C$2:$C$800),--(Risk_Rank_Keys!$C$2:$C$800<Risk_Rank_Keys!C46))+(SUMPRODUCT(--ISNUMBER(Risk_Rank_Keys!$C$2:$C$800),--(Risk_Rank_Keys!$C$2:$C$800=Risk_Rank_Keys!C46))+1)/2)/COUNT(Risk_Rank_Keys!$C$2:$C$800)) -> 0.38075314 | O46: =IF(OR(B46="NW",COUNT(Risk_Rank_Keys!D46)=0),0.5,(SUMPRODUCT(--ISNUMBER(Risk_Rank_Keys!$D$2:$D$800),--(Risk_Rank_Keys!$D$2:$D$800<Risk_Rank_Keys!D46))+(SUMPRODUCT(--ISNUMBER(Risk_Rank_Keys!$D$2:$D$800),--(Risk_Rank_Keys!$D$2:$D$800=Risk_Rank_Keys!D46))+1)/2)/COUNT(Risk_Rank_Keys!$D$2:$D$800)) -> 0.85774059 | P46: =AVERAGE(M46:O46) -> 0.62250116 | Q46: =0.4*H46+0.4*I46+0.2*P46 -> 0.27368672 | R46: =PERCENTILE($Q$2:$Q$800,0.75) -> 0.66771572 | S46: =OR(Q46>=R46,AND(B46="CW",COUNT(J46:L46)<3)) -> FALSE | T46: 0.23548488 | U46: 5.2971239 | V46: 0.27368672 | W46: =Q46-V46 -> 0
A47: 2021-03-17 | B47: CW | C47: 33.453998 | D47: =SUMPRODUCT(Risk_Inputs!B47:AJ47,Risk_Coefs!$B$2:$AJ$2) -> -1.5662348 | E47: =1/(1+EXP(-MAX(-25,MIN(25,D47)))) -> 0.17275382 | F47: =SUMPRODUCT(Risk_Inputs!B47:AJ47,Risk_Coefs!$B$3:$AJ$3) -> 5.0923499 | G47: =MAX(0,F47) -> 5.0923499 | H47: =(SUMPRODUCT(--ISNUMBER($E$2:$E$800),--($E$2:$E$800<E47))+(SUMPRODUCT(--ISNUMBER($E$2:$E$800),--($E$2:$E$800=E47))+1)/2)/COUNT($E$2:$E$800) -> 0.046307885 | I47: =(SUMPRODUCT(--ISNUMBER($G$2:$G$800),--($G$2:$G$800<G47))+(SUMPRODUCT(--ISNUMBER($G$2:$G$800),--($G$2:$G$800=G47))+1)/2)/COUNT($G$2:$G$800) -> 0.14768461 | J47: 53.071322 | K47: 9.8265896 | L47: 0.45237497 | M47: =IF(OR(B47="NW",COUNT(Risk_Rank_Keys!B47)=0),0.5,(SUMPRODUCT(--ISNUMBER(Risk_Rank_Keys!$B$2:$B$800),--(Risk_Rank_Keys!$B$2:$B$800<Risk_Rank_Keys!B47))+(SUMPRODUCT(--ISNUMBER(Risk_Rank_Keys!$B$2:$B$800),--(Risk_Rank_Keys!$B$2:$B$800=Risk_Rank_Keys!B47))+1)/2)/COUNT(Risk_Rank_Keys!$B$2:$B$800)) -> 0.9804742 | N47: =IF(OR(B47="NW",COUNT(Risk_Rank_Keys!C47)=0),0.5,(SUMPRODUCT(--ISNUMBER(Risk_Rank_Keys!$C$2:$C$800),--(Risk_Rank_Keys!$C$2:$C$800<Risk_Rank_Keys!C47))+(SUMPRODUCT(--ISNUMBER(Risk_Rank_Keys!$C$2:$C$800),--(Risk_Rank_Keys!$C$2:$C$800=Risk_Rank_Keys!C47))+1)/2)/COUNT(Risk_Rank_Keys!$C$2:$C$800)) -> 0.87587169 | O47: =IF(OR(B47="NW",COUNT(Risk_Rank_Keys!D47)=0),0.5,(SUMPRODUCT(--ISNUMBER(Risk_Rank_Keys!$D$2:$D$800),--(Risk_Rank_Keys!$D$2:$D$800<Risk_Rank_Keys!D47))+(SUMPRODUCT(--ISNUMBER(Risk_Rank_Keys!$D$2:$D$800),--(Risk_Rank_Keys!$D$2:$D$800=Risk_Rank_Keys!D47))+1)/2)/COUNT(Risk_Rank_Keys!$D$2:$D$800)) -> 0.92329149 | P47: =AVERAGE(M47:O47) -> 0.92654579 | Q47: =0.4*H47+0.4*I47+0.2*P47 -> 0.26290615 | R47: =PERCENTILE($Q$2:$Q$800,0.75) -> 0.66771572 | S47: =OR(Q47>=R47,AND(B47="CW",COUNT(J47:L47)<3)) -> FALSE | T47: 0.17275382 | U47: 5.0923499 | V47: 0.26290615 | W47: =Q47-V47 -> 0
A48: 2021-03-18 | B48: CW | C48: 66.858155 | D48: =SUMPRODUCT(Risk_Inputs!B48:AJ48,Risk_Coefs!$B$2:$AJ$2) -> -1.7918647 | E48: =1/(1+EXP(-MAX(-25,MIN(25,D48)))) -> 0.14284425 | F48: =SUMPRODUCT(Risk_Inputs!B48:AJ48,Risk_Coefs!$B$3:$AJ$3) -> 4.9068025 | G48: =MAX(0,F48) -> 4.9068025 | H48: =(SUMPRODUCT(--ISNUMBER($E$2:$E$800),--($E$2:$E$800<E48))+(SUMPRODUCT(--ISNUMBER($E$2:$E$800),--($E$2:$E$800=E48))+1)/2)/COUNT($E$2:$E$800) -> 0.016270338 | I48: =(SUMPRODUCT(--ISNUMBER($G$2:$G$800),--($G$2:$G$800<G48))+(SUMPRODUCT(--ISNUMBER($G$2:$G$800),--($G$2:$G$800=G48))+1)/2)/COUNT($G$2:$G$800) -> 0.12515645 | J48: 40.447243 | K48: 19.061033 | L48: 0.37558685 | M48: =IF(OR(B48="NW",COUNT(Risk_Rank_Keys!B48)=0),0.5,(SUMPRODUCT(--ISNUMBER(Risk_Rank_Keys!$B$2:$B$800),--(Risk_Rank_Keys!$B$2:$B$800<Risk_Rank_Keys!B48))+(SUMPRODUCT(--ISNUMBER(Risk_Rank_Keys!$B$2:$B$800),--(Risk_Rank_Keys!$B$2:$B$800=Risk_Rank_Keys!B48))+1)/2)/COUNT(Risk_Rank_Keys!$B$2:$B$800)) -> 0.9553696 | N48: =IF(OR(B48="NW",COUNT(Risk_Rank_Keys!C48)=0),0.5,(SUMPRODUCT(--ISNUMBER(Risk_Rank_Keys!$C$2:$C$800),--(Risk_Rank_Keys!$C$2:$C$800<Risk_Rank_Keys!C48))+(SUMPRODUCT(--ISNUMBER(Risk_Rank_Keys!$C$2:$C$800),--(Risk_Rank_Keys!$C$2:$C$800=Risk_Rank_Keys!C48))+1)/2)/COUNT(Risk_Rank_Keys!$C$2:$C$800)) -> 0.958159 | O48: =IF(OR(B48="NW",COUNT(Risk_Rank_Keys!D48)=0),0.5,(SUMPRODUCT(--ISNUMBER(Risk_Rank_Keys!$D$2:$D$800),--(Risk_Rank_Keys!$D$2:$D$800<Risk_Rank_Keys!D48))+(SUMPRODUCT(--ISNUMBER(Risk_Rank_Keys!$D$2:$D$800),--(Risk_Rank_Keys!$D$2:$D$800=Risk_Rank_Keys!D48))+1)/2)/COUNT(Risk_Rank_Keys!$D$2:$D$800)) -> 0.86052999 | P48: =AVERAGE(M48:O48) -> 0.92468619 | Q48: =0.4*H48+0.4*I48+0.2*P48 -> 0.24150795 | R48: =PERCENTILE($Q$2:$Q$800,0.75) -> 0.66771572 | S48: =OR(Q48>=R48,AND(B48="CW",COUNT(J48:L48)<3)) -> FALSE | T48: 0.14284425 | U48: 4.9068025 | V48: 0.24150795 | W48: =Q48-V48 -> 0
A49: 2021-03-19 | B49: CW | C49: -33.845896 | D49: =SUMPRODUCT(Risk_Inputs!B49:AJ49,Risk_Coefs!$B$2:$AJ$2) -> -0.9876183 | E49: =1/(1+EXP(-MAX(-25,MIN(25,D49)))) -> 0.27138276 | F49: =SUMPRODUCT(Risk_Inputs!B49:AJ49,Risk_Coefs!$B$3:$AJ$3) -> 7.9437273 | G49: =MAX(0,F49) -> 7.9437273 | H49: =(SUMPRODUCT(--ISNUMBER($E$2:$E$800),--($E$2:$E$800<E49))+(SUMPRODUCT(--ISNUMBER($E$2:$E$800),--($E$2:$E$800=E49))+1)/2)/COUNT($E$2:$E$800) -> 0.39674593 | I49: =(SUMPRODUCT(--ISNUMBER($G$2:$G$800),--($G$2:$G$800<G49))+(SUMPRODUCT(--ISNUMBER($G$2:$G$800),--($G$2:$G$800=G49))+1)/2)/COUNT($G$2:$G$800) -> 0.53191489 | J49: 21.081033 | K49: 5.374968 | L49: 0.2687484 | M49: =IF(OR(B49="NW",COUNT(Risk_Rank_Keys!B49)=0),0.5,(SUMPRODUCT(--ISNUMBER(Risk_Rank_Keys!$B$2:$B$800),--(Risk_Rank_Keys!$B$2:$B$800<Risk_Rank_Keys!B49))+(SUMPRODUCT(--ISNUMBER(Risk_Rank_Keys!$B$2:$B$800),--(Risk_Rank_Keys!$B$2:$B$800=Risk_Rank_Keys!B49))+1)/2)/COUNT(Risk_Rank_Keys!$B$2:$B$800)) -> 0.81171548 | N49: =IF(OR(B49="NW",COUNT(Risk_Rank_Keys!C49)=0),0.5,(SUMPRODUCT(--ISNUMBER(Risk_Rank_Keys!$C$2:$C$800),--(Risk_Rank_Keys!$C$2:$C$800<Risk_Rank_Keys!C49))+(SUMPRODUCT(--ISNUMBER(Risk_Rank_Keys!$C$2:$C$800),--(Risk_Rank_Keys!$C$2:$C$800=Risk_Rank_Keys!C49))+1)/2)/COUNT(Risk_Rank_Keys!$C$2:$C$800)) -> 0.71408647 | O49: =IF(OR(B49="NW",COUNT(Risk_Rank_Keys!D49)=0),0.5,(SUMPRODUCT(--ISNUMBER(Risk_Rank_Keys!$D$2:$D$800),--(Risk_Rank_Keys!$D$2:$D$800<Risk_Rank_Keys!D49))+(SUMPRODUCT(--ISNUMBER(Risk_Rank_Keys!$D$2:$D$800),--(Risk_Rank_Keys!$D$2:$D$800=Risk_Rank_Keys!D49))+1)/2)/COUNT(Risk_Rank_Keys!$D$2:$D$800)) -> 0.66248257 | P49: =AVERAGE(M49:O49) -> 0.72942817 | Q49: =0.4*H49+0.4*I49+0.2*P49 -> 0.51734997 | R49: =PERCENTILE($Q$2:$Q$800,0.75) -> 0.66771572 | S49: =OR(Q49>=R49,AND(B49="CW",COUNT(J49:L49)<3)) -> FALSE | T49: 0.27138276 | U49: 7.9437273 | V49: 0.51734997 | W49: =Q49-V49 -> 0
A50: 2021-03-22 | B50: CW | C50: 57.521544 | D50: =SUMPRODUCT(Risk_Inputs!B50:AJ50,Risk_Coefs!$B$2:$AJ$2) -> -1.4442205 | E50: =1/(1+EXP(-MAX(-25,MIN(25,D50)))) -> 0.19089263 | F50: =SUMPRODUCT(Risk_Inputs!B50:AJ50,Risk_Coefs!$B$3:$AJ$3) -> 4.0103863 | G50: =MAX(0,F50) -> 4.0103863 | H50: =(SUMPRODUCT(--ISNUMBER($E$2:$E$800),--($E$2:$E$800<E50))+(SUMPRODUCT(--ISNUMBER($E$2:$E$800),--($E$2:$E$800=E50))+1)/2)/COUNT($E$2:$E$800) -> 0.090112641 | I50: =(SUMPRODUCT(--ISNUMBER($G$2:$G$800),--($G$2:$G$800<G50))+(SUMPRODUCT(--ISNUMBER($G$2:$G$800),--($G$2:$G$800=G50))+1)/2)/COUNT($G$2:$G$800) -> 0.052565707 | J50: 48.012631 | K50: 7.3976834 | L50: 0.43243243 | M50: =IF(OR(B50="NW",COUNT(Risk_Rank_Keys!B50)=0),0.5,(SUMPRODUCT(--ISNUMBER(Risk_Rank_Keys!$B$2:$B$800),--(Risk_Rank_Keys!$B$2:$B$800<Risk_Rank_Keys!B50))+(SUMPRODUCT(--ISNUMBER(Risk_Rank_Keys!$B$2:$B$800),--(Risk_Rank_Keys!$B$2:$B$800=Risk_Rank_Keys!B50))+1)/2)/COUNT(Risk_Rank_Keys!$B$2:$B$800)) -> 0.972106 | N50: =IF(OR(B50="NW",COUNT(Risk_Rank_Keys!C50)=0),0.5,(SUMPRODUCT(--ISNUMBER(Risk_Rank_Keys!$C$2:$C$800),--(Risk_Rank_Keys!$C$2:$C$800<Risk_Rank_Keys!C50))+(SUMPRODUCT(--ISNUMBER(Risk_Rank_Keys!$C$2:$C$800),--(Risk_Rank_Keys!$C$2:$C$800=Risk_Rank_Keys!C50))+1)/2)/COUNT(Risk_Rank_Keys!$C$2:$C$800)) -> 0.80055788 | O50: =IF(OR(B50="NW",COUNT(Risk_Rank_Keys!D50)=0),0.5,(SUMPRODUCT(--ISNUMBER(Risk_Rank_Keys!$D$2:$D$800),--(Risk_Rank_Keys!$D$2:$D$800<Risk_Rank_Keys!D50))+(SUMPRODUCT(--ISNUMBER(Risk_Rank_Keys!$D$2:$D$800),--(Risk_Rank_Keys!$D$2:$D$800=Risk_Rank_Keys!D50))+1)/2)/COUNT(Risk_Rank_Keys!$D$2:$D$800)) -> 0.90934449 | P50: =AVERAGE(M50:O50) -> 0.89400279 | Q50: =0.4*H50+0.4*I50+0.2*P50 -> 0.2358719 | R50: =PERCENTILE($Q$2:$Q$800,0.75) -> 0.66771572 | S50: =OR(Q50>=R50,AND(B50="CW",COUNT(J50:L50)<3)) -> FALSE | T50: 0.19089263 | U50: 4.0103863 | V50: 0.2358719 | W50: =Q50-V50 -> 0
A51: 2021-03-23 | B51: CW | C51: 50.160322 | D51: =SUMPRODUCT(Risk_Inputs!B51:AJ51,Risk_Coefs!$B$2:$AJ$2) -> -1.5341504 | E51: =1/(1+EXP(-MAX(-25,MIN(25,D51)))) -> 0.17738724 | F51: =SUMPRODUCT(Risk_Inputs!B51:AJ51,Risk_Coefs!$B$3:$AJ$3) -> 3.4020305 | G51: =MAX(0,F51) -> 3.4020305 | H51: =(SUMPRODUCT(--ISNUMBER($E$2:$E$800),--($E$2:$E$800<E51))+(SUMPRODUCT(--ISNUMBER($E$2:$E$800),--($E$2:$E$800=E51))+1)/2)/COUNT($E$2:$E$800) -> 0.060075094 | I51: =(SUMPRODUCT(--ISNUMBER($G$2:$G$800),--($G$2:$G$800<G51))+(SUMPRODUCT(--ISNUMBER($G$2:$G$800),--($G$2:$G$800=G51))+1)/2)/COUNT($G$2:$G$800) -> 0.03379224 | J51: 34.467814 | K51: 14.920758 | L51: 0.34789331 | M51: =IF(OR(B51="NW",COUNT(Risk_Rank_Keys!B51)=0),0.5,(SUMPRODUCT(--ISNUMBER(Risk_Rank_Keys!$B$2:$B$800),--(Risk_Rank_Keys!$B$2:$B$800<Risk_Rank_Keys!B51))+(SUMPRODUCT(--ISNUMBER(Risk_Rank_Keys!$B$2:$B$800),--(Risk_Rank_Keys!$B$2:$B$800=Risk_Rank_Keys!B51))+1)/2)/COUNT(Risk_Rank_Keys!$B$2:$B$800)) -> 0.92189679 | N51: =IF(OR(B51="NW",COUNT(Risk_Rank_Keys!C51)=0),0.5,(SUMPRODUCT(--ISNUMBER(Risk_Rank_Keys!$C$2:$C$800),--(Risk_Rank_Keys!$C$2:$C$800<Risk_Rank_Keys!C51))+(SUMPRODUCT(--ISNUMBER(Risk_Rank_Keys!$C$2:$C$800),--(Risk_Rank_Keys!$C$2:$C$800=Risk_Rank_Keys!C51))+1)/2)/COUNT(Risk_Rank_Keys!$C$2:$C$800)) -> 0.92747559 | O51: =IF(OR(B51="NW",COUNT(Risk_Rank_Keys!D51)=0),0.5,(SUMPRODUCT(--ISNUMBER(Risk_Rank_Keys!$D$2:$D$800),--(Risk_Rank_Keys!$D$2:$D$800<Risk_Rank_Keys!D51))+(SUMPRODUCT(--ISNUMBER(Risk_Rank_Keys!$D$2:$D$800),--(Risk_Rank_Keys!$D$2:$D$800=Risk_Rank_Keys!D51))+1)/2)/COUNT(Risk_Rank_Keys!$D$2:$D$800)) -> 0.83124128 | P51: =AVERAGE(M51:O51) -> 0.89353789 | Q51: =0.4*H51+0.4*I51+0.2*P51 -> 0.21625451 | R51: =PERCENTILE($Q$2:$Q$800,0.75) -> 0.66771572 | S51: =OR(Q51>=R51,AND(B51="CW",COUNT(J51:L51)<3)) -> FALSE | T51: 0.17738724 | U51: 3.4020305 | V51: 0.21625451 | W51: =Q51-V51 -> 0
A52: 2021-03-24 | B52: CW | C52: -37.220393 | D52: =SUMPRODUCT(Risk_Inputs!B52:AJ52,Risk_Coefs!$B$2:$AJ$2) -> -1.1503289 | E52: =1/(1+EXP(-MAX(-25,MIN(25,D52)))) -> 0.240429 | F52: =SUMPRODUCT(Risk_Inputs!B52:AJ52,Risk_Coefs!$B$3:$AJ$3) -> 5.4470357 | G52: =MAX(0,F52) -> 5.4470357 | H52: =(SUMPRODUCT(--ISNUMBER($E$2:$E$800),--($E$2:$E$800<E52))+(SUMPRODUCT(--ISNUMBER($E$2:$E$800),--($E$2:$E$800=E52))+1)/2)/COUNT($E$2:$E$800) -> 0.22653317 | I52: =(SUMPRODUCT(--ISNUMBER($G$2:$G$800),--($G$2:$G$800<G52))+(SUMPRODUCT(--ISNUMBER($G$2:$G$800),--($G$2:$G$800=G52))+1)/2)/COUNT($G$2:$G$800) -> 0.1902378 | J52: 24.05532 | K52: 17.18239 | L52: 0.30188679 | M52: =IF(OR(B52="NW",COUNT(Risk_Rank_Keys!B52)=0),0.5,(SUMPRODUCT(--ISNUMBER(Risk_Rank_Keys!$B$2:$B$800),--(Risk_Rank_Keys!$B$2:$B$800<Risk_Rank_Keys!B52))+(SUMPRODUCT(--ISNUMBER(Risk_Rank_Keys!$B$2:$B$800),--(Risk_Rank_Keys!$B$2:$B$800=Risk_Rank_Keys!B52))+1)/2)/COUNT(Risk_Rank_Keys!$B$2:$B$800)) -> 0.84518828 | N52: =IF(OR(B52="NW",COUNT(Risk_Rank_Keys!C52)=0),0.5,(SUMPRODUCT(--ISNUMBER(Risk_Rank_Keys!$C$2:$C$800),--(Risk_Rank_Keys!$C$2:$C$800<Risk_Rank_Keys!C52))+(SUMPRODUCT(--ISNUMBER(Risk_Rank_Keys!$C$2:$C$800),--(Risk_Rank_Keys!$C$2:$C$800=Risk_Rank_Keys!C52))+1)/2)/COUNT(Risk_Rank_Keys!$C$2:$C$800)) -> 0.94839609 | O52: =IF(OR(B52="NW",COUNT(Risk_Rank_Keys!D52)=0),0.5,(SUMPRODUCT(--ISNUMBER(Risk_Rank_Keys!$D$2:$D$800),--(Risk_Rank_Keys!$D$2:$D$800<Risk_Rank_Keys!D52))+(SUMPRODUCT(--ISNUMBER(Risk_Rank_Keys!$D$2:$D$800),--(Risk_Rank_Keys!$D$2:$D$800=Risk_Rank_Keys!D52))+1)/2)/COUNT(Risk_Rank_Keys!$D$2:$D$800)) -> 0.75034868 | P52: =AVERAGE(M52:O52) -> 0.84797768 | Q52: =0.4*H52+0.4*I52+0.2*P52 -> 0.33630392 | R52: =PERCENTILE($Q$2:$Q$800,0.75) -> 0.66771572 | S52: =OR(Q52>=R52,AND(B52="CW",COUNT(J52:L52)<3)) -> FALSE | T52: 0.240429 | U52: 5.4470357 | V52: 0.33630392 | W52: =Q52-V52 -> 0
... A80: 2021-05-24 | B80: CW | C80: 53.214645 | D80: =SUMPRODUCT(Risk_Inputs!B80:AJ80,Risk_Coefs!$B$2:$AJ$2) -> -0.82930351 | E80: =1/(1+EXP(-MAX(-25,MIN(25,D80)))) -> 0.30379236 | F80: =SUMPRODUCT(Risk_Inputs!B80:AJ80,Risk_Coefs!$B$3:$AJ$3) -> 6.5094641 | G80: =MAX(0,F80) -> 6.5094641 | H80: =(SUMPRODUCT(--ISNUMBER($E$2:$E$800),--($E$2:$E$800<E80))+(SUMPRODUCT(--ISNUMBER($E$2:$E$800),--($E$2:$E$800=E80))+1)/2)/COUNT($E$2:$E$800) -> 0.58573217 | I80: =(SUMPRODUCT(--ISNUMBER($G$2:$G$800),--($G$2:$G$800<G80))+(SUMPRODUCT(--ISNUMBER($G$2:$G$800),--($G$2:$G$800=G80))+1)/2)/COUNT($G$2:$G$800) -> 0.34418023 | J80: 12.946387 | K80: 2.126231 | L80: 0.38048344 | M80: =IF(OR(B80="NW",COUNT(Risk_Rank_Keys!B80)=0),0.5,(SUMPRODUCT(--ISNUMBER(Risk_Rank_Keys!$B$2:$B$800),--(Risk_Rank_Keys!$B$2:$B$800<Risk_Rank_Keys!B80))+(SUMPRODUCT(--ISNUMBER(Risk_Rank_Keys!$B$2:$B$800),--(Risk_Rank_Keys!$B$2:$B$800=Risk_Rank_Keys!B80))+1)/2)/COUNT(Risk_Rank_Keys!$B$2:$B$800)) -> 0.63598326 | N80: =IF(OR(B80="NW",COUNT(Risk_Rank_Keys!C80)=0),0.5,(SUMPRODUCT(--ISNUMBER(Risk_Rank_Keys!$C$2:$C$800),--(Risk_Rank_Keys!$C$2:$C$800<Risk_Rank_Keys!C80))+(SUMPRODUCT(--ISNUMBER(Risk_Rank_Keys!$C$2:$C$800),--(Risk_Rank_Keys!$C$2:$C$800=Risk_Rank_Keys!C80))+1)/2)/COUNT(Risk_Rank_Keys!$C$2:$C$800)) -> 0.29986053 | O80: =IF(OR(B80="NW",COUNT(Risk_Rank_Keys!D80)=0),0.5,(SUMPRODUCT(--ISNUMBER(Risk_Rank_Keys!$D$2:$D$800),--(Risk_Rank_Keys!$D$2:$D$800<Risk_Rank_Keys!D80))+(SUMPRODUCT(--ISNUMBER(Risk_Rank_Keys!$D$2:$D$800),--(Risk_Rank_Keys!$D$2:$D$800=Risk_Rank_Keys!D80))+1)/2)/COUNT(Risk_Rank_Keys!$D$2:$D$800)) -> 0.86471409 | P80: =AVERAGE(M80:O80) -> 0.60018596 | Q80: =0.4*H80+0.4*I80+0.2*P80 -> 0.49200215 | R80: =PERCENTILE($Q$2:$Q$800,0.75) -> 0.66771572 | S80: =OR(Q80>=R80,AND(B80="CW",COUNT(J80:L80)<3)) -> FALSE | T80: 0.30379236 | U80: 6.5094641 | V80: 0.49200215 | W80: =Q80-V80 -> 0
A81: 2021-05-26 | B81: NW | C81: -12.116713 | D81: =SUMPRODUCT(Risk_Inputs!B81:AJ81,Risk_Coefs!$B$2:$AJ$2) -> -0.53472045 | E81: =1/(1+EXP(-MAX(-25,MIN(25,D81)))) -> 0.36941659 | F81: =SUMPRODUCT(Risk_Inputs!B81:AJ81,Risk_Coefs!$B$3:$AJ$3) -> 11.250621 | G81: =MAX(0,F81) -> 11.250621 | H81: =(SUMPRODUCT(--ISNUMBER($E$2:$E$800),--($E$2:$E$800<E81))+(SUMPRODUCT(--ISNUMBER($E$2:$E$800),--($E$2:$E$800=E81))+1)/2)/COUNT($E$2:$E$800) -> 0.87108886 | I81: =(SUMPRODUCT(--ISNUMBER($G$2:$G$800),--($G$2:$G$800<G81))+(SUMPRODUCT(--ISNUMBER($G$2:$G$800),--($G$2:$G$800=G81))+1)/2)/COUNT($G$2:$G$800) -> 0.89612015 | M81: =IF(OR(B81="NW",COUNT(Risk_Rank_Keys!B81)=0),0.5,(SUMPRODUCT(--ISNUMBER(Risk_Rank_Keys!$B$2:$B$800),--(Risk_Rank_Keys!$B$2:$B$800<Risk_Rank_Keys!B81))+(SUMPRODUCT(--ISNUMBER(Risk_Rank_Keys!$B$2:$B$800),--(Risk_Rank_Keys!$B$2:$B$800=Risk_Rank_Keys!B81))+1)/2)/COUNT(Risk_Rank_Keys!$B$2:$B$800)) -> 0.5 | N81: =IF(OR(B81="NW",COUNT(Risk_Rank_Keys!C81)=0),0.5,(SUMPRODUCT(--ISNUMBER(Risk_Rank_Keys!$C$2:$C$800),--(Risk_Rank_Keys!$C$2:$C$800<Risk_Rank_Keys!C81))+(SUMPRODUCT(--ISNUMBER(Risk_Rank_Keys!$C$2:$C$800),--(Risk_Rank_Keys!$C$2:$C$800=Risk_Rank_Keys!C81))+1)/2)/COUNT(Risk_Rank_Keys!$C$2:$C$800)) -> 0.5 | O81: =IF(OR(B81="NW",COUNT(Risk_Rank_Keys!D81)=0),0.5,(SUMPRODUCT(--ISNUMBER(Risk_Rank_Keys!$D$2:$D$800),--(Risk_Rank_Keys!$D$2:$D$800<Risk_Rank_Keys!D81))+(SUMPRODUCT(--ISNUMBER(Risk_Rank_Keys!$D$2:$D$800),--(Risk_Rank_Keys!$D$2:$D$800=Risk_Rank_Keys!D81))+1)/2)/COUNT(Risk_Rank_Keys!$D$2:$D$800)) -> 0.5 | P81: =AVERAGE(M81:O81) -> 0.5 | Q81: =0.4*H81+0.4*I81+0.2*P81 -> 0.8068836 | R81: =PERCENTILE($Q$2:$Q$800,0.75) -> 0.66771572 | S81: =OR(Q81>=R81,AND(B81="CW",COUNT(J81:L81)<3)) -> TRUE | T81: 0.36941659 | U81: 11.250621 | V81: 0.8068836 | W81: =Q81-V81 -> 0
A82: 2021-05-27 | B82: CW | C82: 37.303337 | D82: =SUMPRODUCT(Risk_Inputs!B82:AJ82,Risk_Coefs!$B$2:$AJ$2) -> -1.6772678 | E82: =1/(1+EXP(-MAX(-25,MIN(25,D82)))) -> 0.15745759 | F82: =SUMPRODUCT(Risk_Inputs!B82:AJ82,Risk_Coefs!$B$3:$AJ$3) -> 4.4467707 | G82: =MAX(0,F82) -> 4.4467707 | H82: =(SUMPRODUCT(--ISNUMBER($E$2:$E$800),--($E$2:$E$800<E82))+(SUMPRODUCT(--ISNUMBER($E$2:$E$800),--($E$2:$E$800=E82))+1)/2)/COUNT($E$2:$E$800) -> 0.031289111 | I82: =(SUMPRODUCT(--ISNUMBER($G$2:$G$800),--($G$2:$G$800<G82))+(SUMPRODUCT(--ISNUMBER($G$2:$G$800),--($G$2:$G$800=G82))+1)/2)/COUNT($G$2:$G$800) -> 0.083854819 | J82: 15.779518 | K82: 28.497409 | L82: 0.51813472 | M82: =IF(OR(B82="NW",COUNT(Risk_Rank_Keys!B82)=0),0.5,(SUMPRODUCT(--ISNUMBER(Risk_Rank_Keys!$B$2:$B$800),--(Risk_Rank_Keys!$B$2:$B$800<Risk_Rank_Keys!B82))+(SUMPRODUCT(--ISNUMBER(Risk_Rank_Keys!$B$2:$B$800),--(Risk_Rank_Keys!$B$2:$B$800=Risk_Rank_Keys!B82))+1)/2)/COUNT(Risk_Rank_Keys!$B$2:$B$800)) -> 0.72384937 | N82: =IF(OR(B82="NW",COUNT(Risk_Rank_Keys!C82)=0),0.5,(SUMPRODUCT(--ISNUMBER(Risk_Rank_Keys!$C$2:$C$800),--(Risk_Rank_Keys!$C$2:$C$800<Risk_Rank_Keys!C82))+(SUMPRODUCT(--ISNUMBER(Risk_Rank_Keys!$C$2:$C$800),--(Risk_Rank_Keys!$C$2:$C$800=Risk_Rank_Keys!C82))+1)/2)/COUNT(Risk_Rank_Keys!$C$2:$C$800)) -> 0.9832636 | O82: =IF(OR(B82="NW",COUNT(Risk_Rank_Keys!D82)=0),0.5,(SUMPRODUCT(--ISNUMBER(Risk_Rank_Keys!$D$2:$D$800),--(Risk_Rank_Keys!$D$2:$D$800<Risk_Rank_Keys!D82))+(SUMPRODUCT(--ISNUMBER(Risk_Rank_Keys!$D$2:$D$800),--(Risk_Rank_Keys!$D$2:$D$800=Risk_Rank_Keys!D82))+1)/2)/COUNT(Risk_Rank_Keys!$D$2:$D$800)) -> 0.9609484 | P82: =AVERAGE(M82:O82) -> 0.88935379 | Q82: =0.4*H82+0.4*I82+0.2*P82 -> 0.22392833 | R82: =PERCENTILE($Q$2:$Q$800,0.75) -> 0.66771572 | S82: =OR(Q82>=R82,AND(B82="CW",COUNT(J82:L82)<3)) -> FALSE | T82: 0.15745759 | U82: 4.4467707 | V82: 0.22392833 | W82: =Q82-V82 -> 0
A83: 2021-05-28 | B83: CW | C83: 29.438158 | D83: =SUMPRODUCT(Risk_Inputs!B83:AJ83,Risk_Coefs!$B$2:$AJ$2) -> -1.2000195 | E83: =1/(1+EXP(-MAX(-25,MIN(25,D83)))) -> 0.23147174 | F83: =SUMPRODUCT(Risk_Inputs!B83:AJ83,Risk_Coefs!$B$3:$AJ$3) -> 8.1040251 | G83: =MAX(0,F83) -> 8.1040251 | H83: =(SUMPRODUCT(--ISNUMBER($E$2:$E$800),--($E$2:$E$800<E83))+(SUMPRODUCT(--ISNUMBER($E$2:$E$800),--($E$2:$E$800=E83))+1)/2)/COUNT($E$2:$E$800) -> 0.18147685 | I83: =(SUMPRODUCT(--ISNUMBER($G$2:$G$800),--($G$2:$G$800<G83))+(SUMPRODUCT(--ISNUMBER($G$2:$G$800),--($G$2:$G$800=G83))+1)/2)/COUNT($G$2:$G$800) -> 0.55444305 | J83: 6.3524165 | K83: 2.3067332 | L83: 0.27015794 | M83: =IF(OR(B83="NW",COUNT(Risk_Rank_Keys!B83)=0),0.5,(SUMPRODUCT(--ISNUMBER(Risk_Rank_Keys!$B$2:$B$800),--(Risk_Rank_Keys!$B$2:$B$800<Risk_Rank_Keys!B83))+(SUMPRODUCT(--ISNUMBER(Risk_Rank_Keys!$B$2:$B$800),--(Risk_Rank_Keys!$B$2:$B$800=Risk_Rank_Keys!B83))+1)/2)/COUNT(Risk_Rank_Keys!$B$2:$B$800)) -> 0.25662483 | N83: =IF(OR(B83="NW",COUNT(Risk_Rank_Keys!C83)=0),0.5,(SUMPRODUCT(--ISNUMBER(Risk_Rank_Keys!$C$2:$C$800),--(Risk_Rank_Keys!$C$2:$C$800<Risk_Rank_Keys!C83))+(SUMPRODUCT(--ISNUMBER(Risk_Rank_Keys!$C$2:$C$800),--(Risk_Rank_Keys!$C$2:$C$800=Risk_Rank_Keys!C83))+1)/2)/COUNT(Risk_Rank_Keys!$C$2:$C$800)) -> 0.34030683 | O83: =IF(OR(B83="NW",COUNT(Risk_Rank_Keys!D83)=0),0.5,(SUMPRODUCT(--ISNUMBER(Risk_Rank_Keys!$D$2:$D$800),--(Risk_Rank_Keys!$D$2:$D$800<Risk_Rank_Keys!D83))+(SUMPRODUCT(--ISNUMBER(Risk_Rank_Keys!$D$2:$D$800),--(Risk_Rank_Keys!$D$2:$D$800=Risk_Rank_Keys!D83))+1)/2)/COUNT(Risk_Rank_Keys!$D$2:$D$800)) -> 0.66806137 | P83: =AVERAGE(M83:O83) -> 0.42166434 | Q83: =0.4*H83+0.4*I83+0.2*P83 -> 0.37870083 | R83: =PERCENTILE($Q$2:$Q$800,0.75) -> 0.66771572 | S83: =OR(Q83>=R83,AND(B83="CW",COUNT(J83:L83)<3)) -> FALSE | T83: 0.23147174 | U83: 8.1040251 | V83: 0.37870083 | W83: =Q83-V83 -> 0
A84: 2021-06-01 | B84: CW | C84: -35.830199 | D84: =SUMPRODUCT(Risk_Inputs!B84:AJ84,Risk_Coefs!$B$2:$AJ$2) -> -1.3175561 | E84: =1/(1+EXP(-MAX(-25,MIN(25,D84)))) -> 0.21122518 | F84: =SUMPRODUCT(Risk_Inputs!B84:AJ84,Risk_Coefs!$B$3:$AJ$3) -> 4.7674975 | G84: =MAX(0,F84) -> 4.7674975 | H84: =(SUMPRODUCT(--ISNUMBER($E$2:$E$800),--($E$2:$E$800<E84))+(SUMPRODUCT(--ISNUMBER($E$2:$E$800),--($E$2:$E$800=E84))+1)/2)/COUNT($E$2:$E$800) -> 0.12640801 | I84: =(SUMPRODUCT(--ISNUMBER($G$2:$G$800),--($G$2:$G$800<G84))+(SUMPRODUCT(--ISNUMBER($G$2:$G$800),--($G$2:$G$800=G84))+1)/2)/COUNT($G$2:$G$800) -> 0.10888611 | J84: 4.2348412 | K84: 2.6654412 | L84: 0.39828431 | M84: =IF(OR(B84="NW",COUNT(Risk_Rank_Keys!B84)=0),0.5,(SUMPRODUCT(--ISNUMBER(Risk_Rank_Keys!$B$2:$B$800),--(Risk_Rank_Keys!$B$2:$B$800<Risk_Rank_Keys!B84))+(SUMPRODUCT(--ISNUMBER(Risk_Rank_Keys!$B$2:$B$800),--(Risk_Rank_Keys!$B$2:$B$800=Risk_Rank_Keys!B84))+1)/2)/COUNT(Risk_Rank_Keys!$B$2:$B$800)) -> 0.085076709 | N84: =IF(OR(B84="NW",COUNT(Risk_Rank_Keys!C84)=0),0.5,(SUMPRODUCT(--ISNUMBER(Risk_Rank_Keys!$C$2:$C$800),--(Risk_Rank_Keys!$C$2:$C$800<Risk_Rank_Keys!C84))+(SUMPRODUCT(--ISNUMBER(Risk_Rank_Keys!$C$2:$C$800),--(Risk_Rank_Keys!$C$2:$C$800=Risk_Rank_Keys!C84))+1)/2)/COUNT(Risk_Rank_Keys!$C$2:$C$800)) -> 0.42259414 | O84: =IF(OR(B84="NW",COUNT(Risk_Rank_Keys!D84)=0),0.5,(SUMPRODUCT(--ISNUMBER(Risk_Rank_Keys!$D$2:$D$800),--(Risk_Rank_Keys!$D$2:$D$800<Risk_Rank_Keys!D84))+(SUMPRODUCT(--ISNUMBER(Risk_Rank_Keys!$D$2:$D$800),--(Risk_Rank_Keys!$D$2:$D$800=Risk_Rank_Keys!D84))+1)/2)/COUNT(Risk_Rank_Keys!$D$2:$D$800)) -> 0.88145049 | P84: =AVERAGE(M84:O84) -> 0.46304045 | Q84: =0.4*H84+0.4*I84+0.2*P84 -> 0.18672574 | R84: =PERCENTILE($Q$2:$Q$800,0.75) -> 0.66771572 | S84: =OR(Q84>=R84,AND(B84="CW",COUNT(J84:L84)<3)) -> FALSE | T84: 0.21122518 | U84: 4.7674975 | V84: 0.18672574 | W84: =Q84-V84 -> 0
A85: 2021-06-02 | B85: CW | C85: 39.326065 | D85: =SUMPRODUCT(Risk_Inputs!B85:AJ85,Risk_Coefs!$B$2:$AJ$2) -> -1.2906298 | E85: =1/(1+EXP(-MAX(-25,MIN(25,D85)))) -> 0.21574622 | F85: =SUMPRODUCT(Risk_Inputs!B85:AJ85,Risk_Coefs!$B$3:$AJ$3) -> 5.229576 | G85: =MAX(0,F85) -> 5.229576 | H85: =(SUMPRODUCT(--ISNUMBER($E$2:$E$800),--($E$2:$E$800<E85))+(SUMPRODUCT(--ISNUMBER($E$2:$E$800),--($E$2:$E$800=E85))+1)/2)/COUNT($E$2:$E$800) -> 0.13141427 | I85: =(SUMPRODUCT(--ISNUMBER($G$2:$G$800),--($G$2:$G$800<G85))+(SUMPRODUCT(--ISNUMBER($G$2:$G$800),--($G$2:$G$800=G85))+1)/2)/COUNT($G$2:$G$800) -> 0.16145181 | J85: 8.6481551 | K85: 3.8709677 | L85: 0.37950664 | M85: =IF(OR(B85="NW",COUNT(Risk_Rank_Keys!B85)=0),0.5,(SUMPRODUCT(--ISNUMBER(Risk_Rank_Keys!$B$2:$B$800),--(Risk_Rank_Keys!$B$2:$B$800<Risk_Rank_Keys!B85))+(SUMPRODUCT(--ISNUMBER(Risk_Rank_Keys!$B$2:$B$800),--(Risk_Rank_Keys!$B$2:$B$800=Risk_Rank_Keys!B85))+1)/2)/COUNT(Risk_Rank_Keys!$B$2:$B$800)) -> 0.43235704 | N85: =IF(OR(B85="NW",COUNT(Risk_Rank_Keys!C85)=0),0.5,(SUMPRODUCT(--ISNUMBER(Risk_Rank_Keys!$C$2:$C$800),--(Risk_Rank_Keys!$C$2:$C$800<Risk_Rank_Keys!C85))+(SUMPRODUCT(--ISNUMBER(Risk_Rank_Keys!$C$2:$C$800),--(Risk_Rank_Keys!$C$2:$C$800=Risk_Rank_Keys!C85))+1)/2)/COUNT(Risk_Rank_Keys!$C$2:$C$800)) -> 0.58019526 | O85: =IF(OR(B85="NW",COUNT(Risk_Rank_Keys!D85)=0),0.5,(SUMPRODUCT(--ISNUMBER(Risk_Rank_Keys!$D$2:$D$800),--(Risk_Rank_Keys!$D$2:$D$800<Risk_Rank_Keys!D85))+(SUMPRODUCT(--ISNUMBER(Risk_Rank_Keys!$D$2:$D$800),--(Risk_Rank_Keys!$D$2:$D$800=Risk_Rank_Keys!D85))+1)/2)/COUNT(Risk_Rank_Keys!$D$2:$D$800)) -> 0.86331939 | P85: =AVERAGE(M85:O85) -> 0.62529056 | Q85: =0.4*H85+0.4*I85+0.2*P85 -> 0.24220455 | R85: =PERCENTILE($Q$2:$Q$800,0.75) -> 0.66771572 | S85: =OR(Q85>=R85,AND(B85="CW",COUNT(J85:L85)<3)) -> FALSE | T85: 0.21574622 | U85: 5.229576 | V85: 0.24220455 | W85: =Q85-V85 -> 0
A86: 2021-06-03 | B86: NW | C86: 19.407361 | D86: =SUMPRODUCT(Risk_Inputs!B86:AJ86,Risk_Coefs!$B$2:$AJ$2) -> -0.67710179 | E86: =1/(1+EXP(-MAX(-25,MIN(25,D86)))) -> 0.33690846 | F86: =SUMPRODUCT(Risk_Inputs!B86:AJ86,Risk_Coefs!$B$3:$AJ$3) -> 10.000966 | G86: =MAX(0,F86) -> 10.000966 | H86: =(SUMPRODUCT(--ISNUMBER($E$2:$E$800),--($E$2:$E$800<E86))+(SUMPRODUCT(--ISNUMBER($E$2:$E$800),--($E$2:$E$800=E86))+1)/2)/COUNT($E$2:$E$800) -> 0.76595745 | I86: =(SUMPRODUCT(--ISNUMBER($G$2:$G$800),--($G$2:$G$800<G86))+(SUMPRODUCT(--ISNUMBER($G$2:$G$800),--($G$2:$G$800=G86))+1)/2)/COUNT($G$2:$G$800) -> 0.78973717 | M86: =IF(OR(B86="NW",COUNT(Risk_Rank_Keys!B86)=0),0.5,(SUMPRODUCT(--ISNUMBER(Risk_Rank_Keys!$B$2:$B$800),--(Risk_Rank_Keys!$B$2:$B$800<Risk_Rank_Keys!B86))+(SUMPRODUCT(--ISNUMBER(Risk_Rank_Keys!$B$2:$B$800),--(Risk_Rank_Keys!$B$2:$B$800=Risk_Rank_Keys!B86))+1)/2)/COUNT(Risk_Rank_Keys!$B$2:$B$800)) -> 0.5 | N86: =IF(OR(B86="NW",COUNT(Risk_Rank_Keys!C86)=0),0.5,(SUMPRODUCT(--ISNUMBER(Risk_Rank_Keys!$C$2:$C$800),--(Risk_Rank_Keys!$C$2:$C$800<Risk_Rank_Keys!C86))+(SUMPRODUCT(--ISNUMBER(Risk_Rank_Keys!$C$2:$C$800),--(Risk_Rank_Keys!$C$2:$C$800=Risk_Rank_Keys!C86))+1)/2)/COUNT(Risk_Rank_Keys!$C$2:$C$800)) -> 0.5 | O86: =IF(OR(B86="NW",COUNT(Risk_Rank_Keys!D86)=0),0.5,(SUMPRODUCT(--ISNUMBER(Risk_Rank_Keys!$D$2:$D$800),--(Risk_Rank_Keys!$D$2:$D$800<Risk_Rank_Keys!D86))+(SUMPRODUCT(--ISNUMBER(Risk_Rank_Keys!$D$2:$D$800),--(Risk_Rank_Keys!$D$2:$D$800=Risk_Rank_Keys!D86))+1)/2)/COUNT(Risk_Rank_Keys!$D$2:$D$800)) -> 0.5 | P86: =AVERAGE(M86:O86) -> 0.5 | Q86: =0.4*H86+0.4*I86+0.2*P86 -> 0.72227785 | R86: =PERCENTILE($Q$2:$Q$800,0.75) -> 0.66771572 | S86: =OR(Q86>=R86,AND(B86="CW",COUNT(J86:L86)<3)) -> TRUE | T86: 0.33690846 | U86: 10.000966 | V86: 0.72227785 | W86: =Q86-V86 -> 0
A87: 2021-06-04 | B87: CW | C87: 30.237081 | D87: =SUMPRODUCT(Risk_Inputs!B87:AJ87,Risk_Coefs!$B$2:$AJ$2) -> -1.4979507 | E87: =1/(1+EXP(-MAX(-25,MIN(25,D87)))) -> 0.18273137 | F87: =SUMPRODUCT(Risk_Inputs!B87:AJ87,Risk_Coefs!$B$3:$AJ$3) -> 5.4030097 | G87: =MAX(0,F87) -> 5.4030097 | H87: =(SUMPRODUCT(--ISNUMBER($E$2:$E$800),--($E$2:$E$800<E87))+(SUMPRODUCT(--ISNUMBER($E$2:$E$800),--($E$2:$E$800=E87))+1)/2)/COUNT($E$2:$E$800) -> 0.07008761 | I87: =(SUMPRODUCT(--ISNUMBER($G$2:$G$800),--($G$2:$G$800<G87))+(SUMPRODUCT(--ISNUMBER($G$2:$G$800),--($G$2:$G$800=G87))+1)/2)/COUNT($G$2:$G$800) -> 0.1864831 | J87: 20.813943 | K87: 8.7549494 | L87: 0.41794985 | M87: =IF(OR(B87="NW",COUNT(Risk_Rank_Keys!B87)=0),0.5,(SUMPRODUCT(--ISNUMBER(Risk_Rank_Keys!$B$2:$B$800),--(Risk_Rank_Keys!$B$2:$B$800<Risk_Rank_Keys!B87))+(SUMPRODUCT(--ISNUMBER(Risk_Rank_Keys!$B$2:$B$800),--(Risk_Rank_Keys!$B$2:$B$800=Risk_Rank_Keys!B87))+1)/2)/COUNT(Risk_Rank_Keys!$B$2:$B$800)) -> 0.80613668 | N87: =IF(OR(B87="NW",COUNT(Risk_Rank_Keys!C87)=0),0.5,(SUMPRODUCT(--ISNUMBER(Risk_Rank_Keys!$C$2:$C$800),--(Risk_Rank_Keys!$C$2:$C$800<Risk_Rank_Keys!C87))+(SUMPRODUCT(--ISNUMBER(Risk_Rank_Keys!$C$2:$C$800),--(Risk_Rank_Keys!$C$2:$C$800=Risk_Rank_Keys!C87))+1)/2)/COUNT(Risk_Rank_Keys!$C$2:$C$800)) -> 0.84379358 | O87: =IF(OR(B87="NW",COUNT(Risk_Rank_Keys!D87)=0),0.5,(SUMPRODUCT(--ISNUMBER(Risk_Rank_Keys!$D$2:$D$800),--(Risk_Rank_Keys!$D$2:$D$800<Risk_Rank_Keys!D87))+(SUMPRODUCT(--ISNUMBER(Risk_Rank_Keys!$D$2:$D$800),--(Risk_Rank_Keys!$D$2:$D$800=Risk_Rank_Keys!D87))+1)/2)/COUNT(Risk_Rank_Keys!$D$2:$D$800)) -> 0.89539749 | P87: =AVERAGE(M87:O87) -> 0.84844258 | Q87: =0.4*H87+0.4*I87+0.2*P87 -> 0.2723168 | R87: =PERCENTILE($Q$2:$Q$800,0.75) -> 0.66771572 | S87: =OR(Q87>=R87,AND(B87="CW",COUNT(J87:L87)<3)) -> FALSE | T87: 0.18273137 | U87: 5.4030097 | V87: 0.2723168 | W87: =Q87-V87 -> 0
A88: 2021-06-07 | B88: CW | C88: 9.3183941 | D88: =SUMPRODUCT(Risk_Inputs!B88:AJ88,Risk_Coefs!$B$2:$AJ$2) -> -0.55138857 | E88: =1/(1+EXP(-MAX(-25,MIN(25,D88)))) -> 0.36554231 | F88: =SUMPRODUCT(Risk_Inputs!B88:AJ88,Risk_Coefs!$B$3:$AJ$3) -> 10.044806 | G88: =MAX(0,F88) -> 10.044806 | H88: =(SUMPRODUCT(--ISNUMBER($E$2:$E$800),--($E$2:$E$800<E88))+(SUMPRODUCT(--ISNUMBER($E$2:$E$800),--($E$2:$E$800=E88))+1)/2)/COUNT($E$2:$E$800) -> 0.86232791 | I88: =(SUMPRODUCT(--ISNUMBER($G$2:$G$800),--($G$2:$G$800<G88))+(SUMPRODUCT(--ISNUMBER($G$2:$G$800),--($G$2:$G$800=G88))+1)/2)/COUNT($G$2:$G$800) -> 0.79349186 | J88: 6.2351676 | K88: 1.3245033 | L88: 0.13796909 | M88: =IF(OR(B88="NW",COUNT(Risk_Rank_Keys!B88)=0),0.5,(SUMPRODUCT(--ISNUMBER(Risk_Rank_Keys!$B$2:$B$800),--(Risk_Rank_Keys!$B$2:$B$800<Risk_Rank_Keys!B88))+(SUMPRODUCT(--ISNUMBER(Risk_Rank_Keys!$B$2:$B$800),--(Risk_Rank_Keys!$B$2:$B$800=Risk_Rank_Keys!B88))+1)/2)/COUNT(Risk_Rank_Keys!$B$2:$B$800)) -> 0.24407252 | N88: =IF(OR(B88="NW",COUNT(Risk_Rank_Keys!C88)=0),0.5,(SUMPRODUCT(--ISNUMBER(Risk_Rank_Keys!$C$2:$C$800),--(Risk_Rank_Keys!$C$2:$C$800<Risk_Rank_Keys!C88))+(SUMPRODUCT(--ISNUMBER(Risk_Rank_Keys!$C$2:$C$800),--(Risk_Rank_Keys!$C$2:$C$800=Risk_Rank_Keys!C88))+1)/2)/COUNT(Risk_Rank_Keys!$C$2:$C$800)) -> 0.089260809 | O88: =IF(OR(B88="NW",COUNT(Risk_Rank_Keys!D88)=0),0.5,(SUMPRODUCT(--ISNUMBER(Risk_Rank_Keys!$D$2:$D$800),--(Risk_Rank_Keys!$D$2:$D$800<Risk_Rank_Keys!D88))+(SUMPRODUCT(--ISNUMBER(Risk_Rank_Keys!$D$2:$D$800),--(Risk_Rank_Keys!$D$2:$D$800=Risk_Rank_Keys!D88))+1)/2)/COUNT(Risk_Rank_Keys!$D$2:$D$800)) -> 0.083682008 | P88: =AVERAGE(M88:O88) -> 0.13900511 | Q88: =0.4*H88+0.4*I88+0.2*P88 -> 0.69012893 | R88: =PERCENTILE($Q$2:$Q$800,0.75) -> 0.66771572 | S88: =OR(Q88>=R88,AND(B88="CW",COUNT(J88:L88)<3)) -> TRUE | T88: 0.36554231 | U88: 10.044806 | V88: 0.69012893 | W88: =Q88-V88 -> 0
A89: 2021-06-08 | B89: CW | C89: 23.907569 | D89: =SUMPRODUCT(Risk_Inputs!B89:AJ89,Risk_Coefs!$B$2:$AJ$2) -> -0.9684085 | E89: =1/(1+EXP(-MAX(-25,MIN(25,D89)))) -> 0.27519784 | F89: =SUMPRODUCT(Risk_Inputs!B89:AJ89,Risk_Coefs!$B$3:$AJ$3) -> 6.4670105 | G89: =MAX(0,F89) -> 6.4670105 | H89: =(SUMPRODUCT(--ISNUMBER($E$2:$E$800),--($E$2:$E$800<E89))+(SUMPRODUCT(--ISNUMBER($E$2:$E$800),--($E$2:$E$800=E89))+1)/2)/COUNT($E$2:$E$800) -> 0.42553191 | I89: =(SUMPRODUCT(--ISNUMBER($G$2:$G$800),--($G$2:$G$800<G89))+(SUMPRODUCT(--ISNUMBER($G$2:$G$800),--($G$2:$G$800=G89))+1)/2)/COUNT($G$2:$G$800) -> 0.3379224 | J89: 5.9093768 | K89: 1.7647059 | L89: 0.35947712 | M89: =IF(OR(B89="NW",COUNT(Risk_Rank_Keys!B89)=0),0.5,(SUMPRODUCT(--ISNUMBER(Risk_Rank_Keys!$B$2:$B$800),--(Risk_Rank_Keys!$B$2:$B$800<Risk_Rank_Keys!B89))+(SUMPRODUCT(--ISNUMBER(Risk_Rank_Keys!$B$2:$B$800),--(Risk_Rank_Keys!$B$2:$B$800=Risk_Rank_Keys!B89))+1)/2)/COUNT(Risk_Rank_Keys!$B$2:$B$800)) -> 0.21896792 | N89: =IF(OR(B89="NW",COUNT(Risk_Rank_Keys!C89)=0),0.5,(SUMPRODUCT(--ISNUMBER(Risk_Rank_Keys!$C$2:$C$800),--(Risk_Rank_Keys!$C$2:$C$800<Risk_Rank_Keys!C89))+(SUMPRODUCT(--ISNUMBER(Risk_Rank_Keys!$C$2:$C$800),--(Risk_Rank_Keys!$C$2:$C$800=Risk_Rank_Keys!C89))+1)/2)/COUNT(Risk_Rank_Keys!$C$2:$C$800)) -> 0.20641562 | O89: =IF(OR(B89="NW",COUNT(Risk_Rank_Keys!D89)=0),0.5,(SUMPRODUCT(--ISNUMBER(Risk_Rank_Keys!$D$2:$D$800),--(Risk_Rank_Keys!$D$2:$D$800<Risk_Rank_Keys!D89))+(SUMPRODUCT(--ISNUMBER(Risk_Rank_Keys!$D$2:$D$800),--(Risk_Rank_Keys!$D$2:$D$800=Risk_Rank_Keys!D89))+1)/2)/COUNT(Risk_Rank_Keys!$D$2:$D$800)) -> 0.84797768 | P89: =AVERAGE(M89:O89) -> 0.42445374 | Q89: =0.4*H89+0.4*I89+0.2*P89 -> 0.39027248 | R89: =PERCENTILE($Q$2:$Q$800,0.75) -> 0.66771572 | S89: =OR(Q89>=R89,AND(B89="CW",COUNT(J89:L89)<3)) -> FALSE | T89: 0.27519784 | U89: 6.4670105 | V89: 0.39027248 | W89: =Q89-V89 -> 0
A90: 2021-06-09 | B90: CW | C90: -43.547664 | D90: =SUMPRODUCT(Risk_Inputs!B90:AJ90,Risk_Coefs!$B$2:$AJ$2) -> -0.78896574 | E90: =1/(1+EXP(-MAX(-25,MIN(25,D90)))) -> 0.31239079 | F90: =SUMPRODUCT(Risk_Inputs!B90:AJ90,Risk_Coefs!$B$3:$AJ$3) -> 8.5250589 | G90: =MAX(0,F90) -> 8.5250589 | H90: =(SUMPRODUCT(--ISNUMBER($E$2:$E$800),--($E$2:$E$800<E90))+(SUMPRODUCT(--ISNUMBER($E$2:$E$800),--($E$2:$E$800=E90))+1)/2)/COUNT($E$2:$E$800) -> 0.62578223 | I90: =(SUMPRODUCT(--ISNUMBER($G$2:$G$800),--($G$2:$G$800<G90))+(SUMPRODUCT(--ISNUMBER($G$2:$G$800),--($G$2:$G$800=G90))+1)/2)/COUNT($G$2:$G$800) -> 0.60951189 | J90: 5.7460682 | K90: 2.5719268 | L90: 0.26155187 | M90: =IF(OR(B90="NW",COUNT(Risk_Rank_Keys!B90)=0),0.5,(SUMPRODUCT(--ISNUMBER(Risk_Rank_Keys!$B$2:$B$800),--(Risk_Rank_Keys!$B$2:$B$800<Risk_Rank_Keys!B90))+(SUMPRODUCT(--ISNUMBER(Risk_Rank_Keys!$B$2:$B$800),--(Risk_Rank_Keys!$B$2:$B$800=Risk_Rank_Keys!B90))+1)/2)/COUNT(Risk_Rank_Keys!$B$2:$B$800)) -> 0.19804742 | N90: =IF(OR(B90="NW",COUNT(Risk_Rank_Keys!C90)=0),0.5,(SUMPRODUCT(--ISNUMBER(Risk_Rank_Keys!$C$2:$C$800),--(Risk_Rank_Keys!$C$2:$C$800<Risk_Rank_Keys!C90))+(SUMPRODUCT(--ISNUMBER(Risk_Rank_Keys!$C$2:$C$800),--(Risk_Rank_Keys!$C$2:$C$800=Risk_Rank_Keys!C90))+1)/2)/COUNT(Risk_Rank_Keys!$C$2:$C$800)) -> 0.40306834 | O90: =IF(OR(B90="NW",COUNT(Risk_Rank_Keys!D90)=0),0.5,(SUMPRODUCT(--ISNUMBER(Risk_Rank_Keys!$D$2:$D$800),--(Risk_Rank_Keys!$D$2:$D$800<Risk_Rank_Keys!D90))+(SUMPRODUCT(--ISNUMBER(Risk_Rank_Keys!$D$2:$D$800),--(Risk_Rank_Keys!$D$2:$D$800=Risk_Rank_Keys!D90))+1)/2)/COUNT(Risk_Rank_Keys!$D$2:$D$800)) -> 0.64016736 | P90: =AVERAGE(M90:O90) -> 0.41376104 | Q90: =0.4*H90+0.4*I90+0.2*P90 -> 0.57686986 | R90: =PERCENTILE($Q$2:$Q$800,0.75) -> 0.66771572 | S90: =OR(Q90>=R90,AND(B90="CW",COUNT(J90:L90)<3)) -> FALSE | T90: 0.31239079 | U90: 8.5250589 | V90: 0.57686986 | W90: =Q90-V90 -> 0
A91: 2021-06-10 | B91: CW | C91: 20.404862 | D91: =SUMPRODUCT(Risk_Inputs!B91:AJ91,Risk_Coefs!$B$2:$AJ$2) -> -0.96560868 | E91: =1/(1+EXP(-MAX(-25,MIN(25,D91)))) -> 0.27575665 | F91: =SUMPRODUCT(Risk_Inputs!B91:AJ91,Risk_Coefs!$B$3:$AJ$3) -> 9.1630453 | G91: =MAX(0,F91) -> 9.1630453 | H91: =(SUMPRODUCT(--ISNUMBER($E$2:$E$800),--($E$2:$E$800<E91))+(SUMPRODUCT(--ISNUMBER($E$2:$E$800),--($E$2:$E$800=E91))+1)/2)/COUNT($E$2:$E$800) -> 0.43178974 | I91: =(SUMPRODUCT(--ISNUMBER($G$2:$G$800),--($G$2:$G$800<G91))+(SUMPRODUCT(--ISNUMBER($G$2:$G$800),--($G$2:$G$800=G91))+1)/2)/COUNT($G$2:$G$800) -> 0.69962453 | J91: 7.0166038 | K91: 4.5454545 | L91: 0.36363636 | M91: =IF(OR(B91="NW",COUNT(Risk_Rank_Keys!B91)=0),0.5,(SUMPRODUCT(--ISNUMBER(Risk_Rank_Keys!$B$2:$B$800),--(Risk_Rank_Keys!$B$2:$B$800<Risk_Rank_Keys!B91))+(SUMPRODUCT(--ISNUMBER(Risk_Rank_Keys!$B$2:$B$800),--(Risk_Rank_Keys!$B$2:$B$800=Risk_Rank_Keys!B91))+1)/2)/COUNT(Risk_Rank_Keys!$B$2:$B$800)) -> 0.31520223 | N91: =IF(OR(B91="NW",COUNT(Risk_Rank_Keys!C91)=0),0.5,(SUMPRODUCT(--ISNUMBER(Risk_Rank_Keys!$C$2:$C$800),--(Risk_Rank_Keys!$C$2:$C$800<Risk_Rank_Keys!C91))+(SUMPRODUCT(--ISNUMBER(Risk_Rank_Keys!$C$2:$C$800),--(Risk_Rank_Keys!$C$2:$C$800=Risk_Rank_Keys!C91))+1)/2)/COUNT(Risk_Rank_Keys!$C$2:$C$800)) -> 0.64853556 | O91: =IF(OR(B91="NW",COUNT(Risk_Rank_Keys!D91)=0),0.5,(SUMPRODUCT(--ISNUMBER(Risk_Rank_Keys!$D$2:$D$800),--(Risk_Rank_Keys!$D$2:$D$800<Risk_Rank_Keys!D91))+(SUMPRODUCT(--ISNUMBER(Risk_Rank_Keys!$D$2:$D$800),--(Risk_Rank_Keys!$D$2:$D$800=Risk_Rank_Keys!D91))+1)/2)/COUNT(Risk_Rank_Keys!$D$2:$D$800)) -> 0.85216179 | P91: =AVERAGE(M91:O91) -> 0.60529986 | Q91: =0.4*H91+0.4*I91+0.2*P91 -> 0.57362568 | R91: =PERCENTILE($Q$2:$Q$800,0.75) -> 0.66771572 | S91: =OR(Q91>=R91,AND(B91="CW",COUNT(J91:L91)<3)) -> FALSE | T91: 0.27575665 | U91: 9.1630453 | V91: 0.57362568 | W91: =Q91-V91 -> 0
A92: 2021-06-11 | B92: CW | C92: 27.553306 | D92: =SUMPRODUCT(Risk_Inputs!B92:AJ92,Risk_Coefs!$B$2:$AJ$2) -> -1.0229789 | E92: =1/(1+EXP(-MAX(-25,MIN(25,D92)))) -> 0.26444756 | F92: =SUMPRODUCT(Risk_Inputs!B92:AJ92,Risk_Coefs!$B$3:$AJ$3) -> 6.9321714 | G92: =MAX(0,F92) -> 6.9321714 | H92: =(SUMPRODUCT(--ISNUMBER($E$2:$E$800),--($E$2:$E$800<E92))+(SUMPRODUCT(--ISNUMBER($E$2:$E$800),--($E$2:$E$800=E92))+1)/2)/COUNT($E$2:$E$800) -> 0.36295369 | I92: =(SUMPRODUCT(--ISNUMBER($G$2:$G$800),--($G$2:$G$800<G92))+(SUMPRODUCT(--ISNUMBER($G$2:$G$800),--($G$2:$G$800=G92))+1)/2)/COUNT($G$2:$G$800) -> 0.40926158 | J92: 5.8534486 | K92: 1.2275964 | L92: 0.22096735 | M92: =IF(OR(B92="NW",COUNT(Risk_Rank_Keys!B92)=0),0.5,(SUMPRODUCT(--ISNUMBER(Risk_Rank_Keys!$B$2:$B$800),--(Risk_Rank_Keys!$B$2:$B$800<Risk_Rank_Keys!B92))+(SUMPRODUCT(--ISNUMBER(Risk_Rank_Keys!$B$2:$B$800),--(Risk_Rank_Keys!$B$2:$B$800=Risk_Rank_Keys!B92))+1)/2)/COUNT(Risk_Rank_Keys!$B$2:$B$800)) -> 0.21059972 | N92: =IF(OR(B92="NW",COUNT(Risk_Rank_Keys!C92)=0),0.5,(SUMPRODUCT(--ISNUMBER(Risk_Rank_Keys!$C$2:$C$800),--(Risk_Rank_Keys!$C$2:$C$800<Risk_Rank_Keys!C92))+(SUMPRODUCT(--ISNUMBER(Risk_Rank_Keys!$C$2:$C$800),--(Risk_Rank_Keys!$C$2:$C$800=Risk_Rank_Keys!C92))+1)/2)/COUNT(Risk_Rank_Keys!$C$2:$C$800)) -> 0.076708508 | O92: =IF(OR(B92="NW",COUNT(Risk_Rank_Keys!D92)=0),0.5,(SUMPRODUCT(--ISNUMBER(Risk_Rank_Keys!$D$2:$D$800),--(Risk_Rank_Keys!$D$2:$D$800<Risk_Rank_Keys!D92))+(SUMPRODUCT(--ISNUMBER(Risk_Rank_Keys!$D$2:$D$800),--(Risk_Rank_Keys!$D$2:$D$800=Risk_Rank_Keys!D92))+1)/2)/COUNT(Risk_Rank_Keys!$D$2:$D$800)) -> 0.44351464 | P92: =AVERAGE(M92:O92) -> 0.24360762 | Q92: =0.4*H92+0.4*I92+0.2*P92 -> 0.35760763 | R92: =PERCENTILE($Q$2:$Q$800,0.75) -> 0.66771572 | S92: =OR(Q92>=R92,AND(B92="CW",COUNT(J92:L92)<3)) -> FALSE | T92: 0.26444756 | U92: 6.9321714 | V92: 0.35760763 | W92: =Q92-V92 -> 0
A93: 2021-06-14 | B93: CW | C93: 14.453933 | D93: =SUMPRODUCT(Risk_Inputs!B93:AJ93,Risk_Coefs!$B$2:$AJ$2) -> -0.86860798 | E93: =1/(1+EXP(-MAX(-25,MIN(25,D93)))) -> 0.29554404 | F93: =SUMPRODUCT(Risk_Inputs!B93:AJ93,Risk_Coefs!$B$3:$AJ$3) -> 8.3178189 | G93: =MAX(0,F93) -> 8.3178189 | H93: =(SUMPRODUCT(--ISNUMBER($E$2:$E$800),--($E$2:$E$800<E93))+(SUMPRODUCT(--ISNUMBER($E$2:$E$800),--($E$2:$E$800=E93))+1)/2)/COUNT($E$2:$E$800) -> 0.5494368 | I93: =(SUMPRODUCT(--ISNUMBER($G$2:$G$800),--($G$2:$G$800<G93))+(SUMPRODUCT(--ISNUMBER($G$2:$G$800),--($G$2:$G$800=G93))+1)/2)/COUNT($G$2:$G$800) -> 0.58322904 | J93: 24.361157 | K93: 6.2662507 | L93: 0.33801352 | M93: =IF(OR(B93="NW",COUNT(Risk_Rank_Keys!B93)=0),0.5,(SUMPRODUCT(--ISNUMBER(Risk_Rank_Keys!$B$2:$B$800),--(Risk_Rank_Keys!$B$2:$B$800<Risk_Rank_Keys!B93))+(SUMPRODUCT(--ISNUMBER(Risk_Rank_Keys!$B$2:$B$800),--(Risk_Rank_Keys!$B$2:$B$800=Risk_Rank_Keys!B93))+1)/2)/COUNT(Risk_Rank_Keys!$B$2:$B$800)) -> 0.84797768 | N93: =IF(OR(B93="NW",COUNT(Risk_Rank_Keys!C93)=0),0.5,(SUMPRODUCT(--ISNUMBER(Risk_Rank_Keys!$C$2:$C$800),--(Risk_Rank_Keys!$C$2:$C$800<Risk_Rank_Keys!C93))+(SUMPRODUCT(--ISNUMBER(Risk_Rank_Keys!$C$2:$C$800),--(Risk_Rank_Keys!$C$2:$C$800=Risk_Rank_Keys!C93))+1)/2)/COUNT(Risk_Rank_Keys!$C$2:$C$800)) -> 0.75313808 | O93: =IF(OR(B93="NW",COUNT(Risk_Rank_Keys!D93)=0),0.5,(SUMPRODUCT(--ISNUMBER(Risk_Rank_Keys!$D$2:$D$800),--(Risk_Rank_Keys!$D$2:$D$800<Risk_Rank_Keys!D93))+(SUMPRODUCT(--ISNUMBER(Risk_Rank_Keys!$D$2:$D$800),--(Risk_Rank_Keys!$D$2:$D$800=Risk_Rank_Keys!D93))+1)/2)/COUNT(Risk_Rank_Keys!$D$2:$D$800)) -> 0.81171548 | P93: =AVERAGE(M93:O93) -> 0.80427708 | Q93: =0.4*H93+0.4*I93+0.2*P93 -> 0.61392175 | R93: =PERCENTILE($Q$2:$Q$800,0.75) -> 0.66771572 | S93: =OR(Q93>=R93,AND(B93="CW",COUNT(J93:L93)<3)) -> FALSE | T93: 0.29554404 | U93: 8.3178189 | V93: 0.61392175 | W93: =Q93-V93 -> 0
A94: 2021-06-15 | B94: CW | C94: 22.328891 | D94: =SUMPRODUCT(Risk_Inputs!B94:AJ94,Risk_Coefs!$B$2:$AJ$2) -> -0.89654272 | E94: =1/(1+EXP(-MAX(-25,MIN(25,D94)))) -> 0.28976149 | F94: =SUMPRODUCT(Risk_Inputs!B94:AJ94,Risk_Coefs!$B$3:$AJ$3) -> 5.9974441 | G94: =MAX(0,F94) -> 5.9974441 | H94: =(SUMPRODUCT(--ISNUMBER($E$2:$E$800),--($E$2:$E$800<E94))+(SUMPRODUCT(--ISNUMBER($E$2:$E$800),--($E$2:$E$800=E94))+1)/2)/COUNT($E$2:$E$800) -> 0.52315394 | I94: =(SUMPRODUCT(--ISNUMBER($G$2:$G$800),--($G$2:$G$800<G94))+(SUMPRODUCT(--ISNUMBER($G$2:$G$800),--($G$2:$G$800=G94))+1)/2)/COUNT($G$2:$G$800) -> 0.26783479 | J94: 5.0770385 | K94: 1.1830202 | L94: 0.27835769 | M94: =IF(OR(B94="NW",COUNT(Risk_Rank_Keys!B94)=0),0.5,(SUMPRODUCT(--ISNUMBER(Risk_Rank_Keys!$B$2:$B$800),--(Risk_Rank_Keys!$B$2:$B$800<Risk_Rank_Keys!B94))+(SUMPRODUCT(--ISNUMBER(Risk_Rank_Keys!$B$2:$B$800),--(Risk_Rank_Keys!$B$2:$B$800=Risk_Rank_Keys!B94))+1)/2)/COUNT(Risk_Rank_Keys!$B$2:$B$800)) -> 0.13389121 | N94: =IF(OR(B94="NW",COUNT(Risk_Rank_Keys!C94)=0),0.5,(SUMPRODUCT(--ISNUMBER(Risk_Rank_Keys!$C$2:$C$800),--(Risk_Rank_Keys!$C$2:$C$800<Risk_Rank_Keys!C94))+(SUMPRODUCT(--ISNUMBER(Risk_Rank_Keys!$C$2:$C$800),--(Risk_Rank_Keys!$C$2:$C$800=Risk_Rank_Keys!C94))+1)/2)/COUNT(Risk_Rank_Keys!$C$2:$C$800)) -> 0.064156206 | O94: =IF(OR(B94="NW",COUNT(Risk_Rank_Keys!D94)=0),0.5,(SUMPRODUCT(--ISNUMBER(Risk_Rank_Keys!$D$2:$D$800),--(Risk_Rank_Keys!$D$2:$D$800<Risk_Rank_Keys!D94))+(SUMPRODUCT(--ISNUMBER(Risk_Rank_Keys!$D$2:$D$800),--(Risk_Rank_Keys!$D$2:$D$800=Risk_Rank_Keys!D94))+1)/2)/COUNT(Risk_Rank_Keys!$D$2:$D$800)) -> 0.69316597 | P94: =AVERAGE(M94:O94) -> 0.29707113 | Q94: =0.4*H94+0.4*I94+0.2*P94 -> 0.37580972 | R94: =PERCENTILE($Q$2:$Q$800,0.75) -> 0.66771572 | S94: =OR(Q94>=R94,AND(B94="CW",COUNT(J94:L94)<3)) -> FALSE | T94: 0.28976149 | U94: 5.9974441 | V94: 0.37580972 | W94: =Q94-V94 -> 0
A95: 2021-06-16 | B95: CW | C95: -13.606096 | D95: =SUMPRODUCT(Risk_Inputs!B95:AJ95,Risk_Coefs!$B$2:$AJ$2) -> -0.71630281 | E95: =1/(1+EXP(-MAX(-25,MIN(25,D95)))) -> 0.32820765 | F95: =SUMPRODUCT(Risk_Inputs!B95:AJ95,Risk_Coefs!$B$3:$AJ$3) -> 9.7130937 | G95: =MAX(0,F95) -> 9.7130937 | H95: =(SUMPRODUCT(--ISNUMBER($E$2:$E$800),--($E$2:$E$800<E95))+(SUMPRODUCT(--ISNUMBER($E$2:$E$800),--($E$2:$E$800=E95))+1)/2)/COUNT($E$2:$E$800) -> 0.72465582 | I95: =(SUMPRODUCT(--ISNUMBER($G$2:$G$800),--($G$2:$G$800<G95))+(SUMPRODUCT(--ISNUMBER($G$2:$G$800),--($G$2:$G$800=G95))+1)/2)/COUNT($G$2:$G$800) -> 0.74968711 | J95: 7.3566557 | K95: 2.4650781 | L95: 0.28759244 | M95: =IF(OR(B95="NW",COUNT(Risk_Rank_Keys!B95)=0),0.5,(SUMPRODUCT(--ISNUMBER(Risk_Rank_Keys!$B$2:$B$800),--(Risk_Rank_Keys!$B$2:$B$800<Risk_Rank_Keys!B95))+(SUMPRODUCT(--ISNUMBER(Risk_Rank_Keys!$B$2:$B$800),--(Risk_Rank_Keys!$B$2:$B$800=Risk_Rank_Keys!B95))+1)/2)/COUNT(Risk_Rank_Keys!$B$2:$B$800)) -> 0.34170153 | N95: =IF(OR(B95="NW",COUNT(Risk_Rank_Keys!C95)=0),0.5,(SUMPRODUCT(--ISNUMBER(Risk_Rank_Keys!$C$2:$C$800),--(Risk_Rank_Keys!$C$2:$C$800<Risk_Rank_Keys!C95))+(SUMPRODUCT(--ISNUMBER(Risk_Rank_Keys!$C$2:$C$800),--(Risk_Rank_Keys!$C$2:$C$800=Risk_Rank_Keys!C95))+1)/2)/COUNT(Risk_Rank_Keys!$C$2:$C$800)) -> 0.38633194 | O95: =IF(OR(B95="NW",COUNT(Risk_Rank_Keys!D95)=0),0.5,(SUMPRODUCT(--ISNUMBER(Risk_Rank_Keys!$D$2:$D$800),--(Risk_Rank_Keys!$D$2:$D$800<Risk_Rank_Keys!D95))+(SUMPRODUCT(--ISNUMBER(Risk_Rank_Keys!$D$2:$D$800),--(Risk_Rank_Keys!$D$2:$D$800=Risk_Rank_Keys!D95))+1)/2)/COUNT(Risk_Rank_Keys!$D$2:$D$800)) -> 0.71966527 | P95: =AVERAGE(M95:O95) -> 0.48256625 | Q95: =0.4*H95+0.4*I95+0.2*P95 -> 0.68625042 | R95: =PERCENTILE($Q$2:$Q$800,0.75) -> 0.66771572 | S95: =OR(Q95>=R95,AND(B95="CW",COUNT(J95:L95)<3)) -> TRUE | T95: 0.32820765 | U95: 9.7130937 | V95: 0.68625042 | W95: =Q95-V95 -> 0
A96: 2021-06-17 | B96: CW | C96: 50.177903 | D96: =SUMPRODUCT(Risk_Inputs!B96:AJ96,Risk_Coefs!$B$2:$AJ$2) -> -0.9855959 | E96: =1/(1+EXP(-MAX(-25,MIN(25,D96)))) -> 0.27178285 | F96: =SUMPRODUCT(Risk_Inputs!B96:AJ96,Risk_Coefs!$B$3:$AJ$3) -> 9.8069876 | G96: =MAX(0,F96) -> 9.8069876 | H96: =(SUMPRODUCT(--ISNUMBER($E$2:$E$800),--($E$2:$E$800<E96))+(SUMPRODUCT(--ISNUMBER($E$2:$E$800),--($E$2:$E$800=E96))+1)/2)/COUNT($E$2:$E$800) -> 0.40050063 | I96: =(SUMPRODUCT(--ISNUMBER($G$2:$G$800),--($G$2:$G$800<G96))+(SUMPRODUCT(--ISNUMBER($G$2:$G$800),--($G$2:$G$800=G96))+1)/2)/COUNT($G$2:$G$800) -> 0.76720901 | J96: 11.63955 | K96: 6.619256 | L96: 0.49234136 | M96: =IF(OR(B96="NW",COUNT(Risk_Rank_Keys!B96)=0),0.5,(SUMPRODUCT(--ISNUMBER(Risk_Rank_Keys!$B$2:$B$800),--(Risk_Rank_Keys!$B$2:$B$800<Risk_Rank_Keys!B96))+(SUMPRODUCT(--ISNUMBER(Risk_Rank_Keys!$B$2:$B$800),--(Risk_Rank_Keys!$B$2:$B$800=Risk_Rank_Keys!B96))+1)/2)/COUNT(Risk_Rank_Keys!$B$2:$B$800)) -> 0.58158996 | N96: =IF(OR(B96="NW",COUNT(Risk_Rank_Keys!C96)=0),0.5,(SUMPRODUCT(--ISNUMBER(Risk_Rank_Keys!$C$2:$C$800),--(Risk_Rank_Keys!$C$2:$C$800<Risk_Rank_Keys!C96))+(SUMPRODUCT(--ISNUMBER(Risk_Rank_Keys!$C$2:$C$800),--(Risk_Rank_Keys!$C$2:$C$800=Risk_Rank_Keys!C96))+1)/2)/COUNT(Risk_Rank_Keys!$C$2:$C$800)) -> 0.77126918 | O96: =IF(OR(B96="NW",COUNT(Risk_Rank_Keys!D96)=0),0.5,(SUMPRODUCT(--ISNUMBER(Risk_Rank_Keys!$D$2:$D$800),--(Risk_Rank_Keys!$D$2:$D$800<Risk_Rank_Keys!D96))+(SUMPRODUCT(--ISNUMBER(Risk_Rank_Keys!$D$2:$D$800),--(Risk_Rank_Keys!$D$2:$D$800=Risk_Rank_Keys!D96))+1)/2)/COUNT(Risk_Rank_Keys!$D$2:$D$800)) -> 0.94700139 | P96: =AVERAGE(M96:O96) -> 0.76662018 | Q96: =0.4*H96+0.4*I96+0.2*P96 -> 0.62040789 | R96: =PERCENTILE($Q$2:$Q$800,0.75) -> 0.66771572 | S96: =OR(Q96>=R96,AND(B96="CW",COUNT(J96:L96)<3)) -> FALSE | T96: 0.27178285 | U96: 9.8069876 | V96: 0.62040789 | W96: =Q96-V96 -> 0
A97: 2021-06-18 | B97: CW | C97: -41.623304 | D97: =SUMPRODUCT(Risk_Inputs!B97:AJ97,Risk_Coefs!$B$2:$AJ$2) -> -0.84425865 | E97: =1/(1+EXP(-MAX(-25,MIN(25,D97)))) -> 0.30063862 | F97: =SUMPRODUCT(Risk_Inputs!B97:AJ97,Risk_Coefs!$B$3:$AJ$3) -> 12.862015 | G97: =MAX(0,F97) -> 12.862015 | H97: =(SUMPRODUCT(--ISNUMBER($E$2:$E$800),--($E$2:$E$800<E97))+(SUMPRODUCT(--ISNUMBER($E$2:$E$800),--($E$2:$E$800=E97))+1)/2)/COUNT($E$2:$E$800) -> 0.56946183 | I97: =(SUMPRODUCT(--ISNUMBER($G$2:$G$800),--($G$2:$G$800<G97))+(SUMPRODUCT(--ISNUMBER($G$2:$G$800),--($G$2:$G$800=G97))+1)/2)/COUNT($G$2:$G$800) -> 0.94868586 | J97: 16.485931 | K97: 4.8261448 | L97: 0.28500855 | M97: =IF(OR(B97="NW",COUNT(Risk_Rank_Keys!B97)=0),0.5,(SUMPRODUCT(--ISNUMBER(Risk_Rank_Keys!$B$2:$B$800),--(Risk_Rank_Keys!$B$2:$B$800<Risk_Rank_Keys!B97))+(SUMPRODUCT(--ISNUMBER(Risk_Rank_Keys!$B$2:$B$800),--(Risk_Rank_Keys!$B$2:$B$800=Risk_Rank_Keys!B97))+1)/2)/COUNT(Risk_Rank_Keys!$B$2:$B$800)) -> 0.73500697 | N97: =IF(OR(B97="NW",COUNT(Risk_Rank_Keys!C97)=0),0.5,(SUMPRODUCT(--ISNUMBER(Risk_Rank_Keys!$C$2:$C$800),--(Risk_Rank_Keys!$C$2:$C$800<Risk_Rank_Keys!C97))+(SUMPRODUCT(--ISNUMBER(Risk_Rank_Keys!$C$2:$C$800),--(Risk_Rank_Keys!$C$2:$C$800=Risk_Rank_Keys!C97))+1)/2)/COUNT(Risk_Rank_Keys!$C$2:$C$800)) -> 0.67782427 | O97: =IF(OR(B97="NW",COUNT(Risk_Rank_Keys!D97)=0),0.5,(SUMPRODUCT(--ISNUMBER(Risk_Rank_Keys!$D$2:$D$800),--(Risk_Rank_Keys!$D$2:$D$800<Risk_Rank_Keys!D97))+(SUMPRODUCT(--ISNUMBER(Risk_Rank_Keys!$D$2:$D$800),--(Risk_Rank_Keys!$D$2:$D$800=Risk_Rank_Keys!D97))+1)/2)/COUNT(Risk_Rank_Keys!$D$2:$D$800)) -> 0.71129707 | P97: =AVERAGE(M97:O97) -> 0.70804277 | Q97: =0.4*H97+0.4*I97+0.2*P97 -> 0.74886763 | R97: =PERCENTILE($Q$2:$Q$800,0.75) -> 0.66771572 | S97: =OR(Q97>=R97,AND(B97="CW",COUNT(J97:L97)<3)) -> TRUE | T97: 0.30063862 | U97: 12.862015 | V97: 0.74886763 | W97: =Q97-V97 -> 0
A98: 2021-06-21 | B98: CW | C98: 9.1129723 | D98: =SUMPRODUCT(Risk_Inputs!B98:AJ98,Risk_Coefs!$B$2:$AJ$2) -> -0.47952725 | E98: =1/(1+EXP(-MAX(-25,MIN(25,D98)))) -> 0.38236376 | F98: =SUMPRODUCT(Risk_Inputs!B98:AJ98,Risk_Coefs!$B$3:$AJ$3) -> 8.4109651 | G98: =MAX(0,F98) -> 8.4109651 | H98: =(SUMPRODUCT(--ISNUMBER($E$2:$E$800),--($E$2:$E$800<E98))+(SUMPRODUCT(--ISNUMBER($E$2:$E$800),--($E$2:$E$800=E98))+1)/2)/COUNT($E$2:$E$800) -> 0.90863579 | I98: =(SUMPRODUCT(--ISNUMBER($G$2:$G$800),--($G$2:$G$800<G98))+(SUMPRODUCT(--ISNUMBER($G$2:$G$800),--($G$2:$G$800=G98))+1)/2)/COUNT($G$2:$G$800) -> 0.59449312 | J98: 10.859338 | K98: 1.92599 | L98: 0.25968405 | M98: =IF(OR(B98="NW",COUNT(Risk_Rank_Keys!B98)=0),0.5,(SUMPRODUCT(--ISNUMBER(Risk_Rank_Keys!$B$2:$B$800),--(Risk_Rank_Keys!$B$2:$B$800<Risk_Rank_Keys!B98))+(SUMPRODUCT(--ISNUMBER(Risk_Rank_Keys!$B$2:$B$800),--(Risk_Rank_Keys!$B$2:$B$800=Risk_Rank_Keys!B98))+1)/2)/COUNT(Risk_Rank_Keys!$B$2:$B$800)) -> 0.53974895 | N98: =IF(OR(B98="NW",COUNT(Risk_Rank_Keys!C98)=0),0.5,(SUMPRODUCT(--ISNUMBER(Risk_Rank_Keys!$C$2:$C$800),--(Risk_Rank_Keys!$C$2:$C$800<Risk_Rank_Keys!C98))+(SUMPRODUCT(--ISNUMBER(Risk_Rank_Keys!$C$2:$C$800),--(Risk_Rank_Keys!$C$2:$C$800=Risk_Rank_Keys!C98))+1)/2)/COUNT(Risk_Rank_Keys!$C$2:$C$800)) -> 0.25244073 | O98: =IF(OR(B98="NW",COUNT(Risk_Rank_Keys!D98)=0),0.5,(SUMPRODUCT(--ISNUMBER(Risk_Rank_Keys!$D$2:$D$800),--(Risk_Rank_Keys!$D$2:$D$800<Risk_Rank_Keys!D98))+(SUMPRODUCT(--ISNUMBER(Risk_Rank_Keys!$D$2:$D$800),--(Risk_Rank_Keys!$D$2:$D$800=Risk_Rank_Keys!D98))+1)/2)/COUNT(Risk_Rank_Keys!$D$2:$D$800)) -> 0.63040446 | P98: =AVERAGE(M98:O98) -> 0.47419805 | Q98: =0.4*H98+0.4*I98+0.2*P98 -> 0.69609117 | R98: =PERCENTILE($Q$2:$Q$800,0.75) -> 0.66771572 | S98: =OR(Q98>=R98,AND(B98="CW",COUNT(J98:L98)<3)) -> TRUE | T98: 0.38236376 | U98: 8.4109651 | V98: 0.69609117 | W98: =Q98-V98 -> 0
... A109: 2021-07-28 | B109: CW | C109: -39.971237 | D109: =SUMPRODUCT(Risk_Inputs!B109:AJ109,Risk_Coefs!$B$2:$AJ$2) -> -0.73545107 | E109: =1/(1+EXP(-MAX(-25,MIN(25,D109)))) -> 0.32399967 | F109: =SUMPRODUCT(Risk_Inputs!B109:AJ109,Risk_Coefs!$B$3:$AJ$3) -> 8.1830683 | G109: =MAX(0,F109) -> 8.1830683 | H109: =(SUMPRODUCT(--ISNUMBER($E$2:$E$800),--($E$2:$E$800<E109))+(SUMPRODUCT(--ISNUMBER($E$2:$E$800),--($E$2:$E$800=E109))+1)/2)/COUNT($E$2:$E$800) -> 0.6971214 | I109: =(SUMPRODUCT(--ISNUMBER($G$2:$G$800),--($G$2:$G$800<G109))+(SUMPRODUCT(--ISNUMBER($G$2:$G$800),--($G$2:$G$800=G109))+1)/2)/COUNT($G$2:$G$800) -> 0.55944931 | J109: 3.7594823 | K109: 3.7813399 | L109: 0.32881217 | M109: =IF(OR(B109="NW",COUNT(Risk_Rank_Keys!B109)=0),0.5,(SUMPRODUCT(--ISNUMBER(Risk_Rank_Keys!$B$2:$B$800),--(Risk_Rank_Keys!$B$2:$B$800<Risk_Rank_Keys!B109))+(SUMPRODUCT(--ISNUMBER(Risk_Rank_Keys!$B$2:$B$800),--(Risk_Rank_Keys!$B$2:$B$800=Risk_Rank_Keys!B109))+1)/2)/COUNT(Risk_Rank_Keys!$B$2:$B$800)) -> 0.059972106 | N109: =IF(OR(B109="NW",COUNT(Risk_Rank_Keys!C109)=0),0.5,(SUMPRODUCT(--ISNUMBER(Risk_Rank_Keys!$C$2:$C$800),--(Risk_Rank_Keys!$C$2:$C$800<Risk_Rank_Keys!C109))+(SUMPRODUCT(--ISNUMBER(Risk_Rank_Keys!$C$2:$C$800),--(Risk_Rank_Keys!$C$2:$C$800=Risk_Rank_Keys!C109))+1)/2)/COUNT(Risk_Rank_Keys!$C$2:$C$800)) -> 0.56624826 | O109: =IF(OR(B109="NW",COUNT(Risk_Rank_Keys!D109)=0),0.5,(SUMPRODUCT(--ISNUMBER(Risk_Rank_Keys!$D$2:$D$800),--(Risk_Rank_Keys!$D$2:$D$800<Risk_Rank_Keys!D109))+(SUMPRODUCT(--ISNUMBER(Risk_Rank_Keys!$D$2:$D$800),--(Risk_Rank_Keys!$D$2:$D$800=Risk_Rank_Keys!D109))+1)/2)/COUNT(Risk_Rank_Keys!$D$2:$D$800)) -> 0.79497908 | P109: =AVERAGE(M109:O109) -> 0.47373315 | Q109: =0.4*H109+0.4*I109+0.2*P109 -> 0.59737491 | R109: =PERCENTILE($Q$2:$Q$800,0.75) -> 0.66771572 | S109: =OR(Q109>=R109,AND(B109="CW",COUNT(J109:L109)<3)) -> FALSE | T109: 0.32399967 | U109: 8.1830683 | V109: 0.59737491 | W109: =Q109-V109 -> 0
A110: 2021-07-29 | B110: NW | C110: 21.120979 | D110: =SUMPRODUCT(Risk_Inputs!B110:AJ110,Risk_Coefs!$B$2:$AJ$2) -> -0.65445374 | E110: =1/(1+EXP(-MAX(-25,MIN(25,D110)))) -> 0.3419866 | F110: =SUMPRODUCT(Risk_Inputs!B110:AJ110,Risk_Coefs!$B$3:$AJ$3) -> 10.068425 | G110: =MAX(0,F110) -> 10.068425 | H110: =(SUMPRODUCT(--ISNUMBER($E$2:$E$800),--($E$2:$E$800<E110))+(SUMPRODUCT(--ISNUMBER($E$2:$E$800),--($E$2:$E$800=E110))+1)/2)/COUNT($E$2:$E$800) -> 0.78973717 | I110: =(SUMPRODUCT(--ISNUMBER($G$2:$G$800),--($G$2:$G$800<G110))+(SUMPRODUCT(--ISNUMBER($G$2:$G$800),--($G$2:$G$800=G110))+1)/2)/COUNT($G$2:$G$800) -> 0.79849812 | M110: =IF(OR(B110="NW",COUNT(Risk_Rank_Keys!B110)=0),0.5,(SUMPRODUCT(--ISNUMBER(Risk_Rank_Keys!$B$2:$B$800),--(Risk_Rank_Keys!$B$2:$B$800<Risk_Rank_Keys!B110))+(SUMPRODUCT(--ISNUMBER(Risk_Rank_Keys!$B$2:$B$800),--(Risk_Rank_Keys!$B$2:$B$800=Risk_Rank_Keys!B110))+1)/2)/COUNT(Risk_Rank_Keys!$B$2:$B$800)) -> 0.5 | N110: =IF(OR(B110="NW",COUNT(Risk_Rank_Keys!C110)=0),0.5,(SUMPRODUCT(--ISNUMBER(Risk_Rank_Keys!$C$2:$C$800),--(Risk_Rank_Keys!$C$2:$C$800<Risk_Rank_Keys!C110))+(SUMPRODUCT(--ISNUMBER(Risk_Rank_Keys!$C$2:$C$800),--(Risk_Rank_Keys!$C$2:$C$800=Risk_Rank_Keys!C110))+1)/2)/COUNT(Risk_Rank_Keys!$C$2:$C$800)) -> 0.5 | O110: =IF(OR(B110="NW",COUNT(Risk_Rank_Keys!D110)=0),0.5,(SUMPRODUCT(--ISNUMBER(Risk_Rank_Keys!$D$2:$D$800),--(Risk_Rank_Keys!$D$2:$D$800<Risk_Rank_Keys!D110))+(SUMPRODUCT(--ISNUMBER(Risk_Rank_Keys!$D$2:$D$800),--(Risk_Rank_Keys!$D$2:$D$800=Risk_Rank_Keys!D110))+1)/2)/COUNT(Risk_Rank_Keys!$D$2:$D$800)) -> 0.5 | P110: =AVERAGE(M110:O110) -> 0.5 | Q110: =0.4*H110+0.4*I110+0.2*P110 -> 0.73529412 | R110: =PERCENTILE($Q$2:$Q$800,0.75) -> 0.66771572 | S110: =OR(Q110>=R110,AND(B110="CW",COUNT(J110:L110)<3)) -> TRUE | T110: 0.3419866 | U110: 10.068425 | V110: 0.73529412 | W110: =Q110-V110 -> 0
A111: 2021-08-03 | B111: CW | C111: -37.700497 | D111: =SUMPRODUCT(Risk_Inputs!B111:AJ111,Risk_Coefs!$B$2:$AJ$2) -> -0.70060984 | E111: =1/(1+EXP(-MAX(-25,MIN(25,D111)))) -> 0.33167703 | F111: =SUMPRODUCT(Risk_Inputs!B111:AJ111,Risk_Coefs!$B$3:$AJ$3) -> 8.7773166 | G111: =MAX(0,F111) -> 8.7773166 | H111: =(SUMPRODUCT(--ISNUMBER($E$2:$E$800),--($E$2:$E$800<E111))+(SUMPRODUCT(--ISNUMBER($E$2:$E$800),--($E$2:$E$800=E111))+1)/2)/COUNT($E$2:$E$800) -> 0.74468085 | I111: =(SUMPRODUCT(--ISNUMBER($G$2:$G$800),--($G$2:$G$800<G111))+(SUMPRODUCT(--ISNUMBER($G$2:$G$800),--($G$2:$G$800=G111))+1)/2)/COUNT($G$2:$G$800) -> 0.64705882 | J111: 2.0040331 | K111: 0.92867756 | L111: 0.18573551 | M111: =IF(OR(B111="NW",COUNT(Risk_Rank_Keys!B111)=0),0.5,(SUMPRODUCT(--ISNUMBER(Risk_Rank_Keys!$B$2:$B$800),--(Risk_Rank_Keys!$B$2:$B$800<Risk_Rank_Keys!B111))+(SUMPRODUCT(--ISNUMBER(Risk_Rank_Keys!$B$2:$B$800),--(Risk_Rank_Keys!$B$2:$B$800=Risk_Rank_Keys!B111))+1)/2)/COUNT(Risk_Rank_Keys!$B$2:$B$800)) -> 0.0055788006 | N111: =IF(OR(B111="NW",COUNT(Risk_Rank_Keys!C111)=0),0.5,(SUMPRODUCT(--ISNUMBER(Risk_Rank_Keys!$C$2:$C$800),--(Risk_Rank_Keys!$C$2:$C$800<Risk_Rank_Keys!C111))+(SUMPRODUCT(--ISNUMBER(Risk_Rank_Keys!$C$2:$C$800),--(Risk_Rank_Keys!$C$2:$C$800=Risk_Rank_Keys!C111))+1)/2)/COUNT(Risk_Rank_Keys!$C$2:$C$800)) -> 0.022315202 | O111: =IF(OR(B111="NW",COUNT(Risk_Rank_Keys!D111)=0),0.5,(SUMPRODUCT(--ISNUMBER(Risk_Rank_Keys!$D$2:$D$800),--(Risk_Rank_Keys!$D$2:$D$800<Risk_Rank_Keys!D111))+(SUMPRODUCT(--ISNUMBER(Risk_Rank_Keys!$D$2:$D$800),--(Risk_Rank_Keys!$D$2:$D$800=Risk_Rank_Keys!D111))+1)/2)/COUNT(Risk_Rank_Keys!$D$2:$D$800)) -> 0.23709902 | P111: =AVERAGE(M111:O111) -> 0.088331009 | Q111: =0.4*H111+0.4*I111+0.2*P111 -> 0.57436207 | R111: =PERCENTILE($Q$2:$Q$800,0.75) -> 0.66771572 | S111: =OR(Q111>=R111,AND(B111="CW",COUNT(J111:L111)<3)) -> FALSE | T111: 0.33167703 | U111: 8.7773166 | V111: 0.57436207 | W111: =Q111-V111 -> 0
A112: 2021-08-04 | B112: CW | C112: 35.58491 | D112: =SUMPRODUCT(Risk_Inputs!B112:AJ112,Risk_Coefs!$B$2:$AJ$2) -> -2.0029404 | E112: =1/(1+EXP(-MAX(-25,MIN(25,D112)))) -> 0.11889454 | F112: =SUMPRODUCT(Risk_Inputs!B112:AJ112,Risk_Coefs!$B$3:$AJ$3) -> 5.1504467 | G112: =MAX(0,F112) -> 5.1504467 | H112: =(SUMPRODUCT(--ISNUMBER($E$2:$E$800),--($E$2:$E$800<E112))+(SUMPRODUCT(--ISNUMBER($E$2:$E$800),--($E$2:$E$800=E112))+1)/2)/COUNT($E$2:$E$800) -> 0.0050062578 | I112: =(SUMPRODUCT(--ISNUMBER($G$2:$G$800),--($G$2:$G$800<G112))+(SUMPRODUCT(--ISNUMBER($G$2:$G$800),--($G$2:$G$800=G112))+1)/2)/COUNT($G$2:$G$800) -> 0.15519399 | J112: 33.745643 | K112: 21.806167 | L112: 0.58737151 | M112: =IF(OR(B112="NW",COUNT(Risk_Rank_Keys!B112)=0),0.5,(SUMPRODUCT(--ISNUMBER(Risk_Rank_Keys!$B$2:$B$800),--(Risk_Rank_Keys!$B$2:$B$800<Risk_Rank_Keys!B112))+(SUMPRODUCT(--ISNUMBER(Risk_Rank_Keys!$B$2:$B$800),--(Risk_Rank_Keys!$B$2:$B$800=Risk_Rank_Keys!B112))+1)/2)/COUNT(Risk_Rank_Keys!$B$2:$B$800)) -> 0.91910739 | N112: =IF(OR(B112="NW",COUNT(Risk_Rank_Keys!C112)=0),0.5,(SUMPRODUCT(--ISNUMBER(Risk_Rank_Keys!$C$2:$C$800),--(Risk_Rank_Keys!$C$2:$C$800<Risk_Rank_Keys!C112))+(SUMPRODUCT(--ISNUMBER(Risk_Rank_Keys!$C$2:$C$800),--(Risk_Rank_Keys!$C$2:$C$800=Risk_Rank_Keys!C112))+1)/2)/COUNT(Risk_Rank_Keys!$C$2:$C$800)) -> 0.9665272 | O112: =IF(OR(B112="NW",COUNT(Risk_Rank_Keys!D112)=0),0.5,(SUMPRODUCT(--ISNUMBER(Risk_Rank_Keys!$D$2:$D$800),--(Risk_Rank_Keys!$D$2:$D$800<Risk_Rank_Keys!D112))+(SUMPRODUCT(--ISNUMBER(Risk_Rank_Keys!$D$2:$D$800),--(Risk_Rank_Keys!$D$2:$D$800=Risk_Rank_Keys!D112))+1)/2)/COUNT(Risk_Rank_Keys!$D$2:$D$800)) -> 0.9748954 | P112: =AVERAGE(M112:O112) -> 0.95351 | Q112: =0.4*H112+0.4*I112+0.2*P112 -> 0.2547821 | R112: =PERCENTILE($Q$2:$Q$800,0.75) -> 0.66771572 | S112: =OR(Q112>=R112,AND(B112="CW",COUNT(J112:L112)<3)) -> FALSE | T112: 0.11889454 | U112: 5.1504467 | V112: 0.2547821 | W112: =Q112-V112 -> 0
A113: 2021-08-05 | B113: NW | C113: 13.957404 | D113: =SUMPRODUCT(Risk_Inputs!B113:AJ113,Risk_Coefs!$B$2:$AJ$2) -> -0.66330707 | E113: =1/(1+EXP(-MAX(-25,MIN(25,D113)))) -> 0.33999712 | F113: =SUMPRODUCT(Risk_Inputs!B113:AJ113,Risk_Coefs!$B$3:$AJ$3) -> 9.7193016 | G113: =MAX(0,F113) -> 9.7193016 | H113: =(SUMPRODUCT(--ISNUMBER($E$2:$E$800),--($E$2:$E$800<E113))+(SUMPRODUCT(--ISNUMBER($E$2:$E$800),--($E$2:$E$800=E113))+1)/2)/COUNT($E$2:$E$800) -> 0.78347935 | I113: =(SUMPRODUCT(--ISNUMBER($G$2:$G$800),--($G$2:$G$800<G113))+(SUMPRODUCT(--ISNUMBER($G$2:$G$800),--($G$2:$G$800=G113))+1)/2)/COUNT($G$2:$G$800) -> 0.7534418 | M113: =IF(OR(B113="NW",COUNT(Risk_Rank_Keys!B113)=0),0.5,(SUMPRODUCT(--ISNUMBER(Risk_Rank_Keys!$B$2:$B$800),--(Risk_Rank_Keys!$B$2:$B$800<Risk_Rank_Keys!B113))+(SUMPRODUCT(--ISNUMBER(Risk_Rank_Keys!$B$2:$B$800),--(Risk_Rank_Keys!$B$2:$B$800=Risk_Rank_Keys!B113))+1)/2)/COUNT(Risk_Rank_Keys!$B$2:$B$800)) -> 0.5 | N113: =IF(OR(B113="NW",COUNT(Risk_Rank_Keys!C113)=0),0.5,(SUMPRODUCT(--ISNUMBER(Risk_Rank_Keys!$C$2:$C$800),--(Risk_Rank_Keys!$C$2:$C$800<Risk_Rank_Keys!C113))+(SUMPRODUCT(--ISNUMBER(Risk_Rank_Keys!$C$2:$C$800),--(Risk_Rank_Keys!$C$2:$C$800=Risk_Rank_Keys!C113))+1)/2)/COUNT(Risk_Rank_Keys!$C$2:$C$800)) -> 0.5 | O113: =IF(OR(B113="NW",COUNT(Risk_Rank_Keys!D113)=0),0.5,(SUMPRODUCT(--ISNUMBER(Risk_Rank_Keys!$D$2:$D$800),--(Risk_Rank_Keys!$D$2:$D$800<Risk_Rank_Keys!D113))+(SUMPRODUCT(--ISNUMBER(Risk_Rank_Keys!$D$2:$D$800),--(Risk_Rank_Keys!$D$2:$D$800=Risk_Rank_Keys!D113))+1)/2)/COUNT(Risk_Rank_Keys!$D$2:$D$800)) -> 0.5 | P113: =AVERAGE(M113:O113) -> 0.5 | Q113: =0.4*H113+0.4*I113+0.2*P113 -> 0.71476846 | R113: =PERCENTILE($Q$2:$Q$800,0.75) -> 0.66771572 | S113: =OR(Q113>=R113,AND(B113="CW",COUNT(J113:L113)<3)) -> TRUE | T113: 0.33999712 | U113: 9.7193016 | V113: 0.71476846 | W113: =Q113-V113 -> 0
A114: 2021-08-11 | B114: CW | C114: 36.583254 | D114: =SUMPRODUCT(Risk_Inputs!B114:AJ114,Risk_Coefs!$B$2:$AJ$2) -> -0.76491917 | E114: =1/(1+EXP(-MAX(-25,MIN(25,D114)))) -> 0.31757922 | F114: =SUMPRODUCT(Risk_Inputs!B114:AJ114,Risk_Coefs!$B$3:$AJ$3) -> 10.460566 | G114: =MAX(0,F114) -> 10.460566 | H114: =(SUMPRODUCT(--ISNUMBER($E$2:$E$800),--($E$2:$E$800<E114))+(SUMPRODUCT(--ISNUMBER($E$2:$E$800),--($E$2:$E$800=E114))+1)/2)/COUNT($E$2:$E$800) -> 0.65707134 | I114: =(SUMPRODUCT(--ISNUMBER($G$2:$G$800),--($G$2:$G$800<G114))+(SUMPRODUCT(--ISNUMBER($G$2:$G$800),--($G$2:$G$800=G114))+1)/2)/COUNT($G$2:$G$800) -> 0.83604506 | J114: 7.6155148 | K114: 4.8906049 | L114: 0.25740026 | M114: =IF(OR(B114="NW",COUNT(Risk_Rank_Keys!B114)=0),0.5,(SUMPRODUCT(--ISNUMBER(Risk_Rank_Keys!$B$2:$B$800),--(Risk_Rank_Keys!$B$2:$B$800<Risk_Rank_Keys!B114))+(SUMPRODUCT(--ISNUMBER(Risk_Rank_Keys!$B$2:$B$800),--(Risk_Rank_Keys!$B$2:$B$800=Risk_Rank_Keys!B114))+1)/2)/COUNT(Risk_Rank_Keys!$B$2:$B$800)) -> 0.36262204 | N114: =IF(OR(B114="NW",COUNT(Risk_Rank_Keys!C114)=0),0.5,(SUMPRODUCT(--ISNUMBER(Risk_Rank_Keys!$C$2:$C$800),--(Risk_Rank_Keys!$C$2:$C$800<Risk_Rank_Keys!C114))+(SUMPRODUCT(--ISNUMBER(Risk_Rank_Keys!$C$2:$C$800),--(Risk_Rank_Keys!$C$2:$C$800=Risk_Rank_Keys!C114))+1)/2)/COUNT(Risk_Rank_Keys!$C$2:$C$800)) -> 0.68619247 | O114: =IF(OR(B114="NW",COUNT(Risk_Rank_Keys!D114)=0),0.5,(SUMPRODUCT(--ISNUMBER(Risk_Rank_Keys!$D$2:$D$800),--(Risk_Rank_Keys!$D$2:$D$800<Risk_Rank_Keys!D114))+(SUMPRODUCT(--ISNUMBER(Risk_Rank_Keys!$D$2:$D$800),--(Risk_Rank_Keys!$D$2:$D$800=Risk_Rank_Keys!D114))+1)/2)/COUNT(Risk_Rank_Keys!$D$2:$D$800)) -> 0.61645746 | P114: =AVERAGE(M114:O114) -> 0.55509066 | Q114: =0.4*H114+0.4*I114+0.2*P114 -> 0.70826469 | R114: =PERCENTILE($Q$2:$Q$800,0.75) -> 0.66771572 | S114: =OR(Q114>=R114,AND(B114="CW",COUNT(J114:L114)<3)) -> TRUE | T114: 0.31757922 | U114: 10.460566 | V114: 0.70826469 | W114: =Q114-V114 -> 0
A115: 2021-08-12 | B115: NW | C115: 21.640783 | D115: =SUMPRODUCT(Risk_Inputs!B115:AJ115,Risk_Coefs!$B$2:$AJ$2) -> -0.74907109 | E115: =1/(1+EXP(-MAX(-25,MIN(25,D115)))) -> 0.32102374 | F115: =SUMPRODUCT(Risk_Inputs!B115:AJ115,Risk_Coefs!$B$3:$AJ$3) -> 9.1299021 | G115: =MAX(0,F115) -> 9.1299021 | H115: =(SUMPRODUCT(--ISNUMBER($E$2:$E$800),--($E$2:$E$800<E115))+(SUMPRODUCT(--ISNUMBER($E$2:$E$800),--($E$2:$E$800=E115))+1)/2)/COUNT($E$2:$E$800) -> 0.67834793 | I115: =(SUMPRODUCT(--ISNUMBER($G$2:$G$800),--($G$2:$G$800<G115))+(SUMPRODUCT(--ISNUMBER($G$2:$G$800),--($G$2:$G$800=G115))+1)/2)/COUNT($G$2:$G$800) -> 0.69586984 | M115: =IF(OR(B115="NW",COUNT(Risk_Rank_Keys!B115)=0),0.5,(SUMPRODUCT(--ISNUMBER(Risk_Rank_Keys!$B$2:$B$800),--(Risk_Rank_Keys!$B$2:$B$800<Risk_Rank_Keys!B115))+(SUMPRODUCT(--ISNUMBER(Risk_Rank_Keys!$B$2:$B$800),--(Risk_Rank_Keys!$B$2:$B$800=Risk_Rank_Keys!B115))+1)/2)/COUNT(Risk_Rank_Keys!$B$2:$B$800)) -> 0.5 | N115: =IF(OR(B115="NW",COUNT(Risk_Rank_Keys!C115)=0),0.5,(SUMPRODUCT(--ISNUMBER(Risk_Rank_Keys!$C$2:$C$800),--(Risk_Rank_Keys!$C$2:$C$800<Risk_Rank_Keys!C115))+(SUMPRODUCT(--ISNUMBER(Risk_Rank_Keys!$C$2:$C$800),--(Risk_Rank_Keys!$C$2:$C$800=Risk_Rank_Keys!C115))+1)/2)/COUNT(Risk_Rank_Keys!$C$2:$C$800)) -> 0.5 | O115: =IF(OR(B115="NW",COUNT(Risk_Rank_Keys!D115)=0),0.5,(SUMPRODUCT(--ISNUMBER(Risk_Rank_Keys!$D$2:$D$800),--(Risk_Rank_Keys!$D$2:$D$800<Risk_Rank_Keys!D115))+(SUMPRODUCT(--ISNUMBER(Risk_Rank_Keys!$D$2:$D$800),--(Risk_Rank_Keys!$D$2:$D$800=Risk_Rank_Keys!D115))+1)/2)/COUNT(Risk_Rank_Keys!$D$2:$D$800)) -> 0.5 | P115: =AVERAGE(M115:O115) -> 0.5 | Q115: =0.4*H115+0.4*I115+0.2*P115 -> 0.64968711 | R115: =PERCENTILE($Q$2:$Q$800,0.75) -> 0.66771572 | S115: =OR(Q115>=R115,AND(B115="CW",COUNT(J115:L115)<3)) -> FALSE | T115: 0.32102374 | U115: 9.1299021 | V115: 0.64968711 | W115: =Q115-V115 -> 0
A116: 2021-08-16 | B116: CW | C116: 11.303362 | D116: =SUMPRODUCT(Risk_Inputs!B116:AJ116,Risk_Coefs!$B$2:$AJ$2) -> -0.83330879 | E116: =1/(1+EXP(-MAX(-25,MIN(25,D116)))) -> 0.3029459 | F116: =SUMPRODUCT(Risk_Inputs!B116:AJ116,Risk_Coefs!$B$3:$AJ$3) -> 6.5377925 | G116: =MAX(0,F116) -> 6.5377925 | H116: =(SUMPRODUCT(--ISNUMBER($E$2:$E$800),--($E$2:$E$800<E116))+(SUMPRODUCT(--ISNUMBER($E$2:$E$800),--($E$2:$E$800=E116))+1)/2)/COUNT($E$2:$E$800) -> 0.58322904 | I116: =(SUMPRODUCT(--ISNUMBER($G$2:$G$800),--($G$2:$G$800<G116))+(SUMPRODUCT(--ISNUMBER($G$2:$G$800),--($G$2:$G$800=G116))+1)/2)/COUNT($G$2:$G$800) -> 0.34793492 | J116: 8.5192821 | K116: 1.9808307 | L116: 0.19169329 | M116: =IF(OR(B116="NW",COUNT(Risk_Rank_Keys!B116)=0),0.5,(SUMPRODUCT(--ISNUMBER(Risk_Rank_Keys!$B$2:$B$800),--(Risk_Rank_Keys!$B$2:$B$800<Risk_Rank_Keys!B116))+(SUMPRODUCT(--ISNUMBER(Risk_Rank_Keys!$B$2:$B$800),--(Risk_Rank_Keys!$B$2:$B$800=Risk_Rank_Keys!B116))+1)/2)/COUNT(Risk_Rank_Keys!$B$2:$B$800)) -> 0.41841004 | N116: =IF(OR(B116="NW",COUNT(Risk_Rank_Keys!C116)=0),0.5,(SUMPRODUCT(--ISNUMBER(Risk_Rank_Keys!$C$2:$C$800),--(Risk_Rank_Keys!$C$2:$C$800<Risk_Rank_Keys!C116))+(SUMPRODUCT(--ISNUMBER(Risk_Rank_Keys!$C$2:$C$800),--(Risk_Rank_Keys!$C$2:$C$800=Risk_Rank_Keys!C116))+1)/2)/COUNT(Risk_Rank_Keys!$C$2:$C$800)) -> 0.26499303 | O116: =IF(OR(B116="NW",COUNT(Risk_Rank_Keys!D116)=0),0.5,(SUMPRODUCT(--ISNUMBER(Risk_Rank_Keys!$D$2:$D$800),--(Risk_Rank_Keys!$D$2:$D$800<Risk_Rank_Keys!D116))+(SUMPRODUCT(--ISNUMBER(Risk_Rank_Keys!$D$2:$D$800),--(Risk_Rank_Keys!$D$2:$D$800=Risk_Rank_Keys!D116))+1)/2)/COUNT(Risk_Rank_Keys!$D$2:$D$800)) -> 0.26220363 | P116: =AVERAGE(M116:O116) -> 0.31520223 | Q116: =0.4*H116+0.4*I116+0.2*P116 -> 0.43550603 | R116: =PERCENTILE($Q$2:$Q$800,0.75) -> 0.66771572 | S116: =OR(Q116>=R116,AND(B116="CW",COUNT(J116:L116)<3)) -> FALSE | T116: 0.3029459 | U116: 6.5377925 | V116: 0.43550603 | W116: =Q116-V116 -> 0
A117: 2021-08-17 | B117: CW | C117: -4.9767561 | D117: =SUMPRODUCT(Risk_Inputs!B117:AJ117,Risk_Coefs!$B$2:$AJ$2) -> -1.0468973 | E117: =1/(1+EXP(-MAX(-25,MIN(25,D117)))) -> 0.25982134 | F117: =SUMPRODUCT(Risk_Inputs!B117:AJ117,Risk_Coefs!$B$3:$AJ$3) -> 5.7928597 | G117: =MAX(0,F117) -> 5.7928597 | H117: =(SUMPRODUCT(--ISNUMBER($E$2:$E$800),--($E$2:$E$800<E117))+(SUMPRODUCT(--ISNUMBER($E$2:$E$800),--($E$2:$E$800=E117))+1)/2)/COUNT($E$2:$E$800) -> 0.33291615 | I117: =(SUMPRODUCT(--ISNUMBER($G$2:$G$800),--($G$2:$G$800<G117))+(SUMPRODUCT(--ISNUMBER($G$2:$G$800),--($G$2:$G$800=G117))+1)/2)/COUNT($G$2:$G$800) -> 0.24030038 | J117: 11.651308 | K117: 8.0796693 | L117: 0.30063886 | M117: =IF(OR(B117="NW",COUNT(Risk_Rank_Keys!B117)=0),0.5,(SUMPRODUCT(--ISNUMBER(Risk_Rank_Keys!$B$2:$B$800),--(Risk_Rank_Keys!$B$2:$B$800<Risk_Rank_Keys!B117))+(SUMPRODUCT(--ISNUMBER(Risk_Rank_Keys!$B$2:$B$800),--(Risk_Rank_Keys!$B$2:$B$800=Risk_Rank_Keys!B117))+1)/2)/COUNT(Risk_Rank_Keys!$B$2:$B$800)) -> 0.58298466 | N117: =IF(OR(B117="NW",COUNT(Risk_Rank_Keys!C117)=0),0.5,(SUMPRODUCT(--ISNUMBER(Risk_Rank_Keys!$C$2:$C$800),--(Risk_Rank_Keys!$C$2:$C$800<Risk_Rank_Keys!C117))+(SUMPRODUCT(--ISNUMBER(Risk_Rank_Keys!$C$2:$C$800),--(Risk_Rank_Keys!$C$2:$C$800=Risk_Rank_Keys!C117))+1)/2)/COUNT(Risk_Rank_Keys!$C$2:$C$800)) -> 0.82566248 | O117: =IF(OR(B117="NW",COUNT(Risk_Rank_Keys!D117)=0),0.5,(SUMPRODUCT(--ISNUMBER(Risk_Rank_Keys!$D$2:$D$800),--(Risk_Rank_Keys!$D$2:$D$800<Risk_Rank_Keys!D117))+(SUMPRODUCT(--ISNUMBER(Risk_Rank_Keys!$D$2:$D$800),--(Risk_Rank_Keys!$D$2:$D$800=Risk_Rank_Keys!D117))+1)/2)/COUNT(Risk_Rank_Keys!$D$2:$D$800)) -> 0.74616457 | P117: =AVERAGE(M117:O117) -> 0.71827057 | Q117: =0.4*H117+0.4*I117+0.2*P117 -> 0.37294072 | R117: =PERCENTILE($Q$2:$Q$800,0.75) -> 0.66771572 | S117: =OR(Q117>=R117,AND(B117="CW",COUNT(J117:L117)<3)) -> FALSE | T117: 0.25982134 | U117: 5.7928597 | V117: 0.37294072 | W117: =Q117-V117 -> 0
A118: 2021-08-30 | B118: CW | C118: -25.483181 | D118: =SUMPRODUCT(Risk_Inputs!B118:AJ118,Risk_Coefs!$B$2:$AJ$2) -> -0.72194957 | E118: =1/(1+EXP(-MAX(-25,MIN(25,D118)))) -> 0.32696382 | F118: =SUMPRODUCT(Risk_Inputs!B118:AJ118,Risk_Coefs!$B$3:$AJ$3) -> 9.2272051 | G118: =MAX(0,F118) -> 9.2272051 | H118: =(SUMPRODUCT(--ISNUMBER($E$2:$E$800),--($E$2:$E$800<E118))+(SUMPRODUCT(--ISNUMBER($E$2:$E$800),--($E$2:$E$800=E118))+1)/2)/COUNT($E$2:$E$800) -> 0.71589487 | I118: =(SUMPRODUCT(--ISNUMBER($G$2:$G$800),--($G$2:$G$800<G118))+(SUMPRODUCT(--ISNUMBER($G$2:$G$800),--($G$2:$G$800=G118))+1)/2)/COUNT($G$2:$G$800) -> 0.70838548 | J118: 7.2375926 | K118: 1.4523449 | L118: 0.2118003 | M118: =IF(OR(B118="NW",COUNT(Risk_Rank_Keys!B118)=0),0.5,(SUMPRODUCT(--ISNUMBER(Risk_Rank_Keys!$B$2:$B$800),--(Risk_Rank_Keys!$B$2:$B$800<Risk_Rank_Keys!B118))+(SUMPRODUCT(--ISNUMBER(Risk_Rank_Keys!$B$2:$B$800),--(Risk_Rank_Keys!$B$2:$B$800=Risk_Rank_Keys!B118))+1)/2)/COUNT(Risk_Rank_Keys!$B$2:$B$800)) -> 0.33193863 | N118: =IF(OR(B118="NW",COUNT(Risk_Rank_Keys!C118)=0),0.5,(SUMPRODUCT(--ISNUMBER(Risk_Rank_Keys!$C$2:$C$800),--(Risk_Rank_Keys!$C$2:$C$800<Risk_Rank_Keys!C118))+(SUMPRODUCT(--ISNUMBER(Risk_Rank_Keys!$C$2:$C$800),--(Risk_Rank_Keys!$C$2:$C$800=Risk_Rank_Keys!C118))+1)/2)/COUNT(Risk_Rank_Keys!$C$2:$C$800)) -> 0.11994421 | O118: =IF(OR(B118="NW",COUNT(Risk_Rank_Keys!D118)=0),0.5,(SUMPRODUCT(--ISNUMBER(Risk_Rank_Keys!$D$2:$D$800),--(Risk_Rank_Keys!$D$2:$D$800<Risk_Rank_Keys!D118))+(SUMPRODUCT(--ISNUMBER(Risk_Rank_Keys!$D$2:$D$800),--(Risk_Rank_Keys!$D$2:$D$800=Risk_Rank_Keys!D118))+1)/2)/COUNT(Risk_Rank_Keys!$D$2:$D$800)) -> 0.39051604 | P118: =AVERAGE(M118:O118) -> 0.28079963 | Q118: =0.4*H118+0.4*I118+0.2*P118 -> 0.62587207 | R118: =PERCENTILE($Q$2:$Q$800,0.75) -> 0.66771572 | S118: =OR(Q118>=R118,AND(B118="CW",COUNT(J118:L118)<3)) -> FALSE | T118: 0.32696382 | U118: 9.2272051 | V118: 0.62587207 | W118: =Q118-V118 -> 0
A119: 2021-08-31 | B119: CW | C119: -39.395642 | D119: =SUMPRODUCT(Risk_Inputs!B119:AJ119,Risk_Coefs!$B$2:$AJ$2) -> -1.1190283 | E119: =1/(1+EXP(-MAX(-25,MIN(25,D119)))) -> 0.24619158 | F119: =SUMPRODUCT(Risk_Inputs!B119:AJ119,Risk_Coefs!$B$3:$AJ$3) -> 6.4054772 | G119: =MAX(0,F119) -> 6.4054772 | H119: =(SUMPRODUCT(--ISNUMBER($E$2:$E$800),--($E$2:$E$800<E119))+(SUMPRODUCT(--ISNUMBER($E$2:$E$800),--($E$2:$E$800=E119))+1)/2)/COUNT($E$2:$E$800) -> 0.24780976 | I119: =(SUMPRODUCT(--ISNUMBER($G$2:$G$800),--($G$2:$G$800<G119))+(SUMPRODUCT(--ISNUMBER($G$2:$G$800),--($G$2:$G$800=G119))+1)/2)/COUNT($G$2:$G$800) -> 0.32790989 | J119: 6.9609332 | K119: 3.9737274 | L119: 0.22988506 | M119: =IF(OR(B119="NW",COUNT(Risk_Rank_Keys!B119)=0),0.5,(SUMPRODUCT(--ISNUMBER(Risk_Rank_Keys!$B$2:$B$800),--(Risk_Rank_Keys!$B$2:$B$800<Risk_Rank_Keys!B119))+(SUMPRODUCT(--ISNUMBER(Risk_Rank_Keys!$B$2:$B$800),--(Risk_Rank_Keys!$B$2:$B$800=Risk_Rank_Keys!B119))+1)/2)/COUNT(Risk_Rank_Keys!$B$2:$B$800)) -> 0.30962343 | N119: =IF(OR(B119="NW",COUNT(Risk_Rank_Keys!C119)=0),0.5,(SUMPRODUCT(--ISNUMBER(Risk_Rank_Keys!$C$2:$C$800),--(Risk_Rank_Keys!$C$2:$C$800<Risk_Rank_Keys!C119))+(SUMPRODUCT(--ISNUMBER(Risk_Rank_Keys!$C$2:$C$800),--(Risk_Rank_Keys!$C$2:$C$800=Risk_Rank_Keys!C119))+1)/2)/COUNT(Risk_Rank_Keys!$C$2:$C$800)) -> 0.59274756 | O119: =IF(OR(B119="NW",COUNT(Risk_Rank_Keys!D119)=0),0.5,(SUMPRODUCT(--ISNUMBER(Risk_Rank_Keys!$D$2:$D$800),--(Risk_Rank_Keys!$D$2:$D$800<Risk_Rank_Keys!D119))+(SUMPRODUCT(--ISNUMBER(Risk_Rank_Keys!$D$2:$D$800),--(Risk_Rank_Keys!$D$2:$D$800=Risk_Rank_Keys!D119))+1)/2)/COUNT(Risk_Rank_Keys!$D$2:$D$800)) -> 0.50209205 | P119: =AVERAGE(M119:O119) -> 0.46815435 | Q119: =0.4*H119+0.4*I119+0.2*P119 -> 0.32391873 | R119: =PERCENTILE($Q$2:$Q$800,0.75) -> 0.66771572 | S119: =OR(Q119>=R119,AND(B119="CW",COUNT(J119:L119)<3)) -> FALSE | T119: 0.24619158 | U119: 6.4054772 | V119: 0.32391873 | W119: =Q119-V119 -> 0
A120: 2021-09-02 | B120: NW | C120: -8.5542811 | D120: =SUMPRODUCT(Risk_Inputs!B120:AJ120,Risk_Coefs!$B$2:$AJ$2) -> -0.64549286 | E120: =1/(1+EXP(-MAX(-25,MIN(25,D120)))) -> 0.34400593 | F120: =SUMPRODUCT(Risk_Inputs!B120:AJ120,Risk_Coefs!$B$3:$AJ$3) -> 10.727927 | G120: =MAX(0,F120) -> 10.727927 | H120: =(SUMPRODUCT(--ISNUMBER($E$2:$E$800),--($E$2:$E$800<E120))+(SUMPRODUCT(--ISNUMBER($E$2:$E$800),--($E$2:$E$800=E120))+1)/2)/COUNT($E$2:$E$800) -> 0.79849812 | I120: =(SUMPRODUCT(--ISNUMBER($G$2:$G$800),--($G$2:$G$800<G120))+(SUMPRODUCT(--ISNUMBER($G$2:$G$800),--($G$2:$G$800=G120))+1)/2)/COUNT($G$2:$G$800) -> 0.85982478 | M120: =IF(OR(B120="NW",COUNT(Risk_Rank_Keys!B120)=0),0.5,(SUMPRODUCT(--ISNUMBER(Risk_Rank_Keys!$B$2:$B$800),--(Risk_Rank_Keys!$B$2:$B$800<Risk_Rank_Keys!B120))+(SUMPRODUCT(--ISNUMBER(Risk_Rank_Keys!$B$2:$B$800),--(Risk_Rank_Keys!$B$2:$B$800=Risk_Rank_Keys!B120))+1)/2)/COUNT(Risk_Rank_Keys!$B$2:$B$800)) -> 0.5 | N120: =IF(OR(B120="NW",COUNT(Risk_Rank_Keys!C120)=0),0.5,(SUMPRODUCT(--ISNUMBER(Risk_Rank_Keys!$C$2:$C$800),--(Risk_Rank_Keys!$C$2:$C$800<Risk_Rank_Keys!C120))+(SUMPRODUCT(--ISNUMBER(Risk_Rank_Keys!$C$2:$C$800),--(Risk_Rank_Keys!$C$2:$C$800=Risk_Rank_Keys!C120))+1)/2)/COUNT(Risk_Rank_Keys!$C$2:$C$800)) -> 0.5 | O120: =IF(OR(B120="NW",COUNT(Risk_Rank_Keys!D120)=0),0.5,(SUMPRODUCT(--ISNUMBER(Risk_Rank_Keys!$D$2:$D$800),--(Risk_Rank_Keys!$D$2:$D$800<Risk_Rank_Keys!D120))+(SUMPRODUCT(--ISNUMBER(Risk_Rank_Keys!$D$2:$D$800),--(Risk_Rank_Keys!$D$2:$D$800=Risk_Rank_Keys!D120))+1)/2)/COUNT(Risk_Rank_Keys!$D$2:$D$800)) -> 0.5 | P120: =AVERAGE(M120:O120) -> 0.5 | Q120: =0.4*H120+0.4*I120+0.2*P120 -> 0.76332916 | R120: =PERCENTILE($Q$2:$Q$800,0.75) -> 0.66771572 | S120: =OR(Q120>=R120,AND(B120="CW",COUNT(J120:L120)<3)) -> TRUE | T120: 0.34400593 | U120: 10.727927 | V120: 0.76332916 | W120: =Q120-V120 -> 0
A121: 2021-09-03 | B121: CW | C121: 9.6282903 | D121: =SUMPRODUCT(Risk_Inputs!B121:AJ121,Risk_Coefs!$B$2:$AJ$2) -> -1.5513318 | E121: =1/(1+EXP(-MAX(-25,MIN(25,D121)))) -> 0.174894 | F121: =SUMPRODUCT(Risk_Inputs!B121:AJ121,Risk_Coefs!$B$3:$AJ$3) -> 6.7735077 | G121: =MAX(0,F121) -> 6.7735077 | H121: =(SUMPRODUCT(--ISNUMBER($E$2:$E$800),--($E$2:$E$800<E121))+(SUMPRODUCT(--ISNUMBER($E$2:$E$800),--($E$2:$E$800=E121))+1)/2)/COUNT($E$2:$E$800) -> 0.052565707 | I121: =(SUMPRODUCT(--ISNUMBER($G$2:$G$800),--($G$2:$G$800<G121))+(SUMPRODUCT(--ISNUMBER($G$2:$G$800),--($G$2:$G$800=G121))+1)/2)/COUNT($G$2:$G$800) -> 0.38923655 | J121: 14.548378 | K121: 7.9282782 | L121: 0.38885288 | M121: =IF(OR(B121="NW",COUNT(Risk_Rank_Keys!B121)=0),0.5,(SUMPRODUCT(--ISNUMBER(Risk_Rank_Keys!$B$2:$B$800),--(Risk_Rank_Keys!$B$2:$B$800<Risk_Rank_Keys!B121))+(SUMPRODUCT(--ISNUMBER(Risk_Rank_Keys!$B$2:$B$800),--(Risk_Rank_Keys!$B$2:$B$800=Risk_Rank_Keys!B121))+1)/2)/COUNT(Risk_Rank_Keys!$B$2:$B$800)) -> 0.69456067 | N121: =IF(OR(B121="NW",COUNT(Risk_Rank_Keys!C121)=0),0.5,(SUMPRODUCT(--ISNUMBER(Risk_Rank_Keys!$C$2:$C$800),--(Risk_Rank_Keys!$C$2:$C$800<Risk_Rank_Keys!C121))+(SUMPRODUCT(--ISNUMBER(Risk_Rank_Keys!$C$2:$C$800),--(Risk_Rank_Keys!$C$2:$C$800=Risk_Rank_Keys!C121))+1)/2)/COUNT(Risk_Rank_Keys!$C$2:$C$800)) -> 0.81868898 | O121: =IF(OR(B121="NW",COUNT(Risk_Rank_Keys!D121)=0),0.5,(SUMPRODUCT(--ISNUMBER(Risk_Rank_Keys!$D$2:$D$800),--(Risk_Rank_Keys!$D$2:$D$800<Risk_Rank_Keys!D121))+(SUMPRODUCT(--ISNUMBER(Risk_Rank_Keys!$D$2:$D$800),--(Risk_Rank_Keys!$D$2:$D$800=Risk_Rank_Keys!D121))+1)/2)/COUNT(Risk_Rank_Keys!$D$2:$D$800)) -> 0.87308229 | P121: =AVERAGE(M121:O121) -> 0.79544398 | Q121: =0.4*H121+0.4*I121+0.2*P121 -> 0.3358097 | R121: =PERCENTILE($Q$2:$Q$800,0.75) -> 0.66771572 | S121: =OR(Q121>=R121,AND(B121="CW",COUNT(J121:L121)<3)) -> FALSE | T121: 0.174894 | U121: 6.7735077 | V121: 0.3358097 | W121: =Q121-V121 -> 0
A122: 2021-09-06 | B122: CW | C122: 22.117196 | D122: =SUMPRODUCT(Risk_Inputs!B122:AJ122,Risk_Coefs!$B$2:$AJ$2) -> -0.95876815 | E122: =1/(1+EXP(-MAX(-25,MIN(25,D122)))) -> 0.2771249 | F122: =SUMPRODUCT(Risk_Inputs!B122:AJ122,Risk_Coefs!$B$3:$AJ$3) -> 8.2694673 | G122: =MAX(0,F122) -> 8.2694673 | H122: =(SUMPRODUCT(--ISNUMBER($E$2:$E$800),--($E$2:$E$800<E122))+(SUMPRODUCT(--ISNUMBER($E$2:$E$800),--($E$2:$E$800=E122))+1)/2)/COUNT($E$2:$E$800) -> 0.44555695 | I122: =(SUMPRODUCT(--ISNUMBER($G$2:$G$800),--($G$2:$G$800<G122))+(SUMPRODUCT(--ISNUMBER($G$2:$G$800),--($G$2:$G$800=G122))+1)/2)/COUNT($G$2:$G$800) -> 0.57571965 | J122: 6.9019662 | K122: 4.6926804 | L122: 0.28054068 | M122: =IF(OR(B122="NW",COUNT(Risk_Rank_Keys!B122)=0),0.5,(SUMPRODUCT(--ISNUMBER(Risk_Rank_Keys!$B$2:$B$800),--(Risk_Rank_Keys!$B$2:$B$800<Risk_Rank_Keys!B122))+(SUMPRODUCT(--ISNUMBER(Risk_Rank_Keys!$B$2:$B$800),--(Risk_Rank_Keys!$B$2:$B$800=Risk_Rank_Keys!B122))+1)/2)/COUNT(Risk_Rank_Keys!$B$2:$B$800)) -> 0.30404463 | N122: =IF(OR(B122="NW",COUNT(Risk_Rank_Keys!C122)=0),0.5,(SUMPRODUCT(--ISNUMBER(Risk_Rank_Keys!$C$2:$C$800),--(Risk_Rank_Keys!$C$2:$C$800<Risk_Rank_Keys!C122))+(SUMPRODUCT(--ISNUMBER(Risk_Rank_Keys!$C$2:$C$800),--(Risk_Rank_Keys!$C$2:$C$800=Risk_Rank_Keys!C122))+1)/2)/COUNT(Risk_Rank_Keys!$C$2:$C$800)) -> 0.66387727 | O122: =IF(OR(B122="NW",COUNT(Risk_Rank_Keys!D122)=0),0.5,(SUMPRODUCT(--ISNUMBER(Risk_Rank_Keys!$D$2:$D$800),--(Risk_Rank_Keys!$D$2:$D$800<Risk_Rank_Keys!D122))+(SUMPRODUCT(--ISNUMBER(Risk_Rank_Keys!$D$2:$D$800),--(Risk_Rank_Keys!$D$2:$D$800=Risk_Rank_Keys!D122))+1)/2)/COUNT(Risk_Rank_Keys!$D$2:$D$800)) -> 0.70013947 | P122: =AVERAGE(M122:O122) -> 0.55602046 | Q122: =0.4*H122+0.4*I122+0.2*P122 -> 0.51971473 | R122: =PERCENTILE($Q$2:$Q$800,0.75) -> 0.66771572 | S122: =OR(Q122>=R122,AND(B122="CW",COUNT(J122:L122)<3)) -> FALSE | T122: 0.2771249 | U122: 8.2694673 | V122: 0.51971473 | W122: =Q122-V122 -> 0
A123: 2021-09-07 | B123: CW | C123: 28.579619 | D123: =SUMPRODUCT(Risk_Inputs!B123:AJ123,Risk_Coefs!$B$2:$AJ$2) -> -0.95328741 | E123: =1/(1+EXP(-MAX(-25,MIN(25,D123)))) -> 0.27822418 | F123: =SUMPRODUCT(Risk_Inputs!B123:AJ123,Risk_Coefs!$B$3:$AJ$3) -> 7.3185512 | G123: =MAX(0,F123) -> 7.3185512 | H123: =(SUMPRODUCT(--ISNUMBER($E$2:$E$800),--($E$2:$E$800<E123))+(SUMPRODUCT(--ISNUMBER($E$2:$E$800),--($E$2:$E$800=E123))+1)/2)/COUNT($E$2:$E$800) -> 0.45556946 | I123: =(SUMPRODUCT(--ISNUMBER($G$2:$G$800),--($G$2:$G$800<G123))+(SUMPRODUCT(--ISNUMBER($G$2:$G$800),--($G$2:$G$800=G123))+1)/2)/COUNT($G$2:$G$800) -> 0.45181477 | J123: 5.5498683 | K123: 1.1707596 | L123: 0.22844089 | M123: =IF(OR(B123="NW",COUNT(Risk_Rank_Keys!B123)=0),0.5,(SUMPRODUCT(--ISNUMBER(Risk_Rank_Keys!$B$2:$B$800),--(Risk_Rank_Keys!$B$2:$B$800<Risk_Rank_Keys!B123))+(SUMPRODUCT(--ISNUMBER(Risk_Rank_Keys!$B$2:$B$800),--(Risk_Rank_Keys!$B$2:$B$800=Risk_Rank_Keys!B123))+1)/2)/COUNT(Risk_Rank_Keys!$B$2:$B$800)) -> 0.17294282 | N123: =IF(OR(B123="NW",COUNT(Risk_Rank_Keys!C123)=0),0.5,(SUMPRODUCT(--ISNUMBER(Risk_Rank_Keys!$C$2:$C$800),--(Risk_Rank_Keys!$C$2:$C$800<Risk_Rank_Keys!C123))+(SUMPRODUCT(--ISNUMBER(Risk_Rank_Keys!$C$2:$C$800),--(Risk_Rank_Keys!$C$2:$C$800=Risk_Rank_Keys!C123))+1)/2)/COUNT(Risk_Rank_Keys!$C$2:$C$800)) -> 0.059972106 | O123: =IF(OR(B123="NW",COUNT(Risk_Rank_Keys!D123)=0),0.5,(SUMPRODUCT(--ISNUMBER(Risk_Rank_Keys!$D$2:$D$800),--(Risk_Rank_Keys!$D$2:$D$800<Risk_Rank_Keys!D123))+(SUMPRODUCT(--ISNUMBER(Risk_Rank_Keys!$D$2:$D$800),--(Risk_Rank_Keys!$D$2:$D$800=Risk_Rank_Keys!D123))+1)/2)/COUNT(Risk_Rank_Keys!$D$2:$D$800)) -> 0.48953975 | P123: =AVERAGE(M123:O123) -> 0.24081822 | Q123: =0.4*H123+0.4*I123+0.2*P123 -> 0.41111734 | R123: =PERCENTILE($Q$2:$Q$800,0.75) -> 0.66771572 | S123: =OR(Q123>=R123,AND(B123="CW",COUNT(J123:L123)<3)) -> FALSE | T123: 0.27822418 | U123: 7.3185512 | V123: 0.41111734 | W123: =Q123-V123 -> 0
A124: 2021-09-08 | B124: CW | C124: 45.374257 | D124: =SUMPRODUCT(Risk_Inputs!B124:AJ124,Risk_Coefs!$B$2:$AJ$2) -> -0.96259254 | E124: =1/(1+EXP(-MAX(-25,MIN(25,D124)))) -> 0.27635942 | F124: =SUMPRODUCT(Risk_Inputs!B124:AJ124,Risk_Coefs!$B$3:$AJ$3) -> 8.257416 | G124: =MAX(0,F124) -> 8.257416 | H124: =(SUMPRODUCT(--ISNUMBER($E$2:$E$800),--($E$2:$E$800<E124))+(SUMPRODUCT(--ISNUMBER($E$2:$E$800),--($E$2:$E$800=E124))+1)/2)/COUNT($E$2:$E$800) -> 0.43804756 | I124: =(SUMPRODUCT(--ISNUMBER($G$2:$G$800),--($G$2:$G$800<G124))+(SUMPRODUCT(--ISNUMBER($G$2:$G$800),--($G$2:$G$800=G124))+1)/2)/COUNT($G$2:$G$800) -> 0.57321652 | J124: 10.315219 | K124: 3.2089552 | L124: 0.3358209 | M124: =IF(OR(B124="NW",COUNT(Risk_Rank_Keys!B124)=0),0.5,(SUMPRODUCT(--ISNUMBER(Risk_Rank_Keys!$B$2:$B$800),--(Risk_Rank_Keys!$B$2:$B$800<Risk_Rank_Keys!B124))+(SUMPRODUCT(--ISNUMBER(Risk_Rank_Keys!$B$2:$B$800),--(Risk_Rank_Keys!$B$2:$B$800=Risk_Rank_Keys!B124))+1)/2)/COUNT(Risk_Rank_Keys!$B$2:$B$800)) -> 0.52022315 | N124: =IF(OR(B124="NW",COUNT(Risk_Rank_Keys!C124)=0),0.5,(SUMPRODUCT(--ISNUMBER(Risk_Rank_Keys!$C$2:$C$800),--(Risk_Rank_Keys!$C$2:$C$800<Risk_Rank_Keys!C124))+(SUMPRODUCT(--ISNUMBER(Risk_Rank_Keys!$C$2:$C$800),--(Risk_Rank_Keys!$C$2:$C$800=Risk_Rank_Keys!C124))+1)/2)/COUNT(Risk_Rank_Keys!$C$2:$C$800)) -> 0.49511855 | O124: =IF(OR(B124="NW",COUNT(Risk_Rank_Keys!D124)=0),0.5,(SUMPRODUCT(--ISNUMBER(Risk_Rank_Keys!$D$2:$D$800),--(Risk_Rank_Keys!$D$2:$D$800<Risk_Rank_Keys!D124))+(SUMPRODUCT(--ISNUMBER(Risk_Rank_Keys!$D$2:$D$800),--(Risk_Rank_Keys!$D$2:$D$800=Risk_Rank_Keys!D124))+1)/2)/COUNT(Risk_Rank_Keys!$D$2:$D$800)) -> 0.80892608 | P124: =AVERAGE(M124:O124) -> 0.60808926 | Q124: =0.4*H124+0.4*I124+0.2*P124 -> 0.52612348 | R124: =PERCENTILE($Q$2:$Q$800,0.75) -> 0.66771572 | S124: =OR(Q124>=R124,AND(B124="CW",COUNT(J124:L124)<3)) -> FALSE | T124: 0.27635942 | U124: 8.257416 | V124: 0.52612348 | W124: =Q124-V124 -> 0
A125: 2021-09-09 | B125: NW | C125: 12.349782 | D125: =SUMPRODUCT(Risk_Inputs!B125:AJ125,Risk_Coefs!$B$2:$AJ$2) -> -0.64949521 | E125: =1/(1+EXP(-MAX(-25,MIN(25,D125)))) -> 0.3431033 | F125: =SUMPRODUCT(Risk_Inputs!B125:AJ125,Risk_Coefs!$B$3:$AJ$3) -> 10.103516 | G125: =MAX(0,F125) -> 10.103516 | H125: =(SUMPRODUCT(--ISNUMBER($E$2:$E$800),--($E$2:$E$800<E125))+(SUMPRODUCT(--ISNUMBER($E$2:$E$800),--($E$2:$E$800=E125))+1)/2)/COUNT($E$2:$E$800) -> 0.79474343 | I125: =(SUMPRODUCT(--ISNUMBER($G$2:$G$800),--($G$2:$G$800<G125))+(SUMPRODUCT(--ISNUMBER($G$2:$G$800),--($G$2:$G$800=G125))+1)/2)/COUNT($G$2:$G$800) -> 0.80100125 | M125: =IF(OR(B125="NW",COUNT(Risk_Rank_Keys!B125)=0),0.5,(SUMPRODUCT(--ISNUMBER(Risk_Rank_Keys!$B$2:$B$800),--(Risk_Rank_Keys!$B$2:$B$800<Risk_Rank_Keys!B125))+(SUMPRODUCT(--ISNUMBER(Risk_Rank_Keys!$B$2:$B$800),--(Risk_Rank_Keys!$B$2:$B$800=Risk_Rank_Keys!B125))+1)/2)/COUNT(Risk_Rank_Keys!$B$2:$B$800)) -> 0.5 | N125: =IF(OR(B125="NW",COUNT(Risk_Rank_Keys!C125)=0),0.5,(SUMPRODUCT(--ISNUMBER(Risk_Rank_Keys!$C$2:$C$800),--(Risk_Rank_Keys!$C$2:$C$800<Risk_Rank_Keys!C125))+(SUMPRODUCT(--ISNUMBER(Risk_Rank_Keys!$C$2:$C$800),--(Risk_Rank_Keys!$C$2:$C$800=Risk_Rank_Keys!C125))+1)/2)/COUNT(Risk_Rank_Keys!$C$2:$C$800)) -> 0.5 | O125: =IF(OR(B125="NW",COUNT(Risk_Rank_Keys!D125)=0),0.5,(SUMPRODUCT(--ISNUMBER(Risk_Rank_Keys!$D$2:$D$800),--(Risk_Rank_Keys!$D$2:$D$800<Risk_Rank_Keys!D125))+(SUMPRODUCT(--ISNUMBER(Risk_Rank_Keys!$D$2:$D$800),--(Risk_Rank_Keys!$D$2:$D$800=Risk_Rank_Keys!D125))+1)/2)/COUNT(Risk_Rank_Keys!$D$2:$D$800)) -> 0.5 | P125: =AVERAGE(M125:O125) -> 0.5 | Q125: =0.4*H125+0.4*I125+0.2*P125 -> 0.73829787 | R125: =PERCENTILE($Q$2:$Q$800,0.75) -> 0.66771572 | S125: =OR(Q125>=R125,AND(B125="CW",COUNT(J125:L125)<3)) -> TRUE | T125: 0.3431033 | U125: 10.103516 | V125: 0.73829787 | W125: =Q125-V125 -> 0
A126: 2021-09-13 | B126: CW | C126: 37.211347 | D126: =SUMPRODUCT(Risk_Inputs!B126:AJ126,Risk_Coefs!$B$2:$AJ$2) -> -0.92620492 | E126: =1/(1+EXP(-MAX(-25,MIN(25,D126)))) -> 0.28369529 | F126: =SUMPRODUCT(Risk_Inputs!B126:AJ126,Risk_Coefs!$B$3:$AJ$3) -> 7.7247657 | G126: =MAX(0,F126) -> 7.7247657 | H126: =(SUMPRODUCT(--ISNUMBER($E$2:$E$800),--($E$2:$E$800<E126))+(SUMPRODUCT(--ISNUMBER($E$2:$E$800),--($E$2:$E$800=E126))+1)/2)/COUNT($E$2:$E$800) -> 0.48060075 | I126: =(SUMPRODUCT(--ISNUMBER($G$2:$G$800),--($G$2:$G$800<G126))+(SUMPRODUCT(--ISNUMBER($G$2:$G$800),--($G$2:$G$800=G126))+1)/2)/COUNT($G$2:$G$800) -> 0.51689612 | J126: 21.583626 | K126: 3.9467069 | L126: 0.30165913 | M126: =IF(OR(B126="NW",COUNT(Risk_Rank_Keys!B126)=0),0.5,(SUMPRODUCT(--ISNUMBER(Risk_Rank_Keys!$B$2:$B$800),--(Risk_Rank_Keys!$B$2:$B$800<Risk_Rank_Keys!B126))+(SUMPRODUCT(--ISNUMBER(Risk_Rank_Keys!$B$2:$B$800),--(Risk_Rank_Keys!$B$2:$B$800=Risk_Rank_Keys!B126))+1)/2)/COUNT(Risk_Rank_Keys!$B$2:$B$800)) -> 0.81729428 | N126: =IF(OR(B126="NW",COUNT(Risk_Rank_Keys!C126)=0),0.5,(SUMPRODUCT(--ISNUMBER(Risk_Rank_Keys!$C$2:$C$800),--(Risk_Rank_Keys!$C$2:$C$800<Risk_Rank_Keys!C126))+(SUMPRODUCT(--ISNUMBER(Risk_Rank_Keys!$C$2:$C$800),--(Risk_Rank_Keys!$C$2:$C$800=Risk_Rank_Keys!C126))+1)/2)/COUNT(Risk_Rank_Keys!$C$2:$C$800)) -> 0.58995816 | O126: =IF(OR(B126="NW",COUNT(Risk_Rank_Keys!D126)=0),0.5,(SUMPRODUCT(--ISNUMBER(Risk_Rank_Keys!$D$2:$D$800),--(Risk_Rank_Keys!$D$2:$D$800<Risk_Rank_Keys!D126))+(SUMPRODUCT(--ISNUMBER(Risk_Rank_Keys!$D$2:$D$800),--(Risk_Rank_Keys!$D$2:$D$800=Risk_Rank_Keys!D126))+1)/2)/COUNT(Risk_Rank_Keys!$D$2:$D$800)) -> 0.74895397 | P126: =AVERAGE(M126:O126) -> 0.71873547 | Q126: =0.4*H126+0.4*I126+0.2*P126 -> 0.54274584 | R126: =PERCENTILE($Q$2:$Q$800,0.75) -> 0.66771572 | S126: =OR(Q126>=R126,AND(B126="CW",COUNT(J126:L126)<3)) -> FALSE | T126: 0.28369529 | U126: 7.7247657 | V126: 0.54274584 | W126: =Q126-V126 -> 0
A127: 2021-09-22 | B127: NW | C127: 10.095023 | D127: =SUMPRODUCT(Risk_Inputs!B127:AJ127,Risk_Coefs!$B$2:$AJ$2) -> -0.40253792 | E127: =1/(1+EXP(-MAX(-25,MIN(25,D127)))) -> 0.40070273 | F127: =SUMPRODUCT(Risk_Inputs!B127:AJ127,Risk_Coefs!$B$3:$AJ$3) -> 12.381458 | G127: =MAX(0,F127) -> 12.381458 | H127: =(SUMPRODUCT(--ISNUMBER($E$2:$E$800),--($E$2:$E$800<E127))+(SUMPRODUCT(--ISNUMBER($E$2:$E$800),--($E$2:$E$800=E127))+1)/2)/COUNT($E$2:$E$800) -> 0.94493116 | I127: =(SUMPRODUCT(--ISNUMBER($G$2:$G$800),--($G$2:$G$800<G127))+(SUMPRODUCT(--ISNUMBER($G$2:$G$800),--($G$2:$G$800=G127))+1)/2)/COUNT($G$2:$G$800) -> 0.93867334 | M127: =IF(OR(B127="NW",COUNT(Risk_Rank_Keys!B127)=0),0.5,(SUMPRODUCT(--ISNUMBER(Risk_Rank_Keys!$B$2:$B$800),--(Risk_Rank_Keys!$B$2:$B$800<Risk_Rank_Keys!B127))+(SUMPRODUCT(--ISNUMBER(Risk_Rank_Keys!$B$2:$B$800),--(Risk_Rank_Keys!$B$2:$B$800=Risk_Rank_Keys!B127))+1)/2)/COUNT(Risk_Rank_Keys!$B$2:$B$800)) -> 0.5 | N127: =IF(OR(B127="NW",COUNT(Risk_Rank_Keys!C127)=0),0.5,(SUMPRODUCT(--ISNUMBER(Risk_Rank_Keys!$C$2:$C$800),--(Risk_Rank_Keys!$C$2:$C$800<Risk_Rank_Keys!C127))+(SUMPRODUCT(--ISNUMBER(Risk_Rank_Keys!$C$2:$C$800),--(Risk_Rank_Keys!$C$2:$C$800=Risk_Rank_Keys!C127))+1)/2)/COUNT(Risk_Rank_Keys!$C$2:$C$800)) -> 0.5 | O127: =IF(OR(B127="NW",COUNT(Risk_Rank_Keys!D127)=0),0.5,(SUMPRODUCT(--ISNUMBER(Risk_Rank_Keys!$D$2:$D$800),--(Risk_Rank_Keys!$D$2:$D$800<Risk_Rank_Keys!D127))+(SUMPRODUCT(--ISNUMBER(Risk_Rank_Keys!$D$2:$D$800),--(Risk_Rank_Keys!$D$2:$D$800=Risk_Rank_Keys!D127))+1)/2)/COUNT(Risk_Rank_Keys!$D$2:$D$800)) -> 0.5 | P127: =AVERAGE(M127:O127) -> 0.5 | Q127: =0.4*H127+0.4*I127+0.2*P127 -> 0.8534418 | R127: =PERCENTILE($Q$2:$Q$800,0.75) -> 0.66771572 | S127: =OR(Q127>=R127,AND(B127="CW",COUNT(J127:L127)<3)) -> TRUE | T127: 0.40070273 | U127: 12.381458 | V127: 0.8534418 | W127: =Q127-V127 -> 0
A128: 2021-09-23 | B128: NW | C128: -38.827697 | D128: =SUMPRODUCT(Risk_Inputs!B128:AJ128,Risk_Coefs!$B$2:$AJ$2) -> -0.47126171 | E128: =1/(1+EXP(-MAX(-25,MIN(25,D128)))) -> 0.38431766 | F128: =SUMPRODUCT(Risk_Inputs!B128:AJ128,Risk_Coefs!$B$3:$AJ$3) -> 11.614615 | G128: =MAX(0,F128) -> 11.614615 | H128: =(SUMPRODUCT(--ISNUMBER($E$2:$E$800),--($E$2:$E$800<E128))+(SUMPRODUCT(--ISNUMBER($E$2:$E$800),--($E$2:$E$800=E128))+1)/2)/COUNT($E$2:$E$800) -> 0.91239049 | I128: =(SUMPRODUCT(--ISNUMBER($G$2:$G$800),--($G$2:$G$800<G128))+(SUMPRODUCT(--ISNUMBER($G$2:$G$800),--($G$2:$G$800=G128))+1)/2)/COUNT($G$2:$G$800) -> 0.90738423 | M128: =IF(OR(B128="NW",COUNT(Risk_Rank_Keys!B128)=0),0.5,(SUMPRODUCT(--ISNUMBER(Risk_Rank_Keys!$B$2:$B$800),--(Risk_Rank_Keys!$B$2:$B$800<Risk_Rank_Keys!B128))+(SUMPRODUCT(--ISNUMBER(Risk_Rank_Keys!$B$2:$B$800),--(Risk_Rank_Keys!$B$2:$B$800=Risk_Rank_Keys!B128))+1)/2)/COUNT(Risk_Rank_Keys!$B$2:$B$800)) -> 0.5 | N128: =IF(OR(B128="NW",COUNT(Risk_Rank_Keys!C128)=0),0.5,(SUMPRODUCT(--ISNUMBER(Risk_Rank_Keys!$C$2:$C$800),--(Risk_Rank_Keys!$C$2:$C$800<Risk_Rank_Keys!C128))+(SUMPRODUCT(--ISNUMBER(Risk_Rank_Keys!$C$2:$C$800),--(Risk_Rank_Keys!$C$2:$C$800=Risk_Rank_Keys!C128))+1)/2)/COUNT(Risk_Rank_Keys!$C$2:$C$800)) -> 0.5 | O128: =IF(OR(B128="NW",COUNT(Risk_Rank_Keys!D128)=0),0.5,(SUMPRODUCT(--ISNUMBER(Risk_Rank_Keys!$D$2:$D$800),--(Risk_Rank_Keys!$D$2:$D$800<Risk_Rank_Keys!D128))+(SUMPRODUCT(--ISNUMBER(Risk_Rank_Keys!$D$2:$D$800),--(Risk_Rank_Keys!$D$2:$D$800=Risk_Rank_Keys!D128))+1)/2)/COUNT(Risk_Rank_Keys!$D$2:$D$800)) -> 0.5 | P128: =AVERAGE(M128:O128) -> 0.5 | Q128: =0.4*H128+0.4*I128+0.2*P128 -> 0.82790989 | R128: =PERCENTILE($Q$2:$Q$800,0.75) -> 0.66771572 | S128: =OR(Q128>=R128,AND(B128="CW",COUNT(J128:L128)<3)) -> TRUE | T128: 0.38431766 | U128: 11.614615 | V128: 0.82790989 | W128: =Q128-V128 -> 0
A129: 2021-09-24 | B129: CW | C129: 30.738682 | D129: =SUMPRODUCT(Risk_Inputs!B129:AJ129,Risk_Coefs!$B$2:$AJ$2) -> -1.6609121 | E129: =1/(1+EXP(-MAX(-25,MIN(25,D129)))) -> 0.1596396 | F129: =SUMPRODUCT(Risk_Inputs!B129:AJ129,Risk_Coefs!$B$3:$AJ$3) -> 6.6682943 | G129: =MAX(0,F129) -> 6.6682943 | H129: =(SUMPRODUCT(--ISNUMBER($E$2:$E$800),--($E$2:$E$800<E129))+(SUMPRODUCT(--ISNUMBER($E$2:$E$800),--($E$2:$E$800=E129))+1)/2)/COUNT($E$2:$E$800) -> 0.03379224 | I129: =(SUMPRODUCT(--ISNUMBER($G$2:$G$800),--($G$2:$G$800<G129))+(SUMPRODUCT(--ISNUMBER($G$2:$G$800),--($G$2:$G$800=G129))+1)/2)/COUNT($G$2:$G$800) -> 0.37046308 | J129: 69.572118 | K129: 7.9473879 | L129: 0.25935532 | M129: =IF(OR(B129="NW",COUNT(Risk_Rank_Keys!B129)=0),0.5,(SUMPRODUCT(--ISNUMBER(Risk_Rank_Keys!$B$2:$B$800),--(Risk_Rank_Keys!$B$2:$B$800<Risk_Rank_Keys!B129))+(SUMPRODUCT(--ISNUMBER(Risk_Rank_Keys!$B$2:$B$800),--(Risk_Rank_Keys!$B$2:$B$800=Risk_Rank_Keys!B129))+1)/2)/COUNT(Risk_Rank_Keys!$B$2:$B$800)) -> 0.9972106 | N129: =IF(OR(B129="NW",COUNT(Risk_Rank_Keys!C129)=0),0.5,(SUMPRODUCT(--ISNUMBER(Risk_Rank_Keys!$C$2:$C$800),--(Risk_Rank_Keys!$C$2:$C$800<Risk_Rank_Keys!C129))+(SUMPRODUCT(--ISNUMBER(Risk_Rank_Keys!$C$2:$C$800),--(Risk_Rank_Keys!$C$2:$C$800=Risk_Rank_Keys!C129))+1)/2)/COUNT(Risk_Rank_Keys!$C$2:$C$800)) -> 0.82008368 | O129: =IF(OR(B129="NW",COUNT(Risk_Rank_Keys!D129)=0),0.5,(SUMPRODUCT(--ISNUMBER(Risk_Rank_Keys!$D$2:$D$800),--(Risk_Rank_Keys!$D$2:$D$800<Risk_Rank_Keys!D129))+(SUMPRODUCT(--ISNUMBER(Risk_Rank_Keys!$D$2:$D$800),--(Risk_Rank_Keys!$D$2:$D$800=Risk_Rank_Keys!D129))+1)/2)/COUNT(Risk_Rank_Keys!$D$2:$D$800)) -> 0.62761506 | P129: =AVERAGE(M129:O129) -> 0.81496978 | Q129: =0.4*H129+0.4*I129+0.2*P129 -> 0.32469608 | R129: =PERCENTILE($Q$2:$Q$800,0.75) -> 0.66771572 | S129: =OR(Q129>=R129,AND(B129="CW",COUNT(J129:L129)<3)) -> FALSE | T129: 0.1596396 | U129: 6.6682943 | V129: 0.32469608 | W129: =Q129-V129 -> 0
A130: 2021-09-27 | B130: CW | C130: 11.318875 | D130: =SUMPRODUCT(Risk_Inputs!B130:AJ130,Risk_Coefs!$B$2:$AJ$2) -> -0.74896317 | E130: =1/(1+EXP(-MAX(-25,MIN(25,D130)))) -> 0.32104726 | F130: =SUMPRODUCT(Risk_Inputs!B130:AJ130,Risk_Coefs!$B$3:$AJ$3) -> 9.6644525 | G130: =MAX(0,F130) -> 9.6644525 | H130: =(SUMPRODUCT(--ISNUMBER($E$2:$E$800),--($E$2:$E$800<E130))+(SUMPRODUCT(--ISNUMBER($E$2:$E$800),--($E$2:$E$800=E130))+1)/2)/COUNT($E$2:$E$800) -> 0.6795995 | I130: =(SUMPRODUCT(--ISNUMBER($G$2:$G$800),--($G$2:$G$800<G130))+(SUMPRODUCT(--ISNUMBER($G$2:$G$800),--($G$2:$G$800=G130))+1)/2)/COUNT($G$2:$G$800) -> 0.74468085 | J130: 9.0414399 | K130: 1.0542844 | L130: 0.269179 | M130: =IF(OR(B130="NW",COUNT(Risk_Rank_Keys!B130)=0),0.5,(SUMPRODUCT(--ISNUMBER(Risk_Rank_Keys!$B$2:$B$800),--(Risk_Rank_Keys!$B$2:$B$800<Risk_Rank_Keys!B130))+(SUMPRODUCT(--ISNUMBER(Risk_Rank_Keys!$B$2:$B$800),--(Risk_Rank_Keys!$B$2:$B$800=Risk_Rank_Keys!B130))+1)/2)/COUNT(Risk_Rank_Keys!$B$2:$B$800)) -> 0.44769874 | N130: =IF(OR(B130="NW",COUNT(Risk_Rank_Keys!C130)=0),0.5,(SUMPRODUCT(--ISNUMBER(Risk_Rank_Keys!$C$2:$C$800),--(Risk_Rank_Keys!$C$2:$C$800<Risk_Rank_Keys!C130))+(SUMPRODUCT(--ISNUMBER(Risk_Rank_Keys!$C$2:$C$800),--(Risk_Rank_Keys!$C$2:$C$800=Risk_Rank_Keys!C130))+1)/2)/COUNT(Risk_Rank_Keys!$C$2:$C$800)) -> 0.034867503 | O130: =IF(OR(B130="NW",COUNT(Risk_Rank_Keys!D130)=0),0.5,(SUMPRODUCT(--ISNUMBER(Risk_Rank_Keys!$D$2:$D$800),--(Risk_Rank_Keys!$D$2:$D$800<Risk_Rank_Keys!D130))+(SUMPRODUCT(--ISNUMBER(Risk_Rank_Keys!$D$2:$D$800),--(Risk_Rank_Keys!$D$2:$D$800=Risk_Rank_Keys!D130))+1)/2)/COUNT(Risk_Rank_Keys!$D$2:$D$800)) -> 0.66387727 | P130: =AVERAGE(M130:O130) -> 0.38214784 | Q130: =0.4*H130+0.4*I130+0.2*P130 -> 0.64614171 | R130: =PERCENTILE($Q$2:$Q$800,0.75) -> 0.66771572 | S130: =OR(Q130>=R130,AND(B130="CW",COUNT(J130:L130)<3)) -> FALSE | T130: 0.32104726 | U130: 9.6644525 | V130: 0.64614171 | W130: =Q130-V130 -> 0
A131: 2021-09-28 | B131: CW | C131: -46.736179 | D131: =SUMPRODUCT(Risk_Inputs!B131:AJ131,Risk_Coefs!$B$2:$AJ$2) -> -0.96145355 | E131: =1/(1+EXP(-MAX(-25,MIN(25,D131)))) -> 0.27658726 | F131: =SUMPRODUCT(Risk_Inputs!B131:AJ131,Risk_Coefs!$B$3:$AJ$3) -> 7.4033015 | G131: =MAX(0,F131) -> 7.4033015 | H131: =(SUMPRODUCT(--ISNUMBER($E$2:$E$800),--($E$2:$E$800<E131))+(SUMPRODUCT(--ISNUMBER($E$2:$E$800),--($E$2:$E$800=E131))+1)/2)/COUNT($E$2:$E$800) -> 0.44055069 | I131: =(SUMPRODUCT(--ISNUMBER($G$2:$G$800),--($G$2:$G$800<G131))+(SUMPRODUCT(--ISNUMBER($G$2:$G$800),--($G$2:$G$800=G131))+1)/2)/COUNT($G$2:$G$800) -> 0.45807259 | J131: 10.034043 | K131: 2.0207254 | L131: 0.18134715 | M131: =IF(OR(B131="NW",COUNT(Risk_Rank_Keys!B131)=0),0.5,(SUMPRODUCT(--ISNUMBER(Risk_Rank_Keys!$B$2:$B$800),--(Risk_Rank_Keys!$B$2:$B$800<Risk_Rank_Keys!B131))+(SUMPRODUCT(--ISNUMBER(Risk_Rank_Keys!$B$2:$B$800),--(Risk_Rank_Keys!$B$2:$B$800=Risk_Rank_Keys!B131))+1)/2)/COUNT(Risk_Rank_Keys!$B$2:$B$800)) -> 0.50767085 | N131: =IF(OR(B131="NW",COUNT(Risk_Rank_Keys!C131)=0),0.5,(SUMPRODUCT(--ISNUMBER(Risk_Rank_Keys!$C$2:$C$800),--(Risk_Rank_Keys!$C$2:$C$800<Risk_Rank_Keys!C131))+(SUMPRODUCT(--ISNUMBER(Risk_Rank_Keys!$C$2:$C$800),--(Risk_Rank_Keys!$C$2:$C$800=Risk_Rank_Keys!C131))+1)/2)/COUNT(Risk_Rank_Keys!$C$2:$C$800)) -> 0.27475593 | O131: =IF(OR(B131="NW",COUNT(Risk_Rank_Keys!D131)=0),0.5,(SUMPRODUCT(--ISNUMBER(Risk_Rank_Keys!$D$2:$D$800),--(Risk_Rank_Keys!$D$2:$D$800<Risk_Rank_Keys!D131))+(SUMPRODUCT(--ISNUMBER(Risk_Rank_Keys!$D$2:$D$800),--(Risk_Rank_Keys!$D$2:$D$800=Risk_Rank_Keys!D131))+1)/2)/COUNT(Risk_Rank_Keys!$D$2:$D$800)) -> 0.21478382 | P131: =AVERAGE(M131:O131) -> 0.33240353 | Q131: =0.4*H131+0.4*I131+0.2*P131 -> 0.42593002 | R131: =PERCENTILE($Q$2:$Q$800,0.75) -> 0.66771572 | S131: =OR(Q131>=R131,AND(B131="CW",COUNT(J131:L131)<3)) -> FALSE | T131: 0.27658726 | U131: 7.4033015 | V131: 0.42593002 | W131: =Q131-V131 -> 0
A132: 2021-09-29 | B132: CW | C132: 53.890799 | D132: =SUMPRODUCT(Risk_Inputs!B132:AJ132,Risk_Coefs!$B$2:$AJ$2) -> -1.4701236 | E132: =1/(1+EXP(-MAX(-25,MIN(25,D132)))) -> 0.18692384 | F132: =SUMPRODUCT(Risk_Inputs!B132:AJ132,Risk_Coefs!$B$3:$AJ$3) -> 5.0194621 | G132: =MAX(0,F132) -> 5.0194621 | H132: =(SUMPRODUCT(--ISNUMBER($E$2:$E$800),--($E$2:$E$800<E132))+(SUMPRODUCT(--ISNUMBER($E$2:$E$800),--($E$2:$E$800=E132))+1)/2)/COUNT($E$2:$E$800) -> 0.076345432 | I132: =(SUMPRODUCT(--ISNUMBER($G$2:$G$800),--($G$2:$G$800<G132))+(SUMPRODUCT(--ISNUMBER($G$2:$G$800),--($G$2:$G$800=G132))+1)/2)/COUNT($G$2:$G$800) -> 0.13767209 | J132: 28.146418 | K132: 11.673262 | L132: 0.42396834 | M132: =IF(OR(B132="NW",COUNT(Risk_Rank_Keys!B132)=0),0.5,(SUMPRODUCT(--ISNUMBER(Risk_Rank_Keys!$B$2:$B$800),--(Risk_Rank_Keys!$B$2:$B$800<Risk_Rank_Keys!B132))+(SUMPRODUCT(--ISNUMBER(Risk_Rank_Keys!$B$2:$B$800),--(Risk_Rank_Keys!$B$2:$B$800=Risk_Rank_Keys!B132))+1)/2)/COUNT(Risk_Rank_Keys!$B$2:$B$800)) -> 0.89539749 | N132: =IF(OR(B132="NW",COUNT(Risk_Rank_Keys!C132)=0),0.5,(SUMPRODUCT(--ISNUMBER(Risk_Rank_Keys!$C$2:$C$800),--(Risk_Rank_Keys!$C$2:$C$800<Risk_Rank_Keys!C132))+(SUMPRODUCT(--ISNUMBER(Risk_Rank_Keys!$C$2:$C$800),--(Risk_Rank_Keys!$C$2:$C$800=Risk_Rank_Keys!C132))+1)/2)/COUNT(Risk_Rank_Keys!$C$2:$C$800)) -> 0.90237099 | O132: =IF(OR(B132="NW",COUNT(Risk_Rank_Keys!D132)=0),0.5,(SUMPRODUCT(--ISNUMBER(Risk_Rank_Keys!$D$2:$D$800),--(Risk_Rank_Keys!$D$2:$D$800<Risk_Rank_Keys!D132))+(SUMPRODUCT(--ISNUMBER(Risk_Rank_Keys!$D$2:$D$800),--(Risk_Rank_Keys!$D$2:$D$800=Risk_Rank_Keys!D132))+1)/2)/COUNT(Risk_Rank_Keys!$D$2:$D$800)) -> 0.90376569 | P132: =AVERAGE(M132:O132) -> 0.90051139 | Q132: =0.4*H132+0.4*I132+0.2*P132 -> 0.26570929 | R132: =PERCENTILE($Q$2:$Q$800,0.75) -> 0.66771572 | S132: =OR(Q132>=R132,AND(B132="CW",COUNT(J132:L132)<3)) -> FALSE | T132: 0.18692384 | U132: 5.0194621 | V132: 0.26570929 | W132: =Q132-V132 -> 0
A133: 2021-09-30 | B133: CW | C133: 33.3117 | D133: =SUMPRODUCT(Risk_Inputs!B133:AJ133,Risk_Coefs!$B$2:$AJ$2) -> -0.69046179 | E133: =1/(1+EXP(-MAX(-25,MIN(25,D133)))) -> 0.33393035 | F133: =SUMPRODUCT(Risk_Inputs!B133:AJ133,Risk_Coefs!$B$3:$AJ$3) -> 10.06081 | G133: =MAX(0,F133) -> 10.06081 | H133: =(SUMPRODUCT(--ISNUMBER($E$2:$E$800),--($E$2:$E$800<E133))+(SUMPRODUCT(--ISNUMBER($E$2:$E$800),--($E$2:$E$800=E133))+1)/2)/COUNT($E$2:$E$800) -> 0.75469337 | I133: =(SUMPRODUCT(--ISNUMBER($G$2:$G$800),--($G$2:$G$800<G133))+(SUMPRODUCT(--ISNUMBER($G$2:$G$800),--($G$2:$G$800=G133))+1)/2)/COUNT($G$2:$G$800) -> 0.79599499 | J133: 9.5242671 | K133: 4.7486034 | L133: 0.27932961 | M133: =IF(OR(B133="NW",COUNT(Risk_Rank_Keys!B133)=0),0.5,(SUMPRODUCT(--ISNUMBER(Risk_Rank_Keys!$B$2:$B$800),--(Risk_Rank_Keys!$B$2:$B$800<Risk_Rank_Keys!B133))+(SUMPRODUCT(--ISNUMBER(Risk_Rank_Keys!$B$2:$B$800),--(Risk_Rank_Keys!$B$2:$B$800=Risk_Rank_Keys!B133))+1)/2)/COUNT(Risk_Rank_Keys!$B$2:$B$800)) -> 0.47838215 | N133: =IF(OR(B133="NW",COUNT(Risk_Rank_Keys!C133)=0),0.5,(SUMPRODUCT(--ISNUMBER(Risk_Rank_Keys!$C$2:$C$800),--(Risk_Rank_Keys!$C$2:$C$800<Risk_Rank_Keys!C133))+(SUMPRODUCT(--ISNUMBER(Risk_Rank_Keys!$C$2:$C$800),--(Risk_Rank_Keys!$C$2:$C$800=Risk_Rank_Keys!C133))+1)/2)/COUNT(Risk_Rank_Keys!$C$2:$C$800)) -> 0.66806137 | O133: =IF(OR(B133="NW",COUNT(Risk_Rank_Keys!D133)=0),0.5,(SUMPRODUCT(--ISNUMBER(Risk_Rank_Keys!$D$2:$D$800),--(Risk_Rank_Keys!$D$2:$D$800<Risk_Rank_Keys!D133))+(SUMPRODUCT(--ISNUMBER(Risk_Rank_Keys!$D$2:$D$800),--(Risk_Rank_Keys!$D$2:$D$800=Risk_Rank_Keys!D133))+1)/2)/COUNT(Risk_Rank_Keys!$D$2:$D$800)) -> 0.69735007 | P133: =AVERAGE(M133:O133) -> 0.61459786 | Q133: =0.4*H133+0.4*I133+0.2*P133 -> 0.74319492 | R133: =PERCENTILE($Q$2:$Q$800,0.75) -> 0.66771572 | S133: =OR(Q133>=R133,AND(B133="CW",COUNT(J133:L133)<3)) -> TRUE | T133: 0.33393035 | U133: 10.06081 | V133: 0.74319492 | W133: =Q133-V133 -> 0
